Workbook

Sheet 製品標準原価_製品課生産分
I3: 38期実際原価（1個あたり） | O3: 38期実際原価（グラムあたり） | U3: 39期標準原価（1個あたり）
G4: g | M4: 円/個 | S4: 円/個 | Y4: 円/個
G5: 内容量 | I5: 前工程費 | J5: 資材費 | K5: 労務費 | L5: 経費 | M5: 計 | O5: 前工程費 | P5: 資材費 | Q5: 労務費 | R5: 経費 | S5: 計 | U5: 前工程費 | V5: 資材費 | W5: 労務費 | X5: 経費 | Y5: 計
B6: 1 | C6: 20051200013 | D6: MKF-Ⅰ 分包150g(AAAAA) | E6: 製品課 | G6: 150 | H6: 5A | I6: ='4.仕掛品(製品課) _作業用(値)'!E17*'4.仕掛品(製品課) _作業用(値)'!G17 -> 775.8794 | J6: ='4.仕掛品(製品課) _作業用(値)'!U17/'4.仕掛品(製品課) _作業用(値)'!K17 -> 87.543683 | K6: ='4.仕掛品(製品課) _作業用(値)'!W17/'4.仕掛品(製品課) _作業用(値)'!K17 -> 226.12593 | L6: ='4.仕掛品(製品課) _作業用(値)'!AA17/'4.仕掛品(製品課) _作業用(値)'!K17 -> 63.928658 | M6: =SUM(I6:L6) -> 1153.4777 | O6: =I6/$G6 -> 5.1725294 | P6: =J6/$G6 -> 0.58362455 | Q6: =K6/$G6 -> 1.5075062 | R6: =L6/$G6 -> 0.42619105 | S6: =M6/$G6 -> 7.6898512 | U6: =ROUND(I6,-1) -> 780 | V6: =ROUND(J6,-1) -> 90 | W6: =ROUND(K6,-1) -> 230 | X6: =ROUND(L6,-1) -> 60 | Y6: =SUM(U6:X6) -> 1160
B7: 2 | C7: 20071100007 | D7: MKF-Ⅰ携帯ﾊﾟｯｸ 50g(5A) | E7: 製品課 | G7: 50 | H7: 5A | I7: ='4.仕掛品(製品課) _作業用(値)'!E18*'4.仕掛品(製品課) _作業用(値)'!G18 -> 258.62647 | J7: ='4.仕掛品(製品課) _作業用(値)'!U18/'4.仕掛品(製品課) _作業用(値)'!K18 -> 50.414624 | K7: ='4.仕掛品(製品課) _作業用(値)'!W18/'4.仕掛品(製品課) _作業用(値)'!K18 -> 156.87486 | L7: ='4.仕掛品(製品課) _作業用(値)'!AA18/'4.仕掛品(製品課) _作業用(値)'!K18 -> 21.309553 | M7: =SUM(I7:L7) -> 487.22551 | O7: =I7/$G7 -> 5.1725294 | P7: =J7/$G7 -> 1.0082925 | Q7: =K7/$G7 -> 3.1374973 | R7: =L7/$G7 -> 0.42619105 | S7: =M7/$G7 -> 9.7445102 | U7: =ROUND(I7,-1) -> 260 | V7: =ROUND(J7,-1) -> 50 | W7: =ROUND(K7,-1) -> 160 | X7: =ROUND(L7,-1) -> 20 | Y7: =SUM(U7:X7) -> 490
B8: 3 | C8: 20051200005 | D8: 万田HI酵素 分包150g | E8: 製品課 | G8: 150 | H8: B | I8: ='4.仕掛品(製品課) _作業用(値)'!E19*'4.仕掛品(製品課) _作業用(値)'!G19 -> 202.3042 | J8: ='4.仕掛品(製品課) _作業用(値)'!U19/'4.仕掛品(製品課) _作業用(値)'!K19 -> 333.92988 | K8: ='4.仕掛品(製品課) _作業用(値)'!W19/'4.仕掛品(製品課) _作業用(値)'!K19 -> 328.3478 | L8: ='4.仕掛品(製品課) _作業用(値)'!AA19/'4.仕掛品(製品課) _作業用(値)'!K19 -> 63.928658 | M8: =SUM(I8:L8) -> 928.51054 | O8: =I8/$G8 -> 1.3486947 | P8: =J8/$G8 -> 2.2261992 | Q8: =K8/$G8 -> 2.1889854 | R8: =L8/$G8 -> 0.42619105 | S8: =M8/$G8 -> 6.1900703 | U8: =ROUND(I8,-1) -> 200 | V8: =ROUND(J8,-1) -> 330 | W8: =ROUND(K8,-1) -> 330 | X8: =ROUND(L8,-1) -> 60 | Y8: =SUM(U8:X8) -> 920
B9: 4 | C9: 20071000005 | D9: 試供品 HI酵素 5g | E9: 製品課 | G9: 5 | H9: B | I9: ='4.仕掛品(製品課) _作業用(値)'!E20*'4.仕掛品(製品課) _作業用(値)'!G20 -> 6.7434734 | J9: ='4.仕掛品(製品課) _作業用(値)'!U20/'4.仕掛品(製品課) _作業用(値)'!K20 -> 6.1951706 | K9: ='4.仕掛品(製品課) _作業用(値)'!W20/'4.仕掛品(製品課) _作業用(値)'!K20 -> 12.064616 | L9: ='4.仕掛品(製品課) _作業用(値)'!AA20/'4.仕掛品(製品課) _作業用(値)'!K20 -> 2.1309553 | M9: =SUM(I9:L9) -> 27.134215 | O9: =I9/$G9 -> 1.3486947 | P9: =J9/$G9 -> 1.2390341 | Q9: =K9/$G9 -> 2.4129231 | R9: =L9/$G9 -> 0.42619105 | S9: =M9/$G9 -> 5.426843 | U9: =ROUND(I9,-1) -> 10 | V9: =ROUND(J9,-1) -> 10 | W9: =ROUND(K9,-1) -> 10 | X9: =ROUND(L9,-1) -> 0 | Y9: =SUM(U9:X9) -> 30
B10: 5 | C10: 20110800311 | D10: MANDA HI KOHSO | E10: 製品課 | G10: 145 | H10: B | I10: ='4.仕掛品(製品課) _作業用(値)'!E21*'4.仕掛品(製品課) _作業用(値)'!G21 -> 195.56073 | J10: ='4.仕掛品(製品課) _作業用(値)'!U21/'4.仕掛品(製品課) _作業用(値)'!K21 -> 871.73246 | K10: ='4.仕掛品(製品課) _作業用(値)'!W21/'4.仕掛品(製品課) _作業用(値)'!K21 -> 398.45126 | L10: ='4.仕掛品(製品課) _作業用(値)'!AA21/'4.仕掛品(製品課) _作業用(値)'!K21 -> 61.797703 | M10: =SUM(I10:L10) -> 1527.5422 | O10: =I10/$G10 -> 1.3486947 | P10: =J10/$G10 -> 6.011948 | Q10: =K10/$G10 -> 2.7479397 | R10: =L10/$G10 -> 0.42619105 | S10: =M10/$G10 -> 10.534773 | U10: =ROUND(I10,-1) -> 200 | V10: =ROUND(J10,-1) -> 870 | W10: =ROUND(K10,-1) -> 400 | X10: =ROUND(L10,-1) -> 60 | Y10: =SUM(U10:X10) -> 1530
B11: 6 | C11: 20110800629 | D11: 万田HI酵素 145g | E11: 製品課 | G11: 145 | H11: B | I11: ='4.仕掛品(製品課) _作業用(値)'!E22*'4.仕掛品(製品課) _作業用(値)'!G22 -> 195.56073 | J11: ='4.仕掛品(製品課) _作業用(値)'!U22/'4.仕掛品(製品課) _作業用(値)'!K22 -> 292.73446 | K11: ='4.仕掛品(製品課) _作業用(値)'!W22/'4.仕掛品(製品課) _作業用(値)'!K22 -> 292.29949 | L11: ='4.仕掛品(製品課) _作業用(値)'!AA22/'4.仕掛品(製品課) _作業用(値)'!K22 -> 61.797703 | M11: =SUM(I11:L11) -> 842.39238 | O11: =I11/$G11 -> 1.3486947 | P11: =J11/$G11 -> 2.0188584 | Q11: =K11/$G11 -> 2.0158586 | R11: =L11/$G11 -> 0.42619105 | S11: =M11/$G11 -> 5.8096027 | U11: =ROUND(I11,-1) -> 200 | V11: =ROUND(J11,-1) -> 290 | W11: =ROUND(K11,-1) -> 290 | X11: =ROUND(L11,-1) -> 60 | Y11: =SUM(U11:X11) -> 840
B12: 7 | C12: 20200800016 | D12: 万田酵素ｴｸｾﾚﾝﾄ 145g | E12: 製品課 | G12: 145 | H12: BE | I12: ='4.仕掛品(製品課) _作業用(値)'!E23*'4.仕掛品(製品課) _作業用(値)'!G23 -> 245.73753 | J12: ='4.仕掛品(製品課) _作業用(値)'!U23/'4.仕掛品(製品課) _作業用(値)'!K23 -> 995.31872 | K12: ='4.仕掛品(製品課) _作業用(値)'!W23/'4.仕掛品(製品課) _作業用(値)'!K23 -> 1433.2262 | L12: ='4.仕掛品(製品課) _作業用(値)'!AA23/'4.仕掛品(製品課) _作業用(値)'!K23 -> 61.797703 | M12: =SUM(I12:L12) -> 2736.0801 | O12: =I12/$G12 -> 1.6947416 | P12: =J12/$G12 -> 6.8642671 | Q12: =K12/$G12 -> 9.8843185 | R12: =L12/$G12 -> 0.42619105 | S12: =M12/$G12 -> 18.869518 | U12: =ROUND(I12,-1) -> 250 | V12: =ROUND(J12,-1) -> 1000 | W12: =ROUND(K12,-1) -> 1430 | X12: =ROUND(L12,-1) -> 60 | Y12: =SUM(U12:X12) -> 2740
B13: 8 | C13: 20200800017 | D13: 万田酵素ｴｸｾﾚﾝﾄ 分包30g（2.5g×12包） | E13: 製品課 | G13: 30 | H13: BE | I13: ='4.仕掛品(製品課) _作業用(値)'!E24*'4.仕掛品(製品課) _作業用(値)'!G24 -> 50.842248 | J13: ='4.仕掛品(製品課) _作業用(値)'!U24/'4.仕掛品(製品課) _作業用(値)'!K24 -> 94.133199 | K13: ='4.仕掛品(製品課) _作業用(値)'!W24/'4.仕掛品(製品課) _作業用(値)'!K24 -> 141.8846 | L13: ='4.仕掛品(製品課) _作業用(値)'!AA24/'4.仕掛品(製品課) _作業用(値)'!K24 -> 12.785732 | M13: =SUM(I13:L13) -> 299.64578 | O13: =I13/$G13 -> 1.6947416 | P13: =J13/$G13 -> 3.1377733 | Q13: =K13/$G13 -> 4.7294866 | R13: =L13/$G13 -> 0.42619105 | S13: =M13/$G13 -> 9.9881926 | U13: =ROUND(I13,-1) -> 50 | V13: =ROUND(J13,-1) -> 90 | W13: =ROUND(K13,-1) -> 140 | X13: =ROUND(L13,-1) -> 10 | Y13: =SUM(U13:X13) -> 290
B14: 9 | C14: 20200800018 | D14: 万田酵素ｴｸｾﾚﾝﾄ 分包450g | E14: 製品課 | G14: 450 | H14: BE | I14: ='4.仕掛品(製品課) _作業用(値)'!E25*'4.仕掛品(製品課) _作業用(値)'!G25 -> 762.63372 | J14: ='4.仕掛品(製品課) _作業用(値)'!U25/'4.仕掛品(製品課) _作業用(値)'!K25 -> 1267.8189 | K14: ='4.仕掛品(製品課) _作業用(値)'!W25/'4.仕掛品(製品課) _作業用(値)'!K25 -> 1130.3836 | L14: ='4.仕掛品(製品課) _作業用(値)'!AA25/'4.仕掛品(製品課) _作業用(値)'!K25 -> 191.78597 | M14: =SUM(I14:L14) -> 3352.6221 | O14: =I14/$G14 -> 1.6947416 | P14: =J14/$G14 -> 2.8173753 | Q14: =K14/$G14 -> 2.5119635 | R14: =L14/$G14 -> 0.42619105 | S14: =M14/$G14 -> 7.4502714 | U14: =ROUND(I14,-1) -> 760 | V14: =ROUND(J14,-1) -> 1270 | W14: =ROUND(K14,-1) -> 1130 | X14: =ROUND(L14,-1) -> 190 | Y14: =SUM(U14:X14) -> 3350
B15: 10 | C15: 20240100051 | D15: 万田酵素 MANUKA HONEY Premium 分包77.5g | E15: 製品課 | G15: 77.5 | H15: BM | I15: ='4.仕掛品(製品課) _作業用(値)'!E26*'4.仕掛品(製品課) _作業用(値)'!G26 -> 348.76583 | J15: ='4.仕掛品(製品課) _作業用(値)'!U26/'4.仕掛品(製品課) _作業用(値)'!K26 -> 43.109808 | K15: ='4.仕掛品(製品課) _作業用(値)'!W26/'4.仕掛品(製品課) _作業用(値)'!K26 -> 52.433911 | L15: ='4.仕掛品(製品課) _作業用(値)'!AA26/'4.仕掛品(製品課) _作業用(値)'!K26 -> 33.029807 | M15: =SUM(I15:L15) -> 477.33935 | O15: =I15/$G15 -> 4.5002042 | P15: =J15/$G15 -> 0.55625559 | Q15: =K15/$G15 -> 0.6765666 | R15: =L15/$G15 -> 0.42619105 | S15: =M15/$G15 -> 6.1592174 | U15: =ROUND(I15,-1) -> 350 | V15: =ROUND(J15,-1) -> 40 | W15: =ROUND(K15,-1) -> 50 | X15: =ROUND(L15,-1) -> 30 | Y15: =SUM(U15:X15) -> 470
B16: 11 | C16: 20110300008 | D16: Man-Koso CARAT 145g | E16: 製品課 | G16: 145 | H16: C | I16: ='4.仕掛品(製品課) _作業用(値)'!E27*'4.仕掛品(製品課) _作業用(値)'!G27 -> 150.00044 | J16: ='4.仕掛品(製品課) _作業用(値)'!U27/'4.仕掛品(製品課) _作業用(値)'!K27 -> 1404.177 | K16: ='4.仕掛品(製品課) _作業用(値)'!W27/'4.仕掛品(製品課) _作業用(値)'!K27 -> 726.94978 | L16: ='4.仕掛品(製品課) _作業用(値)'!AA27/'4.仕掛品(製品課) _作業用(値)'!K27 -> 61.797703 | M16: =SUM(I16:L16) -> 2342.9249 | O16: =I16/$G16 -> 1.0344858 | P16: =J16/$G16 -> 9.6839791 | Q16: =K16/$G16 -> 5.0134467 | R16: =L16/$G16 -> 0.42619105 | S16: =M16/$G16 -> 16.158103 | U16: =ROUND(I16,-1) -> 150 | V16: =ROUND(J16,-1) -> 1400 | W16: =ROUND(K16,-1) -> 730 | X16: =ROUND(L16,-1) -> 60 | Y16: =SUM(U16:X16) -> 2340
B17: 12 | C17: 20200200001 | D17: 万田酵素超熟分包77.5g | E17: 製品課 | G17: 77.5 | H17: D | I17: ='4.仕掛品(製品課) _作業用(値)'!E28*'4.仕掛品(製品課) _作業用(値)'!G28 -> 104.62214 | J17: ='4.仕掛品(製品課) _作業用(値)'!U28/'4.仕掛品(製品課) _作業用(値)'!K28 -> 162.13702 | K17: ='4.仕掛品(製品課) _作業用(値)'!W28/'4.仕掛品(製品課) _作業用(値)'!K28 -> 91.745649 | L17: ='4.仕掛品(製品課) _作業用(値)'!AA28/'4.仕掛品(製品課) _作業用(値)'!K28 -> 33.029807 | M17: =SUM(I17:L17) -> 391.53462 | O17: =I17/$G17 -> 1.3499631 | P17: =J17/$G17 -> 2.0920906 | Q17: =K17/$G17 -> 1.1838148 | R17: =L17/$G17 -> 0.42619105 | S17: =M17/$G17 -> 5.0520595 | U17: =ROUND(I17,-1) -> 100 | V17: =ROUND(J17,-1) -> 160 | W17: =ROUND(K17,-1) -> 90 | X17: =ROUND(L17,-1) -> 30 | Y17: =SUM(U17:X17) -> 380
... B28: 23 | C28: 20110800295 | D28: 万田酵素 MJ | E28: 製品課 | G28: 90 | H28: G | I28: ='4.仕掛品(製品課) _作業用(値)'!E39*'4.仕掛品(製品課) _作業用(値)'!G39 -> 249.77734 | J28: ='4.仕掛品(製品課) _作業用(値)'!U39/'4.仕掛品(製品課) _作業用(値)'!K39 -> 385.91287 | K28: ='4.仕掛品(製品課) _作業用(値)'!W39/'4.仕掛品(製品課) _作業用(値)'!K39 -> 564.14614 | L28: ='4.仕掛品(製品課) _作業用(値)'!AA39/'4.仕掛品(製品課) _作業用(値)'!K39 -> 38.357195 | M28: =SUM(I28:L28) -> 1238.1936 | O28: =I28/$G28 -> 2.7753038 | P28: =J28/$G28 -> 4.2879208 | Q28: =K28/$G28 -> 6.2682905 | R28: =L28/$G28 -> 0.42619105 | S28: =M28/$G28 -> 13.757706 | U28: =ROUND(I28,-1) -> 250 | V28: =ROUND(J28,-1) -> 390 | W28: =ROUND(K28,-1) -> 560 | X28: =ROUND(L28,-1) -> 40 | Y28: =SUM(U28:X28) -> 1240
B29: 24 | C29: 20231100078 | D29: 発酵しょうが 2.5g 支給用 | E29: 製品課 | G29: 2.5 | H29: GP | I29: ='4.仕掛品(製品課) _作業用(値)'!E40*'4.仕掛品(製品課) _作業用(値)'!G40 -> 3.4869975 | J29: ='4.仕掛品(製品課) _作業用(値)'!U40/'4.仕掛品(製品課) _作業用(値)'!K40 -> 0.34291086 | K29: ='4.仕掛品(製品課) _作業用(値)'!W40/'4.仕掛品(製品課) _作業用(値)'!K40 -> 2.4046883 | L29: ='4.仕掛品(製品課) _作業用(値)'!AA40/'4.仕掛品(製品課) _作業用(値)'!K40 -> 1.0654776 | M29: =SUM(I29:L29) -> 7.3000743 | O29: =I29/$G29 -> 1.394799 | P29: =J29/$G29 -> 0.13716435 | Q29: =K29/$G29 -> 0.96187532 | R29: =L29/$G29 -> 0.42619105 | S29: =M29/$G29 -> 2.9200297 | U29: =ROUNDUP(I29,-1) -> 10 | V29: =ROUND(J29,-1) -> 0 | W29: =ROUND(K29,-1) -> 0 | X29: =ROUND(L29,-1) -> 0 | Y29: =SUM(U29:X29) -> 10
B30: 25 | C30: 20230600044 | D30: 万田酵素 ﾌﾟﾗｽ温 発酵しょうが 77.5g | E30: 製品課 | G30: 77.5 | H30: GP | I30: ='4.仕掛品(製品課) _作業用(値)'!E41*'4.仕掛品(製品課) _作業用(値)'!G41 -> 108.09692 | J30: ='4.仕掛品(製品課) _作業用(値)'!U41/'4.仕掛品(製品課) _作業用(値)'!K41 -> 26.631968 | K30: ='4.仕掛品(製品課) _作業用(値)'!W41/'4.仕掛品(製品課) _作業用(値)'!K41 -> 26.385847 | L30: ='4.仕掛品(製品課) _作業用(値)'!AA41/'4.仕掛品(製品課) _作業用(値)'!K41 -> 33.029807 | M30: =SUM(I30:L30) -> 194.14454 | O30: =I30/$G30 -> 1.394799 | P30: =J30/$G30 -> 0.34363829 | Q30: =K30/$G30 -> 0.34046254 | R30: =L30/$G30 -> 0.42619105 | S30: =M30/$G30 -> 2.5050909 | U30: =ROUND(I30,-1) -> 110 | V30: =ROUND(J30,-1) -> 30 | W30: =ROUND(K30,-1) -> 30 | X30: =ROUND(L30,-1) -> 30 | Y30: =SUM(U30:X30) -> 200
B31: 26 | C31: 20230600045 | D31: 万田酵素 ﾌﾟﾗｽ温 発酵しょうが 20g | E31: 製品課 | G31: 20 | H31: GP | I31: ='4.仕掛品(製品課) _作業用(値)'!E42*'4.仕掛品(製品課) _作業用(値)'!G42 -> 27.89598 | J31: ='4.仕掛品(製品課) _作業用(値)'!U42/'4.仕掛品(製品課) _作業用(値)'!K42 -> 25.076167 | K31: ='4.仕掛品(製品課) _作業用(値)'!W42/'4.仕掛品(製品課) _作業用(値)'!K42 -> 26.324217 | L31: ='4.仕掛品(製品課) _作業用(値)'!AA42/'4.仕掛品(製品課) _作業用(値)'!K42 -> 8.5238211 | M31: =SUM(I31:L31) -> 87.820185 | O31: =I31/$G31 -> 1.394799 | P31: =J31/$G31 -> 1.2538083 | Q31: =K31/$G31 -> 1.3162109 | R31: =L31/$G31 -> 0.42619105 | S31: =M31/$G31 -> 4.3910093 | U31: =ROUND(I31,-1) -> 30 | V31: =ROUND(J31,-1) -> 30 | W31: =ROUND(K31,-1) -> 30 | X31: =ROUND(L31,-1) -> 10 | Y31: =SUM(U31:X31) -> 100
B32: 27 | C32: 20230600046 | D32: 試供品 ﾌﾟﾗｽ温発酵しょうが 2.5g | E32: 製品課 | G32: 2.5 | H32: GP | I32: ='4.仕掛品(製品課) _作業用(値)'!E43*'4.仕掛品(製品課) _作業用(値)'!G43 -> 3.4869975 | J32: ='4.仕掛品(製品課) _作業用(値)'!U43/'4.仕掛品(製品課) _作業用(値)'!K43 -> 4.0551279 | K32: ='4.仕掛品(製品課) _作業用(値)'!W43/'4.仕掛品(製品課) _作業用(値)'!K43 -> 10.665764 | L32: ='4.仕掛品(製品課) _作業用(値)'!AA43/'4.仕掛品(製品課) _作業用(値)'!K43 -> 1.0654776 | M32: =SUM(I32:L32) -> 19.273367 | O32: =I32/$G32 -> 1.394799 | P32: =J32/$G32 -> 1.6220511 | Q32: =K32/$G32 -> 4.2663056 | R32: =L32/$G32 -> 0.42619105 | S32: =M32/$G32 -> 7.7093469 | U32: =ROUND(I32,-1) -> 0 | V32: =ROUND(J32,-1) -> 0 | W32: =ROUND(K32,-1) -> 10 | X32: =ROUND(L32,-1) -> 0 | Y32: =SUM(U32:X32) -> 10
B33: 28 | C33: 20241200012 | D33: 万田酵素ﾌﾟﾗｽ温発酵しょうが 75g 5g×15包 | E33: 製品課 | G33: 75 | H33: GP | I33: ='4.仕掛品(製品課) _作業用(値)'!E44*'4.仕掛品(製品課) _作業用(値)'!G44 -> 104.60993 | J33: ='4.仕掛品(製品課) _作業用(値)'!U44/'4.仕掛品(製品課) _作業用(値)'!K44 -> 529.95559 | K33: ='4.仕掛品(製品課) _作業用(値)'!W44/'4.仕掛品(製品課) _作業用(値)'!K44 -> 356.62886 | L33: ='4.仕掛品(製品課) _作業用(値)'!AA44/'4.仕掛品(製品課) _作業用(値)'!K44 -> 31.964329 | M33: =SUM(I33:L33) -> 1023.1587 | O33: =I33/$G33 -> 1.394799 | P33: =J33/$G33 -> 7.0660745 | Q33: =K33/$G33 -> 4.7550514 | R33: =L33/$G33 -> 0.42619105 | S33: =M33/$G33 -> 13.642116 | U33: =ROUND(I33,-1) -> 100 | V33: =ROUND(J33,-1) -> 530 | W33: =ROUND(K33,-1) -> 360 | X33: =ROUND(L33,-1) -> 30 | Y33: =SUM(U33:X33) -> 1020
B34: 29 | C34: 20231200033 | D34: 万田酵素分包75g （中国虹越） | E34: 製品課 | G34: 75 | H34: KOL | I34: ='4.仕掛品(製品課) _作業用(値)'!E45*'4.仕掛品(製品課) _作業用(値)'!G45 -> 97.501712 | J34: ='4.仕掛品(製品課) _作業用(値)'!U45/'4.仕掛品(製品課) _作業用(値)'!K45 -> 109.79819 | K34: ='4.仕掛品(製品課) _作業用(値)'!W45/'4.仕掛品(製品課) _作業用(値)'!K45 -> 421.81908 | L34: ='4.仕掛品(製品課) _作業用(値)'!AA45/'4.仕掛品(製品課) _作業用(値)'!K45 -> 31.964329 | M34: =SUM(I34:L34) -> 661.08331 | O34: =I34/$G34 -> 1.3000228 | P34: =J34/$G34 -> 1.4639759 | Q34: =K34/$G34 -> 5.6242544 | R34: =L34/$G34 -> 0.42619105 | S34: =M34/$G34 -> 8.8144441 | U34: =ROUND(I34,-1) -> 100 | V34: =ROUND(J34,-1) -> 110 | W34: =ROUND(K34,-1) -> 420 | X34: =ROUND(L34,-1) -> 30 | Y34: =SUM(U34:X34) -> 660
B35: 30 | C35: 20241100041 | D35: 試供品 万田酵素分包5g(中国虹越) | E35: 製品課 | G35: 5 | H35: KOL | I35: ='4.仕掛品(製品課) _作業用(値)'!E46*'4.仕掛品(製品課) _作業用(値)'!G46 -> 6.5001142 | J35: ='4.仕掛品(製品課) _作業用(値)'!U46/'4.仕掛品(製品課) _作業用(値)'!K46 -> 1153.1739 | K35: ='4.仕掛品(製品課) _作業用(値)'!W46/'4.仕掛品(製品課) _作業用(値)'!K46 -> 11.446636 | L35: ='4.仕掛品(製品課) _作業用(値)'!AA46/'4.仕掛品(製品課) _作業用(値)'!K46 -> 2.1309553 | M35: =SUM(I35:L35) -> 1173.2516 | O35: =I35/$G35 -> 1.3000228 | P35: =J35/$G35 -> 230.63478 | Q35: =K35/$G35 -> 2.2893272 | R35: =L35/$G35 -> 0.42619105 | S35: =M35/$G35 -> 234.65032 | U35: =ROUND(I35,-1) -> 10 | V35: =ROUND(J35,-1) -> 1150 | W35: =ROUND(K35,-1) -> 10 | X35: =ROUND(L35,-1) -> 0 | Y35: =SUM(U35:X35) -> 1170
B36: 31 | C36: 20250300087 | D36: 万田酵素 分包150g (中国) | E36: 製品課 | G36: 150 | H36: KOL | I36: ='4.仕掛品(製品課) _作業用(値)'!E47*'4.仕掛品(製品課) _作業用(値)'!G47 -> 195.00342 | J36: ='4.仕掛品(製品課) _作業用(値)'!U47/'4.仕掛品(製品課) _作業用(値)'!K47 -> 77.183908 | K36: ='4.仕掛品(製品課) _作業用(値)'!W47/'4.仕掛品(製品課) _作業用(値)'!K47 -> 288.58999 | L36: ='4.仕掛品(製品課) _作業用(値)'!AA47/'4.仕掛品(製品課) _作業用(値)'!K47 -> 63.928658 | M36: =SUM(I36:L36) -> 624.70598 | O36: =I36/$G36 -> 1.3000228 | P36: =J36/$G36 -> 0.51455939 | Q36: =K36/$G36 -> 1.9239332 | R36: =L36/$G36 -> 0.42619105 | S36: =M36/$G36 -> 4.1647065 | U36: =ROUND(I36,-1) -> 200 | V36: =ROUND(J36,-1) -> 80 | W36: =ROUND(K36,-1) -> 290 | X36: =ROUND(L36,-1) -> 60 | Y36: =SUM(U36:X36) -> 630
B37: 32 | C37: 20171000004 | D37: 万田酵素 MULBERRY 分包 77.5g | E37: 製品課 | G37: 77.5 | H37: MP | I37: ='4.仕掛品(製品課) _作業用(値)'!E48*'4.仕掛品(製品課) _作業用(値)'!G48 -> 91.436421 | J37: ='4.仕掛品(製品課) _作業用(値)'!U48/'4.仕掛品(製品課) _作業用(値)'!K48 -> 28.536968 | K37: ='4.仕掛品(製品課) _作業用(値)'!W48/'4.仕掛品(製品課) _作業用(値)'!K48 -> 26.252289 | L37: ='4.仕掛品(製品課) _作業用(値)'!AA48/'4.仕掛品(製品課) _作業用(値)'!K48 -> 33.029807 | M37: =SUM(I37:L37) -> 179.25548 | O37: =I37/$G37 -> 1.1798248 | P37: =J37/$G37 -> 0.36821894 | Q37: =K37/$G37 -> 0.33873922 | R37: =L37/$G37 -> 0.42619105 | S37: =M37/$G37 -> 2.312974 | U37: =ROUND(I37,-1) -> 90 | V37: =ROUND(J37,-1) -> 30 | W37: =ROUND(K37,-1) -> 30 | X37: =ROUND(L37,-1) -> 30 | Y37: =SUM(U37:X37) -> 180
B38: 33 | C38: 20171000006 | D38: 万田酵素 MULBERRY 分包20g | E38: 製品課 | G38: 20 | H38: MP | I38: ='4.仕掛品(製品課) _作業用(値)'!E49*'4.仕掛品(製品課) _作業用(値)'!G49 -> 23.596496 | J38: ='4.仕掛品(製品課) _作業用(値)'!U49/'4.仕掛品(製品課) _作業用(値)'!K49 -> 20.949852 | K38: ='4.仕掛品(製品課) _作業用(値)'!W49/'4.仕掛品(製品課) _作業用(値)'!K49 -> 45.729023 | L38: ='4.仕掛品(製品課) _作業用(値)'!AA49/'4.仕掛品(製品課) _作業用(値)'!K49 -> 8.5238211 | M38: =SUM(I38:L38) -> 98.799191 | O38: =I38/$G38 -> 1.1798248 | P38: =J38/$G38 -> 1.0474926 | Q38: =K38/$G38 -> 2.2864511 | R38: =L38/$G38 -> 0.42619105 | S38: =M38/$G38 -> 4.9399596 | U38: =ROUND(I38,-1) -> 20 | V38: =ROUND(J38,-1) -> 20 | W38: =ROUND(K38,-1) -> 50 | X38: =ROUND(L38,-1) -> 10 | Y38: =SUM(U38:X38) -> 100
B39: 34 | C39: 20171000010 | D39: 万田酵素 MULBERRY ﾁｭｰﾌﾞﾀｲﾌﾟ 26×3本 | E39: 製品課 | G39: 78 | H39: MP | I39: ='4.仕掛品(製品課) _作業用(値)'!E50*'4.仕掛品(製品課) _作業用(値)'!G50 -> 92.026333 | J39: ='4.仕掛品(製品課) _作業用(値)'!U50/'4.仕掛品(製品課) _作業用(値)'!K50 -> 295.50293 | K39: ='4.仕掛品(製品課) _作業用(値)'!W50/'4.仕掛品(製品課) _作業用(値)'!K50 -> 412.79621 | L39: ='4.仕掛品(製品課) _作業用(値)'!AA50/'4.仕掛品(製品課) _作業用(値)'!K50 -> 33.242902 | M39: =SUM(I39:L39) -> 833.56838 | O39: =I39/$G39 -> 1.1798248 | P39: =J39/$G39 -> 3.7884992 | Q39: =K39/$G39 -> 5.2922591 | R39: =L39/$G39 -> 0.42619105 | S39: =M39/$G39 -> 10.686774 | U39: =ROUND(I39,-1) -> 90 | V39: =ROUND(J39,-1) -> 300 | W39: =ROUND(K39,-1) -> 410 | X39: =ROUND(L39,-1) -> 30 | Y39: =SUM(U39:X39) -> 830
B40: 35 | C40: 20181100045 | D40: 万田酵素 MULBERRY 分包35g 2.5g×14包 | E40: 製品課 | G40: 35 | H40: MP | I40: ='4.仕掛品(製品課) _作業用(値)'!E51*'4.仕掛品(製品課) _作業用(値)'!G51 -> 41.293867 | J40: ='4.仕掛品(製品課) _作業用(値)'!U51/'4.仕掛品(製品課) _作業用(値)'!K51 -> 35.144766 | K40: ='4.仕掛品(製品課) _作業用(値)'!W51/'4.仕掛品(製品課) _作業用(値)'!K51 -> 74.777018 | L40: ='4.仕掛品(製品課) _作業用(値)'!AA51/'4.仕掛品(製品課) _作業用(値)'!K51 -> 14.916687 | M40: =SUM(I40:L40) -> 166.13234 | O40: =I40/$G40 -> 1.1798248 | P40: =J40/$G40 -> 1.0041362 | Q40: =K40/$G40 -> 2.1364862 | R40: =L40/$G40 -> 0.42619105 | S40: =M40/$G40 -> 4.7466382 | U40: =ROUND(I40,-1) -> 40 | V40: =ROUND(J40,-1) -> 40 | W40: =ROUND(K40,-1) -> 70 | X40: =ROUND(L40,-1) -> 10 | Y40: =SUM(U40:X40) -> 160
B41: 36 | C41: 20200200034 | D41: 万田酵素MULBERRY 分包 10g 2.5×4包 | E41: 製品課 | G41: 10 | H41: MP | I41: ='4.仕掛品(製品課) _作業用(値)'!E52*'4.仕掛品(製品課) _作業用(値)'!G52 -> 11.798248 | J41: ='4.仕掛品(製品課) _作業用(値)'!U52/'4.仕掛品(製品課) _作業用(値)'!K52 -> 127.57041 | K41: ='4.仕掛品(製品課) _作業用(値)'!W52/'4.仕掛品(製品課) _作業用(値)'!K52 -> 97.398944 | L41: ='4.仕掛品(製品課) _作業用(値)'!AA52/'4.仕掛品(製品課) _作業用(値)'!K52 -> 4.2619105 | M41: =SUM(I41:L41) -> 241.02951 | O41: =I41/$G41 -> 1.1798248 | P41: =J41/$G41 -> 12.757041 | Q41: =K41/$G41 -> 9.7398944 | R41: =L41/$G41 -> 0.42619105 | S41: =M41/$G41 -> 24.102951 | U41: =ROUND(I41,-1) -> 10 | V41: =ROUND(J41,-1) -> 130 | W41: =ROUND(K41,-1) -> 100 | X41: =ROUND(L41,-1) -> 0 | Y41: =SUM(U41:X41) -> 240
B42: 37 | C42: 20220100027 | D42: MULBERRY 2.5g 支給用 | E42: 製品課 | G42: 2.5 | H42: MP | I42: ='4.仕掛品(製品課) _作業用(値)'!E53*'4.仕掛品(製品課) _作業用(値)'!G53 -> 2.949562 | J42: ='4.仕掛品(製品課) _作業用(値)'!U53/'4.仕掛品(製品課) _作業用(値)'!K53 -> 0.35676342 | K42: ='4.仕掛品(製品課) _作業用(値)'!W53/'4.仕掛品(製品課) _作業用(値)'!K53 -> 2.5382187 | L42: ='4.仕掛品(製品課) _作業用(値)'!AA53/'4.仕掛品(製品課) _作業用(値)'!K53 -> 1.0654776 | M42: =SUM(I42:L42) -> 6.9100217 | O42: =I42/$G42 -> 1.1798248 | P42: =J42/$G42 -> 0.14270537 | Q42: =K42/$G42 -> 1.0152875 | R42: =L42/$G42 -> 0.42619105 | S42: =M42/$G42 -> 2.7640087 | U42: =ROUNDUP(I42,-1) -> 10 | V42: =ROUND(J42,-1) -> 0 | W42: =ROUND(K42,-1) -> 0 | X42: =ROUND(L42,-1) -> 0 | Y42: =SUM(U42:X42) -> 10
B43: 38 | C43: 20230900058 | D43: 万田酵素 MULBERRY 分包12.5g | E43: 製品課 | G43: 12.5 | H43: MP | I43: ='4.仕掛品(製品課) _作業用(値)'!E54*'4.仕掛品(製品課) _作業用(値)'!G54 -> 14.74781 | J43: ='4.仕掛品(製品課) _作業用(値)'!U54/'4.仕掛品(製品課) _作業用(値)'!K54 -> 13.116578 | K43: ='4.仕掛品(製品課) _作業用(値)'!W54/'4.仕掛品(製品課) _作業用(値)'!K54 -> 30.294279 | L43: ='4.仕掛品(製品課) _作業用(値)'!AA54/'4.仕掛品(製品課) _作業用(値)'!K54 -> 5.3273882 | M43: =SUM(I43:L43) -> 63.486055 | O43: =I43/$G43 -> 1.1798248 | P43: =J43/$G43 -> 1.0493262 | Q43: =K43/$G43 -> 2.4235423 | R43: =L43/$G43 -> 0.42619105 | S43: =M43/$G43 -> 5.0788844 | U43: =ROUND(I43,-1) -> 10 | V43: =ROUND(J43,-1) -> 10 | W43: =ROUND(K43,-1) -> 30 | X43: =ROUND(L43,-1) -> 10 | Y43: =SUM(U43:X43) -> 60
B44: 39 | C44: 20060200007 | D44: 万田酵素 金印145g | E44: 製品課 | G44: 145 | H44: O | I44: ='4.仕掛品(製品課) _作業用(値)'!E55*'4.仕掛品(製品課) _作業用(値)'!G55 -> 191.80757 | J44: ='4.仕掛品(製品課) _作業用(値)'!U55/'4.仕掛品(製品課) _作業用(値)'!K55 -> 711.19074 | K44: ='4.仕掛品(製品課) _作業用(値)'!W55/'4.仕掛品(製品課) _作業用(値)'!K55 -> 425.01468 | L44: ='4.仕掛品(製品課) _作業用(値)'!AA55/'4.仕掛品(製品課) _作業用(値)'!K55 -> 61.797703 | M44: =SUM(I44:L44) -> 1389.8107 | O44: =I44/$G44 -> 1.3228108 | P44: =J44/$G44 -> 4.9047637 | Q44: =K44/$G44 -> 2.9311357 | R44: =L44/$G44 -> 0.42619105 | S44: =M44/$G44 -> 9.5849013 | U44: =ROUND(I44,-1) -> 190 | V44: =ROUND(J44,-1) -> 710 | W44: =ROUND(K44,-1) -> 430 | X44: =ROUND(L44,-1) -> 60 | Y44: =SUM(U44:X44) -> 1390
B45: 40 | C45: 20071000014 | D45: 試供品 金印 5g | E45: 製品課 | G45: 5 | H45: O | I45: ='4.仕掛品(製品課) _作業用(値)'!E56*'4.仕掛品(製品課) _作業用(値)'!G56 -> 6.6140541 | J45: ='4.仕掛品(製品課) _作業用(値)'!U56/'4.仕掛品(製品課) _作業用(値)'!K56 -> 8.2544451 | K45: ='4.仕掛品(製品課) _作業用(値)'!W56/'4.仕掛品(製品課) _作業用(値)'!K56 -> 14.060636 | L45: ='4.仕掛品(製品課) _作業用(値)'!AA56/'4.仕掛品(製品課) _作業用(値)'!K56 -> 2.1309553 | M45: =SUM(I45:L45) -> 31.06009 | O45: =I45/$G45 -> 1.3228108 | P45: =J45/$G45 -> 1.650889 | Q45: =K45/$G45 -> 2.8121272 | R45: =L45/$G45 -> 0.42619105 | S45: =M45/$G45 -> 6.2120181 | U45: =ROUND(I45,-1) -> 10 | V45: =ROUND(J45,-1) -> 10 | W45: =ROUND(K45,-1) -> 10 | X45: =ROUND(L45,-1) -> 0 | Y45: =SUM(U45:X45) -> 30
B46: 41 | C46: 20071100028 | D46: 万田酵素 金印 分包150g | E46: 製品課 | G46: 150 | H46: O | I46: ='4.仕掛品(製品課) _作業用(値)'!E57*'4.仕掛品(製品課) _作業用(値)'!G57 -> 198.42162 | J46: ='4.仕掛品(製品課) _作業用(値)'!U57/'4.仕掛品(製品課) _作業用(値)'!K57 -> 255.58587 | K46: ='4.仕掛品(製品課) _作業用(値)'!W57/'4.仕掛品(製品課) _作業用(値)'!K57 -> 281.21272 | L46: ='4.仕掛品(製品課) _作業用(値)'!AA57/'4.仕掛品(製品課) _作業用(値)'!K57 -> 63.928658 | M46: =SUM(I46:L46) -> 799.14887 | O46: =I46/$G46 -> 1.3228108 | P46: =J46/$G46 -> 1.7039058 | Q46: =K46/$G46 -> 1.8747515 | R46: =L46/$G46 -> 0.42619105 | S46: =M46/$G46 -> 5.3276592 | U46: =ROUND(I46,-1) -> 200 | V46: =ROUND(J46,-1) -> 260 | W46: =ROUND(K46,-1) -> 280 | X46: =ROUND(L46,-1) -> 60 | Y46: =SUM(U46:X46) -> 800
B47: 42 | C47: 20110800312 | D47: MANDA KOHSO GOLD 145ｇ | E47: 製品課 | G47: 145 | H47: O | I47: ='4.仕掛品(製品課) _作業用(値)'!E58*'4.仕掛品(製品課) _作業用(値)'!G58 -> 191.80757 | J47: ='4.仕掛品(製品課) _作業用(値)'!U58/'4.仕掛品(製品課) _作業用(値)'!K58 -> 1588.7743 | K47: ='4.仕掛品(製品課) _作業用(値)'!W58/'4.仕掛品(製品課) _作業用(値)'!K58 -> 623.14182 | L47: ='4.仕掛品(製品課) _作業用(値)'!AA58/'4.仕掛品(製品課) _作業用(値)'!K58 -> 61.797703 | M47: =SUM(I47:L47) -> 2465.5214 | O47: =I47/$G47 -> 1.3228108 | P47: =J47/$G47 -> 10.957064 | Q47: =K47/$G47 -> 4.2975298 | R47: =L47/$G47 -> 0.42619105 | S47: =M47/$G47 -> 17.003596 | U47: =ROUND(I47,-1) -> 190 | V47: =ROUND(J47,-1) -> 1590 | W47: =ROUND(K47,-1) -> 620 | X47: =ROUND(L47,-1) -> 60 | Y47: =SUM(U47:X47) -> 2460
B48: 43 | C48: 20140100011 | D48: Man-Koso GOLD 145g | E48: 製品課 | G48: 145 | H48: O | I48: ='4.仕掛品(製品課) _作業用(値)'!E59*'4.仕掛品(製品課) _作業用(値)'!G59 -> 191.80757 | J48: ='4.仕掛品(製品課) _作業用(値)'!U59/'4.仕掛品(製品課) _作業用(値)'!K59 -> 1984.4659 | K48: ='4.仕掛品(製品課) _作業用(値)'!W59/'4.仕掛品(製品課) _作業用(値)'!K59 -> 419.278 | L48: ='4.仕掛品(製品課) _作業用(値)'!AA59/'4.仕掛品(製品課) _作業用(値)'!K59 -> 61.797703 | M48: =SUM(I48:L48) -> 2657.3491 | O48: =I48/$G48 -> 1.3228108 | P48: =J48/$G48 -> 13.685971 | Q48: =K48/$G48 -> 2.8915724 | R48: =L48/$G48 -> 0.42619105 | S48: =M48/$G48 -> 18.326546 | U48: =ROUND(I48,-1) -> 190 | V48: =ROUND(J48,-1) -> 1980 | W48: =ROUND(K48,-1) -> 420 | X48: =ROUND(L48,-1) -> 60 | Y48: =SUM(U48:X48) -> 2650
B49: 44 | C49: 20061200012 | D49: 万田酵素 145g(販売店向け) | E49: 製品課 | G49: 145 | H49: P | I49: ='4.仕掛品(製品課) _作業用(値)'!E60*'4.仕掛品(製品課) _作業用(値)'!G60 -> 183.52784 | J49: ='4.仕掛品(製品課) _作業用(値)'!U60/'4.仕掛品(製品課) _作業用(値)'!K60 -> 178.38354 | K49: ='4.仕掛品(製品課) _作業用(値)'!W60/'4.仕掛品(製品課) _作業用(値)'!K60 -> 272.14884 | L49: ='4.仕掛品(製品課) _作業用(値)'!AA60/'4.仕掛品(製品課) _作業用(値)'!K60 -> 61.797703 | M49: =SUM(I49:L49) -> 695.85792 | O49: =I49/$G49 -> 1.2657092 | P49: =J49/$G49 -> 1.2302313 | Q49: =K49/$G49 -> 1.8768885 | R49: =L49/$G49 -> 0.42619105 | S49: =M49/$G49 -> 4.7990201 | U49: =ROUND(I49,-1) -> 180 | V49: =ROUND(J49,-1) -> 180 | W49: =ROUND(K49,-1) -> 270 | X49: =ROUND(L49,-1) -> 60 | Y49: =SUM(U49:X49) -> 690
B50: 45 | C50: 20070300033 | D50: 万田酵素 分包150g(販売店向け) | E50: 製品課 | G50: 150 | H50: P | I50: ='4.仕掛品(製品課) _作業用(値)'!E61*'4.仕掛品(製品課) _作業用(値)'!G61 -> 189.85638 | J50: ='4.仕掛品(製品課) _作業用(値)'!U61/'4.仕掛品(製品課) _作業用(値)'!K61 -> 84.105232 | K50: ='4.仕掛品(製品課) _作業用(値)'!W61/'4.仕掛品(製品課) _作業用(値)'!K61 -> 242.79606 | L50: ='4.仕掛品(製品課) _作業用(値)'!AA61/'4.仕掛品(製品課) _作業用(値)'!K61 -> 63.928658 | M50: =SUM(I50:L50) -> 580.68633 | O50: =I50/$G50 -> 1.2657092 | P50: =J50/$G50 -> 0.56070155 | Q50: =K50/$G50 -> 1.6186404 | R50: =L50/$G50 -> 0.42619105 | S50: =M50/$G50 -> 3.8712422 | U50: =ROUND(I50,-1) -> 190 | V50: =ROUND(J50,-1) -> 80 | W50: =ROUND(K50,-1) -> 240 | X50: =ROUND(L50,-1) -> 60 | Y50: =SUM(U50:X50) -> 570
B51: 46 | C51: 20080100023 | D51: 試供品 万田酵素 5g(販売店向け) | E51: 製品課 | G51: 5 | H51: P | I51: ='4.仕掛品(製品課) _作業用(値)'!E62*'4.仕掛品(製品課) _作業用(値)'!G62 -> 6.3285461 | J51: ='4.仕掛品(製品課) _作業用(値)'!U62/'4.仕掛品(製品課) _作業用(値)'!K62 -> 2.8439627 | K51: ='4.仕掛品(製品課) _作業用(値)'!W62/'4.仕掛品(製品課) _作業用(値)'!K62 -> 12.13219 | L51: ='4.仕掛品(製品課) _作業用(値)'!AA62/'4.仕掛品(製品課) _作業用(値)'!K62 -> 2.1309553 | M51: =SUM(I51:L51) -> 23.435654 | O51: =I51/$G51 -> 1.2657092 | P51: =J51/$G51 -> 0.56879254 | Q51: =K51/$G51 -> 2.4264379 | R51: =L51/$G51 -> 0.42619105 | S51: =M51/$G51 -> 4.6871308 | U51: =ROUND(I51,-1) -> 10 | V51: =ROUND(J51,-1) -> 0 | W51: =ROUND(K51,-1) -> 10 | X51: =ROUND(L51,-1) -> 0 | Y51: =SUM(U51:X51) -> 20
B52: 47 | C52: 20090100014 | D52: 万田酵素 300g(販売店限定品) | E52: 製品課 | G52: 300 | H52: P | I52: ='4.仕掛品(製品課) _作業用(値)'!E63*'4.仕掛品(製品課) _作業用(値)'!G63 -> 379.71277 | J52: ='4.仕掛品(製品課) _作業用(値)'!U63/'4.仕掛品(製品課) _作業用(値)'!K63 -> 736.16942 | K52: ='4.仕掛品(製品課) _作業用(値)'!W63/'4.仕掛品(製品課) _作業用(値)'!K63 -> 835.02393 | L52: ='4.仕掛品(製品課) _作業用(値)'!AA63/'4.仕掛品(製品課) _作業用(値)'!K63 -> 127.85732 | M52: =SUM(I52:L52) -> 2078.7634 | O52: =I52/$G52 -> 1.2657092 | P52: =J52/$G52 -> 2.4538981 | Q52: =K52/$G52 -> 2.7834131 | R52: =L52/$G52 -> 0.42619105 | S52: =M52/$G52 -> 6.9292115 | U52: =ROUND(I52,-1) -> 380 | V52: =ROUND(J52,-1) -> 740 | W52: =ROUND(K52,-1) -> 840 | X52: =ROUND(L52,-1) -> 130 | Y52: =SUM(U52:X52) -> 2090
B53: 48 | C53: 20090300004 | D53: 万田酵素 分包50g | E53: 製品課 | G53: 50 | H53: P | I53: ='4.仕掛品(製品課) _作業用(値)'!E64*'4.仕掛品(製品課) _作業用(値)'!G64 -> 63.285461 | J53: ='4.仕掛品(製品課) _作業用(値)'!U64/'4.仕掛品(製品課) _作業用(値)'!K64 -> 317.81488 | K53: ='4.仕掛品(製品課) _作業用(値)'!W64/'4.仕掛品(製品課) _作業用(値)'!K64 -> 209.37565 | L53: ='4.仕掛品(製品課) _作業用(値)'!AA64/'4.仕掛品(製品課) _作業用(値)'!K64 -> 21.309553 | M53: =SUM(I53:L53) -> 611.78555 | O53: =I53/$G53 -> 1.2657092 | P53: =J53/$G53 -> 6.3562976 | Q53: =K53/$G53 -> 4.187513 | R53: =L53/$G53 -> 0.42619105 | S53: =M53/$G53 -> 12.235711 | U53: =ROUND(I53,-1) -> 60 | V53: =ROUND(J53,-1) -> 320 | W53: =ROUND(K53,-1) -> 210 | X53: =ROUND(L53,-1) -> 20 | Y53: =SUM(U53:X53) -> 610
B54: 49 | C54: 20110300007 | D54: Man-Koso PREMIUM 145g | E54: 製品課 | G54: 145 | H54: P | I54: ='4.仕掛品(製品課) _作業用(値)'!E65*'4.仕掛品(製品課) _作業用(値)'!G65 -> 183.52784 | J54: ='4.仕掛品(製品課) _作業用(値)'!U65/'4.仕掛品(製品課) _作業用(値)'!K65 -> 504.49201 | K54: ='4.仕掛品(製品課) _作業用(値)'!W65/'4.仕掛品(製品課) _作業用(値)'!K65 -> 239.17488 | L54: ='4.仕掛品(製品課) _作業用(値)'!AA65/'4.仕掛品(製品課) _作業用(値)'!K65 -> 61.797703 | M54: =SUM(I54:L54) -> 988.99243 | O54: =I54/$G54 -> 1.2657092 | P54: =J54/$G54 -> 3.4792553 | Q54: =K54/$G54 -> 1.6494819 | R54: =L54/$G54 -> 0.42619105 | S54: =M54/$G54 -> 6.8206375 | U54: =ROUND(I54,-1) -> 180 | V54: =ROUND(J54,-1) -> 500 | W54: =ROUND(K54,-1) -> 240 | X54: =ROUND(L54,-1) -> 60 | Y54: =SUM(U54:X54) -> 980
... B62: 57 | C62: 20240400020 | D62: 万田酵素(宇宙用) 2.5g×8包 通信販売用 | E62: 製品課 | G62: 20 | H62: P | I62: ='4.仕掛品(製品課) _作業用(値)'!E73*'4.仕掛品(製品課) _作業用(値)'!G73 -> 25.314184 | J62: ='4.仕掛品(製品課) _作業用(値)'!U73/'4.仕掛品(製品課) _作業用(値)'!K73 -> 132.40799 | K62: ='4.仕掛品(製品課) _作業用(値)'!W73/'4.仕掛品(製品課) _作業用(値)'!K73 -> 131.72259 | L62: ='4.仕掛品(製品課) _作業用(値)'!AA73/'4.仕掛品(製品課) _作業用(値)'!K73 -> 8.5238211 | M62: =SUM(I62:L62) -> 297.96859 | O62: =I62/$G62 -> 1.2657092 | P62: =J62/$G62 -> 6.6203997 | Q62: =K62/$G62 -> 6.5861297 | R62: =L62/$G62 -> 0.42619105 | S62: =M62/$G62 -> 14.89843 | U62: =ROUND(I62,-1) -> 30 | V62: =ROUND(J62,-1) -> 130 | W62: =ROUND(K62,-1) -> 130 | X62: =ROUND(L62,-1) -> 10 | Y62: =SUM(U62:X62) -> 300
B63: 58 | C63: 20170400004 | D63: 試供品 万田酵素 GINGER 2.5g | E63: 製品課 | G63: 2.5 | H63: PE | I63: ='4.仕掛品(製品課) _作業用(値)'!E74*'4.仕掛品(製品課) _作業用(値)'!G74 -> 2.8748334 | J63: ='4.仕掛品(製品課) _作業用(値)'!U74/'4.仕掛品(製品課) _作業用(値)'!K74 -> 2.1396659 | K63: ='4.仕掛品(製品課) _作業用(値)'!W74/'4.仕掛品(製品課) _作業用(値)'!K74 -> 10.825092 | L63: ='4.仕掛品(製品課) _作業用(値)'!AA74/'4.仕掛品(製品課) _作業用(値)'!K74 -> 1.0654776 | M63: =SUM(I63:L63) -> 16.905069 | O63: =I63/$G63 -> 1.1499334 | P63: =J63/$G63 -> 0.85586635 | Q63: =K63/$G63 -> 4.3300367 | R63: =L63/$G63 -> 0.42619105 | S63: =M63/$G63 -> 6.7620275 | U63: =ROUNDUP(I63,-1) -> 10 | V63: =ROUND(J63,-1) -> 0 | W63: =ROUND(K63,-1) -> 10 | X63: =ROUND(L63,-1) -> 0 | Y63: =SUM(U63:X63) -> 20
B64: 59 | C64: 20170400005 | D64: 万田酵素 GINGER 分包20g | E64: 製品課 | G64: 20 | H64: PE | I64: ='4.仕掛品(製品課) _作業用(値)'!E75*'4.仕掛品(製品課) _作業用(値)'!G75 -> 22.998667 | J64: ='4.仕掛品(製品課) _作業用(値)'!U75/'4.仕掛品(製品課) _作業用(値)'!K75 -> 21.005571 | K64: ='4.仕掛品(製品課) _作業用(値)'!W75/'4.仕掛品(製品課) _作業用(値)'!K75 -> 19.988472 | L64: ='4.仕掛品(製品課) _作業用(値)'!AA75/'4.仕掛品(製品課) _作業用(値)'!K75 -> 8.5238211 | M64: =SUM(I64:L64) -> 72.516531 | O64: =I64/$G64 -> 1.1499334 | P64: =J64/$G64 -> 1.0502785 | Q64: =K64/$G64 -> 0.99942361 | R64: =L64/$G64 -> 0.42619105 | S64: =M64/$G64 -> 3.6258265 | U64: =ROUND(I64,-1) -> 20 | V64: =ROUND(J64,-1) -> 20 | W64: =ROUND(K64,-1) -> 20 | X64: =ROUND(L64,-1) -> 10 | Y64: =SUM(U64:X64) -> 70
B65: 60 | C65: 20170400006 | D65: 万田酵素GINGER分包77.5g | E65: 製品課 | G65: 77.5 | H65: PE | I65: ='4.仕掛品(製品課) _作業用(値)'!E76*'4.仕掛品(製品課) _作業用(値)'!G76 -> 89.119835 | J65: ='4.仕掛品(製品課) _作業用(値)'!U76/'4.仕掛品(製品課) _作業用(値)'!K76 -> 24.058593 | K65: ='4.仕掛品(製品課) _作業用(値)'!W76/'4.仕掛品(製品課) _作業用(値)'!K76 -> 26.544158 | L65: ='4.仕掛品(製品課) _作業用(値)'!AA76/'4.仕掛品(製品課) _作業用(値)'!K76 -> 33.029807 | M65: =SUM(I65:L65) -> 172.75239 | O65: =I65/$G65 -> 1.1499334 | P65: =J65/$G65 -> 0.31043345 | Q65: =K65/$G65 -> 0.34250526 | R65: =L65/$G65 -> 0.42619105 | S65: =M65/$G65 -> 2.2290631 | U65: =ROUND(I65,-1) -> 90 | V65: =ROUND(J65,-1) -> 20 | W65: =ROUND(K65,-1) -> 30 | X65: =ROUND(L65,-1) -> 30 | Y65: =SUM(U65:X65) -> 170
B66: 61 | C66: 20170400017 | D66: 万田酵素 GINGER 分包 35g | E66: 製品課 | G66: 35 | H66: PE | I66: ='4.仕掛品(製品課) _作業用(値)'!E77*'4.仕掛品(製品課) _作業用(値)'!G77 -> 40.247667 | J66: ='4.仕掛品(製品課) _作業用(値)'!U77/'4.仕掛品(製品課) _作業用(値)'!K77 -> 44.31097 | K66: ='4.仕掛品(製品課) _作業用(値)'!W77/'4.仕掛品(製品課) _作業用(値)'!K77 -> 80.529097 | L66: ='4.仕掛品(製品課) _作業用(値)'!AA77/'4.仕掛品(製品課) _作業用(値)'!K77 -> 14.916687 | M66: =SUM(I66:L66) -> 180.00442 | O66: =I66/$G66 -> 1.1499334 | P66: =J66/$G66 -> 1.2660277 | Q66: =K66/$G66 -> 2.3008313 | R66: =L66/$G66 -> 0.42619105 | S66: =M66/$G66 -> 5.1429834 | U66: =ROUND(I66,-1) -> 40 | V66: =ROUND(J66,-1) -> 40 | W66: =ROUND(K66,-1) -> 80 | X66: =ROUND(L66,-1) -> 10 | Y66: =SUM(U66:X66) -> 170
B67: 62 | C67: 20171000009 | D67: 万田酵素GINGERﾁｭｰﾌﾞﾀｲﾌﾟ26×3本 | E67: 製品課 | G67: 78 | H67: PE | I67: ='4.仕掛品(製品課) _作業用(値)'!E78*'4.仕掛品(製品課) _作業用(値)'!G78 -> 89.694801 | J67: ='4.仕掛品(製品課) _作業用(値)'!U78/'4.仕掛品(製品課) _作業用(値)'!K78 -> 295.50254 | K67: ='4.仕掛品(製品課) _作業用(値)'!W78/'4.仕掛品(製品課) _作業用(値)'!K78 -> 348.95942 | L67: ='4.仕掛品(製品課) _作業用(値)'!AA78/'4.仕掛品(製品課) _作業用(値)'!K78 -> 33.242902 | M67: =SUM(I67:L67) -> 767.39966 | O67: =I67/$G67 -> 1.1499334 | P67: =J67/$G67 -> 3.7884941 | Q67: =K67/$G67 -> 4.4738387 | R67: =L67/$G67 -> 0.42619105 | S67: =M67/$G67 -> 9.8384572 | U67: =ROUND(I67,-1) -> 90 | V67: =ROUND(J67,-1) -> 300 | W67: =ROUND(K67,-1) -> 350 | X67: =ROUND(L67,-1) -> 30 | Y67: =SUM(U67:X67) -> 770
B68: 63 | C68: 20181100042 | D68: 万田酵素 GINGER2.5g×4包 | E68: 製品課 | G68: 10 | H68: PE | I68: ='4.仕掛品(製品課) _作業用(値)'!E79*'4.仕掛品(製品課) _作業用(値)'!G79 -> 11.499334 | J68: ='4.仕掛品(製品課) _作業用(値)'!U79/'4.仕掛品(製品課) _作業用(値)'!K79 -> 49.498076 | K68: ='4.仕掛品(製品課) _作業用(値)'!W79/'4.仕掛品(製品課) _作業用(値)'!K79 -> 120.15453 | L68: ='4.仕掛品(製品課) _作業用(値)'!AA79/'4.仕掛品(製品課) _作業用(値)'!K79 -> 4.2619105 | M68: =SUM(I68:L68) -> 185.41384 | O68: =I68/$G68 -> 1.1499334 | P68: =J68/$G68 -> 4.9498076 | Q68: =K68/$G68 -> 12.015453 | R68: =L68/$G68 -> 0.42619105 | S68: =M68/$G68 -> 18.541384 | U68: =ROUND(I68,-1) -> 10 | V68: =ROUND(J68,-1) -> 50 | W68: =ROUND(K68,-1) -> 120 | X68: =ROUND(L68,-1) -> 0 | Y68: =SUM(U68:X68) -> 180
B69: 64 | C69: 20190100014 | D69: 万田酵素GINGER分包50ｇ | E69: 製品課 | G69: 50 | H69: PE | I69: ='4.仕掛品(製品課) _作業用(値)'!E80*'4.仕掛品(製品課) _作業用(値)'!G80 -> 57.496668 | J69: ='4.仕掛品(製品課) _作業用(値)'!U80/'4.仕掛品(製品課) _作業用(値)'!K80 -> 33.973875 | K69: ='4.仕掛品(製品課) _作業用(値)'!W80/'4.仕掛品(製品課) _作業用(値)'!K80 -> 33.745526 | L69: ='4.仕掛品(製品課) _作業用(値)'!AA80/'4.仕掛品(製品課) _作業用(値)'!K80 -> 21.309553 | M69: =SUM(I69:L69) -> 146.52562 | O69: =I69/$G69 -> 1.1499334 | P69: =J69/$G69 -> 0.67947749 | Q69: =K69/$G69 -> 0.67491052 | R69: =L69/$G69 -> 0.42619105 | S69: =M69/$G69 -> 2.9305124 | U69: =ROUND(I69,-1) -> 60 | V69: =ROUND(J69,-1) -> 30 | W69: =ROUND(K69,-1) -> 30 | X69: =ROUND(L69,-1) -> 20 | Y69: =SUM(U69:X69) -> 140
B70: 65 | C70: 20220100028 | D70: GINGER 2.5g 支給用 | E70: 製品課 | G70: 2.5 | H70: PE | I70: ='4.仕掛品(製品課) _作業用(値)'!E81*'4.仕掛品(製品課) _作業用(値)'!G81 -> 2.8748334 | J70: ='4.仕掛品(製品課) _作業用(値)'!U81/'4.仕掛品(製品課) _作業用(値)'!K81 -> 0.36773077 | K70: ='4.仕掛品(製品課) _作業用(値)'!W81/'4.仕掛品(製品課) _作業用(値)'!K81 -> 2.452477 | L70: ='4.仕掛品(製品課) _作業用(値)'!AA81/'4.仕掛品(製品課) _作業用(値)'!K81 -> 1.0654776 | M70: =SUM(I70:L70) -> 6.7605188 | O70: =I70/$G70 -> 1.1499334 | P70: =J70/$G70 -> 0.14709231 | Q70: =K70/$G70 -> 0.98099081 | R70: =L70/$G70 -> 0.42619105 | S70: =M70/$G70 -> 2.7042075 | U70: =ROUND(I70,-1) -> 0 | V70: =ROUND(J70,-1) -> 0 | W70: =ROUND(K70,-1) -> 0 | X70: =ROUND(L70,-1) -> 0 | Y70: =SUM(U70:X70) -> 0
B71: 66 | C71: 20050700013 | D71: 万田酵素 ｊ 分包150g | E71: 製品課 | G71: 150 | H71: PG | I71: ='4.仕掛品(製品課) _作業用(値)'!E82*'4.仕掛品(製品課) _作業用(値)'!G82 -> 224.59947 | J71: ='4.仕掛品(製品課) _作業用(値)'!U82/'4.仕掛品(製品課) _作業用(値)'!K82 -> 331.09776 | K71: ='4.仕掛品(製品課) _作業用(値)'!W82/'4.仕掛品(製品課) _作業用(値)'!K82 -> 348.95942 | L71: ='4.仕掛品(製品課) _作業用(値)'!AA82/'4.仕掛品(製品課) _作業用(値)'!K82 -> 63.928658 | M71: =SUM(I71:L71) -> 968.58531 | O71: =I71/$G71 -> 1.4973298 | P71: =J71/$G71 -> 2.2073184 | Q71: =K71/$G71 -> 2.3263961 | R71: =L71/$G71 -> 0.42619105 | S71: =M71/$G71 -> 6.4572354 | U71: =ROUND(I71,-1) -> 220 | V71: =ROUND(J71,-1) -> 330 | W71: =ROUND(K71,-1) -> 350 | X71: =ROUND(L71,-1) -> 60 | Y71: =SUM(U71:X71) -> 960
B72: 67 | C72: 20080300003 | D72: 試供品 万田酵素 ｊ 5g | E72: 製品課 | G72: 5 | H72: PG | I72: ='4.仕掛品(製品課) _作業用(値)'!E83*'4.仕掛品(製品課) _作業用(値)'!G83 -> 7.4866489 | J72: ='4.仕掛品(製品課) _作業用(値)'!U83/'4.仕掛品(製品課) _作業用(値)'!K83 -> 10.396847 | K72: ='4.仕掛品(製品課) _作業用(値)'!W83/'4.仕掛品(製品課) _作業用(値)'!K83 -> 40.921929 | L72: ='4.仕掛品(製品課) _作業用(値)'!AA83/'4.仕掛品(製品課) _作業用(値)'!K83 -> 2.1309553 | M72: =SUM(I72:L72) -> 60.93638 | O72: =I72/$G72 -> 1.4973298 | P72: =J72/$G72 -> 2.0793694 | Q72: =K72/$G72 -> 8.1843857 | R72: =L72/$G72 -> 0.42619105 | S72: =M72/$G72 -> 12.187276 | U72: =ROUND(I72,-1) -> 10 | V72: =ROUND(J72,-1) -> 10 | W72: =ROUND(K72,-1) -> 40 | X72: =ROUND(L72,-1) -> 0 | Y72: =SUM(U72:X72) -> 60
B73: 68 | C73: 20091200010 | D73: MANDA CARE PLUS 75g(梅) | E73: 製品課 | G73: 75 | H73: PG | I73: ='4.仕掛品(製品課) _作業用(値)'!E84*'4.仕掛品(製品課) _作業用(値)'!G84 -> 112.29973 | J73: ='4.仕掛品(製品課) _作業用(値)'!U84/'4.仕掛品(製品課) _作業用(値)'!K84 -> 113.65312 | K73: ='4.仕掛品(製品課) _作業用(値)'!W84/'4.仕掛品(製品課) _作業用(値)'!K84 -> 165.89327 | L73: ='4.仕掛品(製品課) _作業用(値)'!AA84/'4.仕掛品(製品課) _作業用(値)'!K84 -> 31.964329 | M73: =SUM(I73:L73) -> 423.81045 | O73: =I73/$G73 -> 1.4973298 | P73: =J73/$G73 -> 1.5153749 | Q73: =K73/$G73 -> 2.2119103 | R73: =L73/$G73 -> 0.42619105 | S73: =M73/$G73 -> 5.650806 | U73: =ROUND(I73,-1) -> 110 | V73: =ROUND(J73,-1) -> 110 | W73: =ROUND(K73,-1) -> 170 | X73: =ROUND(L73,-1) -> 30 | Y73: =SUM(U73:X73) -> 420
B74: 69 | C74: 20091200011 | D74: MANDA CARE PLUS 5g(梅) | E74: 製品課 | G74: 5 | H74: PG | I74: ='4.仕掛品(製品課) _作業用(値)'!E85*'4.仕掛品(製品課) _作業用(値)'!G85 -> 7.4866489 | J74: ='4.仕掛品(製品課) _作業用(値)'!U85/'4.仕掛品(製品課) _作業用(値)'!K85 -> 21.742178 | K74: ='4.仕掛品(製品課) _作業用(値)'!W85/'4.仕掛品(製品課) _作業用(値)'!K85 -> 121.43276 | L74: ='4.仕掛品(製品課) _作業用(値)'!AA85/'4.仕掛品(製品課) _作業用(値)'!K85 -> 2.1309553 | M74: =SUM(I74:L74) -> 152.79255 | O74: =I74/$G74 -> 1.4973298 | P74: =J74/$G74 -> 4.3484357 | Q74: =K74/$G74 -> 24.286553 | R74: =L74/$G74 -> 0.42619105 | S74: =M74/$G74 -> 30.558509 | U74: =ROUND(I74,-1) -> 10 | V74: =ROUND(J74,-1) -> 20 | W74: =ROUND(K74,-1) -> 120 | X74: =ROUND(L74,-1) -> 0 | Y74: =SUM(U74:X74) -> 150
B75: 70 | C75: 20221100028 | D75: 万田酵素 j 分包50ｇ | E75: 製品課 | G75: 50 | H75: PG | I75: ='4.仕掛品(製品課) _作業用(値)'!E86*'4.仕掛品(製品課) _作業用(値)'!G86 -> 74.866489 | J75: ='4.仕掛品(製品課) _作業用(値)'!U86/'4.仕掛品(製品課) _作業用(値)'!K86 -> 126.6824 | K75: ='4.仕掛品(製品課) _作業用(値)'!W86/'4.仕掛品(製品課) _作業用(値)'!K86 -> 201.32274 | L75: ='4.仕掛品(製品課) _作業用(値)'!AA86/'4.仕掛品(製品課) _作業用(値)'!K86 -> 21.309553 | M75: =SUM(I75:L75) -> 424.18118 | O75: =I75/$G75 -> 1.4973298 | P75: =J75/$G75 -> 2.533648 | Q75: =K75/$G75 -> 4.0264548 | R75: =L75/$G75 -> 0.42619105 | S75: =M75/$G75 -> 8.4836236 | U75: =ROUND(I75,-1) -> 70 | V75: =ROUND(J75,-1) -> 130 | W75: =ROUND(K75,-1) -> 200 | X75: =ROUND(L75,-1) -> 20 | Y75: =SUM(U75:X75) -> 420
... B80: 75 | C80: 20240600040 | D80: NONI酵素 分包14g 2g×7包 | E80: 製品課 | G80: 14 | H80: PSA | I80: ='4.仕掛品(製品課) _作業用(値)'!E91*'4.仕掛品(製品課) _作業用(値)'!G91 -> 25.10913 | J80: ='4.仕掛品(製品課) _作業用(値)'!U91/'4.仕掛品(製品課) _作業用(値)'!K91 -> 89.703612 | K80: ='4.仕掛品(製品課) _作業用(値)'!W91/'4.仕掛品(製品課) _作業用(値)'!K91 -> 97.497728 | L80: ='4.仕掛品(製品課) _作業用(値)'!AA91/'4.仕掛品(製品課) _作業用(値)'!K91 -> 5.9666748 | M80: =SUM(I80:L80) -> 218.27714 | O80: =I80/$G80 -> 1.7935093 | P80: =J80/$G80 -> 6.4074009 | Q80: =K80/$G80 -> 6.9641234 | R80: =L80/$G80 -> 0.42619105 | S80: =M80/$G80 -> 15.591225 | U80: =ROUND(I80,-1) -> 30 | V80: =ROUND(J80,-1) -> 90 | W80: =ROUND(K80,-1) -> 100 | X80: =ROUND(L80,-1) -> 10 | Y80: =SUM(U80:X80) -> 230
B81: 76 | C81: 20170400007 | D81: 試供品 万田酵素 STANDARD 2.5g | E81: 製品課 | G81: 2.5 | H81: PX | I81: ='4.仕掛品(製品課) _作業用(値)'!E92*'4.仕掛品(製品課) _作業用(値)'!G92 -> 3.1326284 | J81: ='4.仕掛品(製品課) _作業用(値)'!U92/'4.仕掛品(製品課) _作業用(値)'!K92 -> 2.3313888 | K81: ='4.仕掛品(製品課) _作業用(値)'!W92/'4.仕掛品(製品課) _作業用(値)'!K92 -> 11.097544 | L81: ='4.仕掛品(製品課) _作業用(値)'!AA92/'4.仕掛品(製品課) _作業用(値)'!K92 -> 1.0654776 | M81: =SUM(I81:L81) -> 17.627039 | O81: =I81/$G81 -> 1.2530514 | P81: =J81/$G81 -> 0.93255551 | Q81: =K81/$G81 -> 4.4390177 | R81: =L81/$G81 -> 0.42619105 | S81: =M81/$G81 -> 7.0508156 | U81: =ROUNDUP(I81,-1) -> 10 | V81: =ROUND(J81,-1) -> 0 | W81: =ROUND(K81,-1) -> 10 | X81: =ROUND(L81,-1) -> 0 | Y81: =SUM(U81:X81) -> 20
B82: 77 | C82: 20170400008 | D82: 万田酵素 STANDARD 分包20g | E82: 製品課 | G82: 20 | H82: PX | I82: ='4.仕掛品(製品課) _作業用(値)'!E93*'4.仕掛品(製品課) _作業用(値)'!G93 -> 25.061028 | J82: ='4.仕掛品(製品課) _作業用(値)'!U93/'4.仕掛品(製品課) _作業用(値)'!K93 -> 21.202984 | K82: ='4.仕掛品(製品課) _作業用(値)'!W93/'4.仕掛品(製品課) _作業用(値)'!K93 -> 28.185184 | L82: ='4.仕掛品(製品課) _作業用(値)'!AA93/'4.仕掛品(製品課) _作業用(値)'!K93 -> 8.5238211 | M82: =SUM(I82:L82) -> 82.973016 | O82: =I82/$G82 -> 1.2530514 | P82: =J82/$G82 -> 1.0601492 | Q82: =K82/$G82 -> 1.4092592 | R82: =L82/$G82 -> 0.42619105 | S82: =M82/$G82 -> 4.1486508 | U82: =ROUND(I82,-1) -> 30 | V82: =ROUND(J82,-1) -> 20 | W82: =ROUND(K82,-1) -> 30 | X82: =ROUND(L82,-1) -> 10 | Y82: =SUM(U82:X82) -> 90
B83: 78 | C83: 20170400009 | D83: 万田酵素STANDARD分包77.5g | E83: 製品課 | G83: 77.5 | H83: PX | I83: ='4.仕掛品(製品課) _作業用(値)'!E94*'4.仕掛品(製品課) _作業用(値)'!G94 -> 97.111482 | J83: ='4.仕掛品(製品課) _作業用(値)'!U94/'4.仕掛品(製品課) _作業用(値)'!K94 -> 28.836831 | K83: ='4.仕掛品(製品課) _作業用(値)'!W94/'4.仕掛品(製品課) _作業用(値)'!K94 -> 44.907684 | L83: ='4.仕掛品(製品課) _作業用(値)'!AA94/'4.仕掛品(製品課) _作業用(値)'!K94 -> 33.029807 | M83: =SUM(I83:L83) -> 203.8858 | O83: =I83/$G83 -> 1.2530514 | P83: =J83/$G83 -> 0.37208814 | Q83: =K83/$G83 -> 0.57945398 | R83: =L83/$G83 -> 0.42619105 | S83: =M83/$G83 -> 2.6307846 | U83: =ROUND(I83,-1) -> 100 | V83: =ROUND(J83,-1) -> 30 | W83: =ROUND(K83,-1) -> 40 | X83: =ROUND(L83,-1) -> 30 | Y83: =SUM(U83:X83) -> 200
B84: 79 | C84: 20170400016 | D84: 万田酵素 STANDARD 分包35g | E84: 製品課 | G84: 35 | H84: PX | I84: ='4.仕掛品(製品課) _作業用(値)'!E95*'4.仕掛品(製品課) _作業用(値)'!G95 -> 43.856798 | J84: ='4.仕掛品(製品課) _作業用(値)'!U95/'4.仕掛品(製品課) _作業用(値)'!K95 -> 227.03239 | K84: ='4.仕掛品(製品課) _作業用(値)'!W95/'4.仕掛品(製品課) _作業用(値)'!K95 -> 80.529097 | L84: ='4.仕掛品(製品課) _作業用(値)'!AA95/'4.仕掛品(製品課) _作業用(値)'!K95 -> 14.916687 | M84: =SUM(I84:L84) -> 366.33497 | O84: =I84/$G84 -> 1.2530514 | P84: =J84/$G84 -> 6.4866396 | Q84: =K84/$G84 -> 2.3008313 | R84: =L84/$G84 -> 0.42619105 | S84: =M84/$G84 -> 10.466713 | U84: =ROUND(I84,-1) -> 40 | V84: =ROUND(J84,-1) -> 230 | W84: =ROUND(K84,-1) -> 80 | X84: =ROUND(L84,-1) -> 10 | Y84: =SUM(U84:X84) -> 360
B85: 80 | C85: 20171000008 | D85: 万田酵素STANDARDﾁｭｰﾌﾞﾀｲﾌﾟ26×3本 | E85: 製品課 | G85: 78 | H85: PX | I85: ='4.仕掛品(製品課) _作業用(値)'!E96*'4.仕掛品(製品課) _作業用(値)'!G96 -> 97.738007 | J85: ='4.仕掛品(製品課) _作業用(値)'!U96/'4.仕掛品(製品課) _作業用(値)'!K96 -> 295.50293 | K85: ='4.仕掛品(製品課) _作業用(値)'!W96/'4.仕掛品(製品課) _作業用(値)'!K96 -> 377.33634 | L85: ='4.仕掛品(製品課) _作業用(値)'!AA96/'4.仕掛品(製品課) _作業用(値)'!K96 -> 33.242902 | M85: =SUM(I85:L85) -> 803.82018 | O85: =I85/$G85 -> 1.2530514 | P85: =J85/$G85 -> 3.7884992 | Q85: =K85/$G85 -> 4.8376454 | R85: =L85/$G85 -> 0.42619105 | S85: =M85/$G85 -> 10.305387 | U85: =ROUND(I85,-1) -> 100 | V85: =ROUND(J85,-1) -> 300 | W85: =ROUND(K85,-1) -> 380 | X85: =ROUND(L85,-1) -> 30 | Y85: =SUM(U85:X85) -> 810
B86: 81 | C86: 20180500084 | D86: 万田酵素 STANDARD 分包50g | E86: 製品課 | G86: 50 | H86: PX | I86: ='4.仕掛品(製品課) _作業用(値)'!E97*'4.仕掛品(製品課) _作業用(値)'!G97 -> 62.652569 | J86: ='4.仕掛品(製品課) _作業用(値)'!U97/'4.仕掛品(製品課) _作業用(値)'!K97 -> 36.676071 | K86: ='4.仕掛品(製品課) _作業用(値)'!W97/'4.仕掛品(製品課) _作業用(値)'!K97 -> 35.637877 | L86: ='4.仕掛品(製品課) _作業用(値)'!AA97/'4.仕掛品(製品課) _作業用(値)'!K97 -> 21.309553 | M86: =SUM(I86:L86) -> 156.27607 | O86: =I86/$G86 -> 1.2530514 | P86: =J86/$G86 -> 0.73352143 | Q86: =K86/$G86 -> 0.71275753 | R86: =L86/$G86 -> 0.42619105 | S86: =M86/$G86 -> 3.1255214 | U86: =ROUND(I86,-1) -> 60 | V86: =ROUND(J86,-1) -> 40 | W86: =ROUND(K86,-1) -> 40 | X86: =ROUND(L86,-1) -> 20 | Y86: =SUM(U86:X86) -> 160
B87: 82 | C87: 20181100040 | D87: 万田酵素 STANDARD2.5g×4包 | E87: 製品課 | G87: 10 | H87: PX | I87: ='4.仕掛品(製品課) _作業用(値)'!E98*'4.仕掛品(製品課) _作業用(値)'!G98 -> 12.530514 | J87: ='4.仕掛品(製品課) _作業用(値)'!U98/'4.仕掛品(製品課) _作業用(値)'!K98 -> 49.494006 | K87: ='4.仕掛品(製品課) _作業用(値)'!W98/'4.仕掛品(製品課) _作業用(値)'!K98 -> 147.63668 | L87: ='4.仕掛品(製品課) _作業用(値)'!AA98/'4.仕掛品(製品課) _作業用(値)'!K98 -> 4.2619105 | M87: =SUM(I87:L87) -> 213.92311 | O87: =I87/$G87 -> 1.2530514 | P87: =J87/$G87 -> 4.9494006 | Q87: =K87/$G87 -> 14.763668 | R87: =L87/$G87 -> 0.42619105 | S87: =M87/$G87 -> 21.392311 | U87: =ROUND(I87,-1) -> 10 | V87: =ROUND(J87,-1) -> 50 | W87: =ROUND(K87,-1) -> 150 | X87: =ROUND(L87,-1) -> 0 | Y87: =SUM(U87:X87) -> 210
B88: 83 | C88: 20191200078 | D88: MANDA WELLNESS SUPERFOOD 31×2.5 | E88: 製品課 | G88: 77.5 | H88: PX | I88: ='4.仕掛品(製品課) _作業用(値)'!E99*'4.仕掛品(製品課) _作業用(値)'!G99 -> 97.111482 | J88: ='4.仕掛品(製品課) _作業用(値)'!U99/'4.仕掛品(製品課) _作業用(値)'!K99 -> 426.35793 | K88: ='4.仕掛品(製品課) _作業用(値)'!W99/'4.仕掛品(製品課) _作業用(値)'!K99 -> 285.68656 | L88: ='4.仕掛品(製品課) _作業用(値)'!AA99/'4.仕掛品(製品課) _作業用(値)'!K99 -> 33.029807 | M88: =SUM(I88:L88) -> 842.18577 | O88: =I88/$G88 -> 1.2530514 | P88: =J88/$G88 -> 5.5013926 | Q88: =K88/$G88 -> 3.6862782 | R88: =L88/$G88 -> 0.42619105 | S88: =M88/$G88 -> 10.866913 | U88: =ROUND(I88,-1) -> 100 | V88: =ROUND(J88,-1) -> 430 | W88: =ROUND(K88,-1) -> 290 | X88: =ROUND(L88,-1) -> 30 | Y88: =SUM(U88:X88) -> 850
B89: 84 | C89: 20201100053 | D89: 万田酵素MANUKA HONEY 分包77.5g | E89: 製品課 | G89: 77.5 | H89: PXM | I89: ='4.仕掛品(製品課) _作業用(値)'!E100*'4.仕掛品(製品課) _作業用(値)'!G100 -> 310.62953 | J89: ='4.仕掛品(製品課) _作業用(値)'!U100/'4.仕掛品(製品課) _作業用(値)'!K100 -> 80.970101 | K89: ='4.仕掛品(製品課) _作業用(値)'!W100/'4.仕掛品(製品課) _作業用(値)'!K100 -> 58.398219 | L89: ='4.仕掛品(製品課) _作業用(値)'!AA100/'4.仕掛品(製品課) _作業用(値)'!K100 -> 33.029807 | M89: =SUM(I89:L89) -> 483.02765 | O89: =I89/$G89 -> 4.0081229 | P89: =J89/$G89 -> 1.0447755 | Q89: =K89/$G89 -> 0.75352541 | R89: =L89/$G89 -> 0.42619105 | S89: =M89/$G89 -> 6.2326149 | U89: =ROUND(I89,-1) -> 310 | V89: =ROUND(J89,-1) -> 80 | W89: =ROUND(K89,-1) -> 60 | X89: =ROUND(L89,-1) -> 30 | Y89: =SUM(U89:X89) -> 480
B90: 85 | C90: 20201100054 | D90: 試供品 万田酵素MANUKA HONEY 分包2.5g | E90: 製品課 | G90: 2.5 | H90: PXM | I90: ='4.仕掛品(製品課) _作業用(値)'!E101*'4.仕掛品(製品課) _作業用(値)'!G101 -> 10.020307 | J90: ='4.仕掛品(製品課) _作業用(値)'!U101/'4.仕掛品(製品課) _作業用(値)'!K101 -> 4.0066358 | K90: ='4.仕掛品(製品課) _作業用(値)'!W101/'4.仕掛品(製品課) _作業用(値)'!K101 -> 10.793606 | L90: ='4.仕掛品(製品課) _作業用(値)'!AA101/'4.仕掛品(製品課) _作業用(値)'!K101 -> 1.0654776 | M90: =SUM(I90:L90) -> 25.886027 | O90: =I90/$G90 -> 4.0081229 | P90: =J90/$G90 -> 1.6026543 | Q90: =K90/$G90 -> 4.3174423 | R90: =L90/$G90 -> 0.42619105 | S90: =M90/$G90 -> 10.354411 | U90: =ROUND(I90,-1) -> 10 | V90: =ROUND(J90,-1) -> 0 | W90: =ROUND(K90,-1) -> 10 | X90: =ROUND(L90,-1) -> 0 | Y90: =SUM(U90:X90) -> 20
B91: 86 | C91: 20220700012 | D91: 万田酵素 ﾏﾇｶﾊﾆｰBlend 50g | E91: 製品課 | G91: 50 | H91: PXM | I91: ='4.仕掛品(製品課) _作業用(値)'!E102*'4.仕掛品(製品課) _作業用(値)'!G102 -> 200.40615 | J91: ='4.仕掛品(製品課) _作業用(値)'!U102/'4.仕掛品(製品課) _作業用(値)'!K102 -> 89.809543 | K91: ='4.仕掛品(製品課) _作業用(値)'!W102/'4.仕掛品(製品課) _作業用(値)'!K102 -> 59.629879 | L91: ='4.仕掛品(製品課) _作業用(値)'!AA102/'4.仕掛品(製品課) _作業用(値)'!K102 -> 21.309553 | M91: =SUM(I91:L91) -> 371.15512 | O91: =I91/$G91 -> 4.0081229 | P91: =J91/$G91 -> 1.7961909 | Q91: =K91/$G91 -> 1.1925976 | R91: =L91/$G91 -> 0.42619105 | S91: =M91/$G91 -> 7.4231024 | U91: =ROUND(I91,-1) -> 200 | V91: =ROUND(J91,-1) -> 90 | W91: =ROUND(K91,-1) -> 60 | X91: =ROUND(L91,-1) -> 20 | Y91: =SUM(U91:X91) -> 370
B92: 87 | C92: 20080700007 | D92: ﾊﾞｲｵ・EX 125ｇ | E92: 製品課 | G92: 125 | H92: Q | I92: ='4.仕掛品(製品課) _作業用(値)'!E103*'4.仕掛品(製品課) _作業用(値)'!G103 -> 193.57889 | J92: ='4.仕掛品(製品課) _作業用(値)'!U103/'4.仕掛品(製品課) _作業用(値)'!K103 -> 385.14832 | K92: ='4.仕掛品(製品課) _作業用(値)'!W103/'4.仕掛品(製品課) _作業用(値)'!K103 -> 414.14964 | L92: ='4.仕掛品(製品課) _作業用(値)'!AA103/'4.仕掛品(製品課) _作業用(値)'!K103 -> 53.273882 | M92: =SUM(I92:L92) -> 1046.1507 | O92: =I92/$G92 -> 1.5486311 | P92: =J92/$G92 -> 3.0811866 | Q92: =K92/$G92 -> 3.3131971 | R92: =L92/$G92 -> 0.42619105 | S92: =M92/$G92 -> 8.3692059 | U92: =ROUND(I92,-1) -> 190 | V92: =ROUND(J92,-1) -> 390 | W92: =ROUND(K92,-1) -> 410 | X92: =ROUND(L92,-1) -> 50 | Y92: =SUM(U92:X92) -> 1040
B93: 88 | C93: 20120500014 | D93: 植物性発酵物（A飼料）1kg | E93: 製品課 | G93: 1000 | H93: T | I93: ='4.仕掛品(製品課) _作業用(値)'!E104*'4.仕掛品(製品課) _作業用(値)'!G104 -> 1580.0702 | J93: ='4.仕掛品(製品課) _作業用(値)'!U104/'4.仕掛品(製品課) _作業用(値)'!K104 -> 156.92772 | K93: ='4.仕掛品(製品課) _作業用(値)'!W104/'4.仕掛品(製品課) _作業用(値)'!K104 -> 875.88465 | L93: ='4.仕掛品(製品課) _作業用(値)'!AA104/'4.仕掛品(製品課) _作業用(値)'!K104 -> 426.19105 | M93: =SUM(I93:L93) -> 3039.0737 | O93: =I93/$G93 -> 1.5800702 | P93: =J93/$G93 -> 0.15692772 | Q93: =K93/$G93 -> 0.87588465 | R93: =L93/$G93 -> 0.42619105 | S93: =M93/$G93 -> 3.0390737 | U93: =ROUND(I93,-1) -> 1580 | V93: =ROUND(J93,-1) -> 160 | W93: =ROUND(K93,-1) -> 880 | X93: =ROUND(L93,-1) -> 430 | Y93: =SUM(U93:X93) -> 3050
... B95: 90 | C95: 20241000066 | D95: 馬用万田酵素 1kg | E95: 製品課 | G95: 1000 | H95: T | I95: ='4.仕掛品(製品課) _作業用(値)'!E106*'4.仕掛品(製品課) _作業用(値)'!G106 -> 1580.0702 | J95: ='4.仕掛品(製品課) _作業用(値)'!U106/'4.仕掛品(製品課) _作業用(値)'!K106 -> 106.59402 | K95: ='4.仕掛品(製品課) _作業用(値)'!W106/'4.仕掛品(製品課) _作業用(値)'!K106 -> 330.41519 | L95: ='4.仕掛品(製品課) _作業用(値)'!AA106/'4.仕掛品(製品課) _作業用(値)'!K106 -> 426.19105 | M95: =SUM(I95:L95) -> 2443.2705 | O95: =I95/$G95 -> 1.5800702 | P95: =J95/$G95 -> 0.10659402 | Q95: =K95/$G95 -> 0.33041519 | R95: =L95/$G95 -> 0.42619105 | S95: =M95/$G95 -> 2.4432705 | U95: =ROUND(I95,-1) -> 1580 | V95: =ROUND(J95,-1) -> 110 | W95: =ROUND(K95,-1) -> 330 | X95: =ROUND(L95,-1) -> 430 | Y95: =SUM(U95:X95) -> 2450
B96: 91 | C96: 20250400005 | D96: 馬用万田酵素 10kg | E96: 製品課 | G96: 10000 | H96: T | I96: ='4.仕掛品(製品課) _作業用(値)'!E107*'4.仕掛品(製品課) _作業用(値)'!G107/10 -> 15800.702 | J96: ='4.仕掛品(製品課) _作業用(値)'!U107/'4.仕掛品(製品課) _作業用(値)'!K107 -> 1215.0445 | K96: ='4.仕掛品(製品課) _作業用(値)'!W107/'4.仕掛品(製品課) _作業用(値)'!K107 -> 4235.6213 | L96: ='4.仕掛品(製品課) _作業用(値)'!AA107/'4.仕掛品(製品課) _作業用(値)'!K107 -> 42619.105 | M96: =SUM(I96:L96) -> 63870.474 | O96: =I96/$G96 -> 1.5800702 | P96: =J96/$G96 -> 0.12150445 | Q96: =K96/$G96 -> 0.42356213 | R96: =L96/$G96 -> 4.2619105 | S96: =M96/$G96 -> 6.3870474 | U96: =ROUND(I96,-1) -> 15800 | V96: =ROUND(J96,-1) -> 1220 | W96: =ROUND(K96,-1) -> 4240 | X96: =ROUND(L96,-1) -> 42620 | Y96: =SUM(U96:X96) -> 63880
B97: 92 | C97: 20080700011 | D97: 試供品 ｽｰﾊﾟｰ氣Ⅰ 5g | E97: 製品課 | G97: 5 | H97: V | I97: ='4.仕掛品(製品課) _作業用(値)'!E108*'4.仕掛品(製品課) _作業用(値)'!G108 -> 6.0568634 | J97: ='4.仕掛品(製品課) _作業用(値)'!U108/'4.仕掛品(製品課) _作業用(値)'!K108 -> 5.8187706 | K97: ='4.仕掛品(製品課) _作業用(値)'!W108/'4.仕掛品(製品課) _作業用(値)'!K108 -> 12.143276 | L97: ='4.仕掛品(製品課) _作業用(値)'!AA108/'4.仕掛品(製品課) _作業用(値)'!K108 -> 2.1309553 | M97: =SUM(I97:L97) -> 26.149866 | O97: =I97/$G97 -> 1.2113727 | P97: =J97/$G97 -> 1.1637541 | Q97: =K97/$G97 -> 2.4286553 | R97: =L97/$G97 -> 0.42619105 | S97: =M97/$G97 -> 5.2299732 | U97: =ROUND(I97,-1) -> 10 | V97: =ROUND(J97,-1) -> 10 | W97: =ROUND(K97,-1) -> 10 | X97: =ROUND(L97,-1) -> 0 | Y97: =SUM(U97:X97) -> 30
B98: 93 | C98: 20080800002 | D98: ｽｰﾊﾟｰ万田酵素氣Ⅰ 35g | E98: 製品課 | G98: 35 | H98: V | I98: ='4.仕掛品(製品課) _作業用(値)'!E109*'4.仕掛品(製品課) _作業用(値)'!G109 -> 42.398044 | J98: ='4.仕掛品(製品課) _作業用(値)'!U109/'4.仕掛品(製品課) _作業用(値)'!K109 -> 98.065074 | K98: ='4.仕掛品(製品課) _作業用(値)'!W109/'4.仕掛品(製品課) _作業用(値)'!K109 -> 128.84655 | L98: ='4.仕掛品(製品課) _作業用(値)'!AA109/'4.仕掛品(製品課) _作業用(値)'!K109 -> 14.916687 | M98: =SUM(I98:L98) -> 284.22636 | O98: =I98/$G98 -> 1.2113727 | P98: =J98/$G98 -> 2.8018593 | Q98: =K98/$G98 -> 3.6813301 | R98: =L98/$G98 -> 0.42619105 | S98: =M98/$G98 -> 8.1207531 | U98: =ROUND(I98,-1) -> 40 | V98: =ROUND(J98,-1) -> 100 | W98: =ROUND(K98,-1) -> 130 | X98: =ROUND(L98,-1) -> 10 | Y98: =SUM(U98:X98) -> 280
B99: 94 | C99: 20081200016 | D99: ｽｰﾊﾟｰ氣Ⅰ 分包600g(150g×4箱) | E99: 製品課 | G99: 600 | H99: V | I99: ='4.仕掛品(製品課) _作業用(値)'!E110*'4.仕掛品(製品課) _作業用(値)'!G110 -> 726.82361 | J99: ='4.仕掛品(製品課) _作業用(値)'!U110/'4.仕掛品(製品課) _作業用(値)'!K110 -> 1218.6252 | K99: ='4.仕掛品(製品課) _作業用(値)'!W110/'4.仕掛品(製品課) _作業用(値)'!K110 -> 1349.2375 | L99: ='4.仕掛品(製品課) _作業用(値)'!AA110/'4.仕掛品(製品課) _作業用(値)'!K110 -> 255.71463 | M99: =SUM(I99:L99) -> 3550.401 | O99: =I99/$G99 -> 1.2113727 | P99: =J99/$G99 -> 2.0310421 | Q99: =K99/$G99 -> 2.2487292 | R99: =L99/$G99 -> 0.42619105 | S99: =M99/$G99 -> 5.917335 | U99: =ROUND(I99,-1) -> 730 | V99: =ROUND(J99,-1) -> 1220 | W99: =ROUND(K99,-1) -> 1350 | X99: =ROUND(L99,-1) -> 260 | Y99: =SUM(U99:X99) -> 3560
B100: 95 | C100: 20110800272 | D100: ｽｰﾊﾟｰ万田酵素 氣Ⅰ | E100: 製品課 | G100: 175 | H100: V | I100: ='4.仕掛品(製品課) _作業用(値)'!E111*'4.仕掛品(製品課) _作業用(値)'!G111 -> 211.99022 | J100: ='4.仕掛品(製品課) _作業用(値)'!U111/'4.仕掛品(製品課) _作業用(値)'!K111 -> 1574.0489 | K100: ='4.仕掛品(製品課) _作業用(値)'!W111/'4.仕掛品(製品課) _作業用(値)'!K111 -> 1605.7885 | L100: ='4.仕掛品(製品課) _作業用(値)'!AA111/'4.仕掛品(製品課) _作業用(値)'!K111 -> 74.583434 | M100: =SUM(I100:L100) -> 3466.4111 | O100: =I100/$G100 -> 1.2113727 | P100: =J100/$G100 -> 8.994565 | Q100: =K100/$G100 -> 9.1759345 | R100: =L100/$G100 -> 0.42619105 | S100: =M100/$G100 -> 19.808063 | U100: =ROUND(I100,-1) -> 210 | V100: =ROUND(J100,-1) -> 1570 | W100: =ROUND(K100,-1) -> 1610 | X100: =ROUND(L100,-1) -> 70 | Y100: =SUM(U100:X100) -> 3460
B101: 96 | C101: 20060800006 | D101: 試供品 万田31号 1ml×6 | E101: 製品課 | G101: 7.8 | H101: X | I101: ='4.仕掛品(製品課) _作業用(値)'!E112*'4.仕掛品(製品課) _作業用(値)'!G112 -> 12.270371 | J101: ='4.仕掛品(製品課) _作業用(値)'!U112/'4.仕掛品(製品課) _作業用(値)'!K112 -> 13.863592 | K101: ='4.仕掛品(製品課) _作業用(値)'!W112/'4.仕掛品(製品課) _作業用(値)'!K112 -> 82.957752 | L101: ='4.仕掛品(製品課) _作業用(値)'!AA112/'4.仕掛品(製品課) _作業用(値)'!K112 -> 3.3242902 | M101: =SUM(I101:L101) -> 112.41601 | O101: =I101/$G101 -> 1.5731245 | P101: =J101/$G101 -> 1.7773836 | Q101: =K101/$G101 -> 10.635609 | R101: =L101/$G101 -> 0.42619105 | S101: =M101/$G101 -> 14.412308 | U101: =ROUND(I101,-1) -> 10 | V101: =ROUND(J101,-1) -> 10 | W101: =ROUND(K101,-1) -> 80 | X101: =ROUND(L101,-1) -> 0 | Y101: =SUM(U101:X101) -> 100
B102: 97 | C102: 20081200013 | D102: 万田31号 100ml | E102: 製品課 | G102: 130 | H102: X | I102: ='4.仕掛品(製品課) _作業用(値)'!E113*'4.仕掛品(製品課) _作業用(値)'!G113 -> 204.50619 | J102: ='4.仕掛品(製品課) _作業用(値)'!U113/'4.仕掛品(製品課) _作業用(値)'!K113 -> 161.77049 | K102: ='4.仕掛品(製品課) _作業用(値)'!W113/'4.仕掛品(製品課) _作業用(値)'!K113 -> 270.29442 | L102: ='4.仕掛品(製品課) _作業用(値)'!AA113/'4.仕掛品(製品課) _作業用(値)'!K113 -> 55.404837 | M102: =SUM(I102:L102) -> 691.97594 | O102: =I102/$G102 -> 1.5731245 | P102: =J102/$G102 -> 1.2443884 | Q102: =K102/$G102 -> 2.0791879 | R102: =L102/$G102 -> 0.42619105 | S102: =M102/$G102 -> 5.3228918 | U102: =ROUND(I102,-1) -> 200 | V102: =ROUND(J102,-1) -> 160 | W102: =ROUND(K102,-1) -> 270 | X102: =ROUND(L102,-1) -> 60 | Y102: =SUM(U102:X102) -> 690
B103: 98 | C103: 20081200014 | D103: 万田31号 500ml | E103: 製品課 | G103: 650 | H103: X | I103: ='4.仕掛品(製品課) _作業用(値)'!E114*'4.仕掛品(製品課) _作業用(値)'!G114 -> 1022.5309 | J103: ='4.仕掛品(製品課) _作業用(値)'!U114/'4.仕掛品(製品課) _作業用(値)'!K114 -> 354.28851 | K103: ='4.仕掛品(製品課) _作業用(値)'!W114/'4.仕掛品(製品課) _作業用(値)'!K114 -> 340.3313 | L103: ='4.仕掛品(製品課) _作業用(値)'!AA114/'4.仕掛品(製品課) _作業用(値)'!K114 -> 277.02418 | M103: =SUM(I103:L103) -> 1994.1749 | O103: =I103/$G103 -> 1.5731245 | P103: =J103/$G103 -> 0.54505924 | Q103: =K103/$G103 -> 0.52358662 | R103: =L103/$G103 -> 0.42619105 | S103: =M103/$G103 -> 3.0679614 | U103: =ROUND(I103,-1) -> 1020 | V103: =ROUND(J103,-1) -> 350 | W103: =ROUND(K103,-1) -> 340 | X103: =ROUND(L103,-1) -> 280 | Y103: =SUM(U103:X103) -> 1990
B104: 99 | C104: 20081200019 | D104: 万田31号 1ﾘｯﾄﾙ | E104: 製品課 | G104: 1300 | H104: X | I104: ='4.仕掛品(製品課) _作業用(値)'!E115*'4.仕掛品(製品課) _作業用(値)'!G115 -> 2045.0619 | J104: ='4.仕掛品(製品課) _作業用(値)'!U115/'4.仕掛品(製品課) _作業用(値)'!K115 -> 403.55423 | K104: ='4.仕掛品(製品課) _作業用(値)'!W115/'4.仕掛品(製品課) _作業用(値)'!K115 -> 363.1244 | L104: ='4.仕掛品(製品課) _作業用(値)'!AA115/'4.仕掛品(製品課) _作業用(値)'!K115 -> 554.04837 | M104: =SUM(I104:L104) -> 3365.7889 | O104: =I104/$G104 -> 1.5731245 | P104: =J104/$G104 -> 0.31042633 | Q104: =K104/$G104 -> 0.27932646 | R104: =L104/$G104 -> 0.42619105 | S104: =M104/$G104 -> 2.5890684 | U104: =ROUND(I104,-1) -> 2050 | V104: =ROUND(J104,-1) -> 400 | W104: =ROUND(K104,-1) -> 360 | X104: =ROUND(L104,-1) -> 550 | Y104: =SUM(U104:X104) -> 3360
B105: 100 | C105: 20230300008 | D105: 健康農業のための万田酵素 500ml | E105: 製品課 | G105: 650 | H105: X | I105: ='4.仕掛品(製品課) _作業用(値)'!E116*'4.仕掛品(製品課) _作業用(値)'!G116 -> 1022.5309 | J105: ='4.仕掛品(製品課) _作業用(値)'!U116/'4.仕掛品(製品課) _作業用(値)'!K116 -> 253.96596 | K105: ='4.仕掛品(製品課) _作業用(値)'!W116/'4.仕掛品(製品課) _作業用(値)'!K116 -> 223.69194 | L105: ='4.仕掛品(製品課) _作業用(値)'!AA116/'4.仕掛品(製品課) _作業用(値)'!K116 -> 277.02418 | M105: =SUM(I105:L105) -> 1777.213 | O105: =I105/$G105 -> 1.5731245 | P105: =J105/$G105 -> 0.39071685 | Q105: =K105/$G105 -> 0.34414144 | R105: =L105/$G105 -> 0.42619105 | S105: =M105/$G105 -> 2.7341739 | U105: =ROUND(I105,-1) -> 1020 | V105: =ROUND(J105,-1) -> 250 | W105: =ROUND(K105,-1) -> 220 | X105: =ROUND(L105,-1) -> 280 | Y105: =SUM(U105:X105) -> 1770
B106: 101 | C106: 20241200064 | D106: 万田ｸﾞﾘｰﾝｷｰﾊﾟｰ 200ml | E106: 製品課 | G106: 260 | H106: X | I106: ='4.仕掛品(製品課) _作業用(値)'!E117*'4.仕掛品(製品課) _作業用(値)'!G117 -> 409.01238 | J106: ='4.仕掛品(製品課) _作業用(値)'!U117/'4.仕掛品(製品課) _作業用(値)'!K117 -> 171.26382 | K106: ='4.仕掛品(製品課) _作業用(値)'!W117/'4.仕掛品(製品課) _作業用(値)'!K117 -> 241.58729 | L106: ='4.仕掛品(製品課) _作業用(値)'!AA117/'4.仕掛品(製品課) _作業用(値)'!K117 -> 110.80967 | M106: =SUM(I106:L106) -> 932.67316 | O106: =I106/$G106 -> 1.5731245 | P106: =J106/$G106 -> 0.65870698 | Q106: =K106/$G106 -> 0.92918188 | R106: =L106/$G106 -> 0.42619105 | S106: =M106/$G106 -> 3.5872044 | U106: =ROUND(I106,-1) -> 410 | V106: =ROUND(J106,-1) -> 170 | W106: =ROUND(K106,-1) -> 240 | X106: =ROUND(L106,-1) -> 110 | Y106: =SUM(U106:X106) -> 930
B107: 102 | C107: 20160900041 | D107: 万田31号500ml(韓国向) | E107: 製品課 | G107: 650 | H107: XC | I107: ='4.仕掛品(製品課) _作業用(値)'!E118*'4.仕掛品(製品課) _作業用(値)'!G118 -> 1757.0207 | J107: ='4.仕掛品(製品課) _作業用(値)'!U118/'4.仕掛品(製品課) _作業用(値)'!K118 -> 520.77602 | K107: ='4.仕掛品(製品課) _作業用(値)'!W118/'4.仕掛品(製品課) _作業用(値)'!K118 -> 407.97148 | L107: ='4.仕掛品(製品課) _作業用(値)'!AA118/'4.仕掛品(製品課) _作業用(値)'!K118 -> 277.02418 | M107: =SUM(I107:L107) -> 2962.7924 | O107: =I107/$G107 -> 2.7031088 | P107: =J107/$G107 -> 0.80119388 | Q107: =K107/$G107 -> 0.62764843 | R107: =L107/$G107 -> 0.42619105 | S107: =M107/$G107 -> 4.5581421 | U107: =ROUND(I107,-1) -> 1760 | V107: =ROUND(J107,-1) -> 520 | W107: =ROUND(K107,-1) -> 410 | X107: =ROUND(L107,-1) -> 280 | Y107: =SUM(U107:X107) -> 2970
B108: 103 | C108: 20160900042 | D108: 万田31号1ﾘｯﾄﾙ(韓国向) | E108: 製品課 | G108: 1300 | H108: XC | I108: ='4.仕掛品(製品課) _作業用(値)'!E119*'4.仕掛品(製品課) _作業用(値)'!G119 -> 3514.0414 | J108: ='4.仕掛品(製品課) _作業用(値)'!U119/'4.仕掛品(製品課) _作業用(値)'!K119 -> 408.01775 | K108: ='4.仕掛品(製品課) _作業用(値)'!W119/'4.仕掛品(製品課) _作業用(値)'!K119 -> 499.7917 | L108: ='4.仕掛品(製品課) _作業用(値)'!AA119/'4.仕掛品(製品課) _作業用(値)'!K119 -> 554.04837 | M108: =SUM(I108:L108) -> 4975.8992 | O108: =I108/$G108 -> 2.7031088 | P108: =J108/$G108 -> 0.31385981 | Q108: =K108/$G108 -> 0.38445515 | R108: =L108/$G108 -> 0.42619105 | S108: =M108/$G108 -> 3.8276148 | U108: =ROUND(I108,-1) -> 3510 | V108: =ROUND(J108,-1) -> 410 | W108: =ROUND(K108,-1) -> 500 | X108: =ROUND(L108,-1) -> 550 | Y108: =SUM(U108:X108) -> 4970
... B116: 111 | C116: 20091200013 | D116: MANDA CARE PLUS 5g(ﾊﾟﾊﾟｲﾔ･ｺｺｱ) | E116: 製品課 | G116: 5 | H116: ZA | I116: ='4.仕掛品(製品課) _作業用(値)'!E127*'4.仕掛品(製品課) _作業用(値)'!G127 -> 11.036573 | J116: ='4.仕掛品(製品課) _作業用(値)'!U127/'4.仕掛品(製品課) _作業用(値)'!K127 -> 21.742178 | K116: ='4.仕掛品(製品課) _作業用(値)'!W127/'4.仕掛品(製品課) _作業用(値)'!K127 -> 44.227091 | L116: ='4.仕掛品(製品課) _作業用(値)'!AA127/'4.仕掛品(製品課) _作業用(値)'!K127 -> 2.1309553 | M116: =SUM(I116:L116) -> 79.136798 | O116: =I116/$G116 -> 2.2073146 | P116: =J116/$G116 -> 4.3484357 | Q116: =K116/$G116 -> 8.8454182 | R116: =L116/$G116 -> 0.42619105 | S116: =M116/$G116 -> 15.82736 | U116: =ROUND(I116,-1) -> 10 | V116: =ROUND(J116,-1) -> 20 | W116: =ROUND(K116,-1) -> 40 | X116: =ROUND(L116,-1) -> 0 | Y116: =SUM(U116:X116) -> 70

Sheet Sheet16
C1: 1 | D1: 2 | E1: 3 | F1: 4 | G1: 5 | H1: 6 | I1: 7 | J1: 8 | K1: 9 | L1: 10 | M1: 11 | N1: 12 | O1: 13 | P1: 14 | Q1: 15 | R1: 16 | S1: 17 | T1: 18 | U1: 19 | V1: 20 | W1: 21 | X1: 22 | Y1: 23 | Z1: 24 | AA1: 25 | AB1: 26 | AC1: 27 | AD1: 28 | AE1: 29 | AF1: 30
C2: 5A | D2: B | E2: BE | F2: BM | G2: C | H2: D | I2: DC | J2: EB | K2: FB | L2: G | M2: GP | N2: KOL | O2: MP | P2: O | Q2: P | R2: PE | S2: PG | T2: PR | U2: PSA | V2: PX | W2: PXM | X2: Q | Y2: T | Z2: V | AA2: X | AB2: XC | AC2: Y | AD2: YA | AE2: YC | AF2: ZA
C3: 2 | D3: 4 | E3: 3 | F3: 1 | G3: 1 | H3: 2 | I3: 2 | J3: 5 | K3: 2 | L3: 2 | M3: 6 | N3: 3 | O3: 8 | P3: 5 | Q3: 14 | R3: 9 | S3: 7 | T3: 2 | U3: 3 | V3: 9 | W3: 3 | X3: 1 | Y3: 4 | Z3: 5 | AA3: 6 | AB3: 3 | AC3: 3 | AD3: 1 | AE3: 1 | AF3: 3 | AG3: =SUM(C3:AF3) -> 120
B4: ='4.仕掛品(製品課) _作業用(値)'!A17 -> 20051200013 | C4: ='4.仕掛品(製品課) _作業用(値)'!B17 -> MKF-Ⅰ 分包150g(AAAAA)
B5: ='4.仕掛品(製品課) _作業用(値)'!A18 -> 20071100007 | C5: ='4.仕掛品(製品課) _作業用(値)'!B18 -> MKF-Ⅰ携帯ﾊﾟｯｸ 50g(5A)
C6: ='4.仕掛品(製品課) _作業用(値)'!A19 -> 20051200005 | D6: ='4.仕掛品(製品課) _作業用(値)'!B19 -> 万田HI酵素 分包150g
C7: ='4.仕掛品(製品課) _作業用(値)'!A20 -> 20071000005 | D7: ='4.仕掛品(製品課) _作業用(値)'!B20 -> 試供品 HI酵素 5g
C8: ='4.仕掛品(製品課) _作業用(値)'!A21 -> 20110800311 | D8: ='4.仕掛品(製品課) _作業用(値)'!B21 -> MANDA HI KOHSO
C9: ='4.仕掛品(製品課) _作業用(値)'!A22 -> 20110800629 | D9: ='4.仕掛品(製品課) _作業用(値)'!B22 -> 万田HI酵素 145g
D10: ='4.仕掛品(製品課) _作業用(値)'!A23 -> 20200800016 | E10: ='4.仕掛品(製品課) _作業用(値)'!B23 -> 万田酵素ｴｸｾﾚﾝﾄ 145g
D11: ='4.仕掛品(製品課) _作業用(値)'!A24 -> 20200800017 | E11: ='4.仕掛品(製品課) _作業用(値)'!B24 -> 万田酵素ｴｸｾﾚﾝﾄ 分包30g（2.5g×12包）
D12: ='4.仕掛品(製品課) _作業用(値)'!A25 -> 20200800018 | E12: ='4.仕掛品(製品課) _作業用(値)'!B25 -> 万田酵素ｴｸｾﾚﾝﾄ 分包450g
E13: ='4.仕掛品(製品課) _作業用(値)'!A26 -> 20240100051 | F13: ='4.仕掛品(製品課) _作業用(値)'!B26 -> 万田酵素 MANUKA HONEY Premium 分包77.5g
F14: ='4.仕掛品(製品課) _作業用(値)'!A27 -> 20110300008 | G14: ='4.仕掛品(製品課) _作業用(値)'!B27 -> Man-Koso CARAT 145g

Sheet 4.仕掛品(製品課) _作業用(値)
A1: 第37期 仕掛品(製品課)
L2: 内容量(g)*数量(個)
F3: 製品記号 | H3: 期首棚卸 | K3: 当期投入 | AE3: 当期商品製造原価 | AH3: 在庫調整 | AJ3: 期末棚卸
H4: 数量 | M4: 仕掛品(製品課製造分) | O4: 仕掛品(外注品内製分) | Q4: 仕掛品(製造部製造分) | S4: 資材費 | V4: 労務費(製品課) | X4: 労務費(製造部) | Z4: 経費 | AB4: 外注加工費 | AC4: 別コードに振替 | AJ4: 数量
A5: SCコード | B5: 商品名 | C5: 区分 | D5: 半製品 | E5: 内容量(g) | F5: 製品記号 | G5: ｸﾞﾗﾑ単価 | H5: 数量 | I5: 進捗度 | J5: 金額 | K5: 数量 | M5: 配賦係数 | N5: 金額 | O5: 配賦係数 | P5: 金額 | Q5: 配賦係数 | R5: 金額 | S5: 包材価格 | T5: 配賦係数 | U5: 金額 | V5: 配賦係数 | W5: 金額 | X5: 配賦係数 | Y5: 金額 | Z5: 配賦係数 | AA5: 金額 | AB5: (原液原価込み) | AC5: 数量 | AD5: 金額 | AE5: 数量 | AF5: 金額 | AG5: 単価 | AH5: 数量 | AI5: 原価 | AJ5: 数量 | AK5: 進捗度 | AL5: 金額 | AO5: 34期資材 | AP5: 34期単価 | AR5: 絞り込み
A6: 20110801161 | B6: BE 2.5g×2 | C6: 半製品 | D6: 半製品 | E6: 5 | F6: BE | G6: 1.6947416 | H6: 3800 | J6: 25204.237 | AJ6: 0 | AL6: 0 | AP6: 7.1801316 | AR6: ok
A7: 20110801267 | B7: EB 2.5g×2 | C7: 半製品 | D7: 半製品 | E7: 5 | F7: EB | G7: 1.3583252 | H7: 4500 | J7: 19728.659 | AJ7: 12600 | AL7: 369655.96 | AP7: 2136.147 | AR7: ok
A8: 20230600090 | B8: 発酵しょうが 2.5g | C8: 半製品 | D8: 半製品 | E8: 2.5 | F8: GP | G8: 1.394799 | H8: 44000 | J8: 107278.15 | AJ8: 100000 | AL8: 753532.73 | AR8: ok
A9: 20180700008 | B9: MULBERRY 2.5g | C9: 半製品 | D9: 半製品 | E9: 2.5 | F9: MP | G9: 1.1798248 | H9: 40000 | J9: 87224.699 | AJ9: 24200 | AL9: 172038.19 | AO9: 1775.9687 | AP9: 7296.6701 | AR9: ok
A10: 20110801273 | B10: P 2.5g×2 | C10: 半製品 | D10: 半製品 | E10: 5 | F10: P | G10: 1.2657092 | H10: 124800 | J10: 599836.36 | AJ10: 52300 | AL10: 670818.01 | AO10: 68.967368 | AP10: 729.09329 | AR10: ok
A11: 20170500057 | B11: GINGER 2.5g | C11: 半製品 | D11: 半製品 | E11: 2.5 | F11: PE | G11: 1.1499334 | H11: 31600 | J11: 67389.992 | AJ11: 18000 | AL11: 125180.49 | AP11: 0 | AR11: ok
A12: 20110801158 | B12: PG 2.5g×2 | C12: 半製品 | D12: 半製品 | E12: 5 | F12: PG | G12: 0 | H12: 180 | J12: 1110.9506 | AJ12: 1350 | AL12: 82945.988 | AP12: 0 | AR12: ok
A13: 20110801164 | B13: ｊPG 2.5g×2 | C13: 半製品 | D13: 半製品 | E13: 5 | F13: PG | G13: 1.4973298 | H13: 900 | J13: 5554.7532 | AJ13: 1800 | AL13: 110594.65 | AP13: 0 | AR13: ok
A14: 20170500058 | B14: STANDARD 2.5g | C14: 半製品 | D14: 半製品 | E14: 2.5 | F14: PX | G14: 1.2530514 | H14: 8400 | J14: 20308.946 | AJ14: 26000 | AL14: 463797.99 | AP14: 0 | AR14: ok
A15: 20110801268 | B15: V 2.5g×2 | C15: 半製品 | D15: 半製品 | E15: 5 | F15: V | G15: 1.2113727 | H15: 0 | J15: 0 | AJ15: 12700 | AL15: 337292.91 | AO15: 594.95854 | AP15: 2504.1591 | AR15: ok
A16: 20110801159 | B16: ZA 2.5g×2 | C16: 半製品 | D16: 半製品 | E16: 5 | F16: ZA | G16: 2.2073146 | H16: 4500 | J16: 37735.653 | AJ16: 0 | AL16: 0 | AP16: 0 | AR16: ok
A17: 20051200013 | B17: MKF-Ⅰ 分包150g(AAAAA) | C17: 製品課 | E17: 150 | F17: 5A | G17: 5.1725294 | H17: 0 | J17: 0 | K17: 814 | L17: =E17*K17 -> 122100 | M17: 631565.83 | N17: 674174.91 | S17: 110.73288 | T17: 90136.568 | U17: 71260.558 | V17: 1600 | W17: 184066.51 | Y17: 0 | Z17: 122100 | AA17: 52037.928 | AE17: 814 | AF17: 981539.91 | AG17: 1205.823 | AH17: 0 | AI17: 0 | AJ17: 0 | AL17: 0 | AO17: 3.0756837 | AP17: 27.221301 | AR17: ok
A18: 20071100007 | B18: MKF-Ⅰ携帯ﾊﾟｯｸ 50g(5A) | C18: 製品課 | E18: 50 | F18: 5A | G18: 5.1725294 | H18: 0 | J18: 0 | K18: 671 | L18: =E18*K18 -> 33550 | M18: 173538.36 | N18: 185246.26 | S18: 63.768813 | T18: 42788.873 | U18: 33828.212 | V18: 915 | W18: 105263.03 | Y18: 0 | Z18: 33550 | AA18: 14298.71 | AE18: 671 | AF18: 338636.22 | AG18: 504.67394 | AH18: 0 | AI18: 0 | AJ18: 0 | AL18: 0 | AP18: 0 | AR18: ok
A19: 20051200005 | B19: 万田HI酵素 分包150g | C19: 製品課 | E19: 150 | F19: B | G19: 1.3486947 | H19: 0 | J19: 0 | K19: 960 | L19: =E19*K19 -> 144000 | M19: 194212.03 | N19: 207314.7 | S19: 422.38363 | T19: 405488.29 | U19: 320572.68 | V19: 2740 | W19: 315213.89 | Y19: 0 | Z19: 144000 | AA19: 61371.512 | AE19: 960 | AF19: 904472.79 | AG19: 942.15915 | AH19: 0 | AI19: 0 | AJ19: 0 | AL19: 0 | AP19: 0 | AR19: ok
A20: 20071000005 | B20: 試供品 HI酵素 5g | C20: 製品課 | E20: 5 | F20: B | G20: 1.3486947 | H20: 0 | J20: 0 | K20: 19500 | L20: =E20*K20 -> 97500 | M20: 131497.73 | N20: 140369.33 | S20: 7.8361921 | T20: 152805.75 | U20: 120805.83 | V20: 2045 | W20: 235260 | Y20: 0 | Z20: 97500 | AA20: 41553.628 | AE20: 19500 | AF20: 537988.79 | AG20: 27.589169 | AH20: 0 | AI20: 0 | AJ20: 0 | AL20: 0 | AO20: 3.4266837 | AP20: 22.183364 | AR20: ok
A21: 20110800311 | B21: MANDA HI KOHSO | C21: 製品課 | E21: 145 | F21: B | G21: 1.3486947 | H21: 0 | J21: 0 | K21: 192 | L21: =E21*K21 -> 27840 | M21: 37547.66 | N21: 40080.842 | S21: 1102.6433 | T21: 211707.5 | U21: 167372.63 | V21: 665 | W21: 76502.642 | Y21: 0 | Z21: 27840 | AA21: 11865.159 | AE21: 192 | AF21: 295821.28 | AG21: 1540.7358 | AH21: 0 | AI21: 0 | AJ21: 0 | AL21: 0 | AP21: 368.28403 | AR21: ok
A22: 20110800629 | B22: 万田HI酵素 145g | C22: 製品課 | E22: 145 | F22: B | G22: 1.3486947 | H22: 0 | J22: 0 | K22: 1470 | L22: =E22*K22 -> 213150 | M22: 287474.27 | N22: 306868.95 | S22: 370.27608 | T22: 544305.84 | U22: 430319.66 | V22: 3735 | W22: 429680.25 | Y22: 0 | Z22: 213150 | AA22: 90842.623 | AE22: 1470 | AF22: 1257711.5 | AG22: 855.58604 | AH22: 0 | AI22: 0 | AJ22: 0 | AL22: 0 | AP22: 477.35077 | AR22: ok
A23: 20200800016 | B23: 万田酵素ｴｸｾﾚﾝﾄ 145g | C23: 製品課 | E23: 145 | F23: BE | G23: 1.6947416 | H23: 0 | J23: 0 | K23: 120 | L23: =E23*K23 -> 17400 | M23: 29488.504 | N23: 31477.969 | S23: 1258.9659 | T23: 151075.91 | U23: 119438.25 | V23: 1495 | W23: 171987.14 | Y23: 0 | Z23: 17400 | AA23: 7415.7243 | AE23: 120 | AF23: 330319.08 | AG23: 2752.659 | AH23: 0 | AI23: 0 | AJ23: 0 | AL23: 0 | AP23: 0 | AR23: ok
A24: 20200800017 | B24: 万田酵素ｴｸｾﾚﾝﾄ 分包30g（2.5g×12包） | C24: 製品課 | E24: 30 | F24: BE | G24: 1.6947416 | H24: 0 | J24: 0 | K24: 1800 | L24: =E24*K24 -> 54000 | M24: 91516.046 | N24: 97690.247 | S24: 119.06788 | T24: 214322.19 | U24: 169439.76 | V24: 2220 | W24: 255392.28 | Y24: 0 | Z24: 54000 | AA24: 23014.317 | AE24: 1800 | AF24: 545536.6 | AG24: 303.07589 | AH24: 0 | AI24: 0 | AJ24: 0 | AL24: 0 | AP24: 820.07323 | AR24: ok
A25: 20200800018 | B25: 万田酵素ｴｸｾﾚﾝﾄ 分包450g | C25: 製品課 | E25: 450 | F25: BE | G25: 1.6947416 | H25: 0 | J25: 0 | K25: 402 | L25: =E25*K25 -> 180900 | M25: 306578.75 | N25: 327262.33 | S25: 1603.6479 | T25: 644666.45 | U25: 509663.19 | V25: 3950 | W25: 454414.19 | Y25: 0 | Z25: 180900 | AA25: 77097.962 | AE25: 402 | AF25: 1368437.7 | AG25: 3404.0738 | AH25: 0 | AI25: 0 | AJ25: 0 | AL25: 0 | AP25: 566.432 | AR25: ok
A26: 20240100051 | B26: 万田酵素 MANUKA HONEY Premium 分包77.5g | C26: 製品課 | E26: 77.5 | F26: BM | G26: 4.5002042 | H26: 0 | J26: 0 | K26: 14700 | L26: =E26*K26 -> 1139250 | M26: 5126857.6 | N26: 5472745.1 | S26: 54.529045 | T26: 801576.97 | U26: 633714.18 | V26: 6700 | W26: 770778.5 | Y26: 0 | Z26: 1139250 | AA26: 485538.16 | AE26: 14700 | AF26: 7362775.9 | AG26: 500.86911 | AH26: 0 | AI26: 0 | AJ26: 0 | AL26: 0 | AO26: 0 | AP26: 130.25509 | AR26: ok
A27: 20110300008 | B27: Man-Koso CARAT 145g | C27: 製品課 | E27: 145 | F27: C | G27: 1.0344858 | H27: 0 | J27: 0 | K27: 163 | L27: =E27*K27 -> 23635 | M27: 24450.072 | N27: 26099.615 | S27: 1776.1255 | T27: 289508.46 | U27: 228880.85 | V27: 1030 | W27: 118492.81 | Y27: 0 | Z27: 23635 | AA27: 10073.026 | AE27: 163 | AF27: 383546.3 | AG27: 2353.0448 | AH27: 0 | AI27: 0 | AJ27: 0 | AL27: 0 | AO27: 371.03526 | AP27: 2226.1295 | AR27: ok
A28: 20200200001 | B28: 万田酵素超熟分包77.5g | C28: 製品課 | E28: 77.5 | F28: D | G28: 1.3499631 | H28: 0 | J28: 0 | K28: 2000 | L28: =E28*K28 -> 155000 | M28: 209244.28 | N28: 223361.1 | S28: 205.08505 | T28: 410170.09 | U28: 324274.04 | V28: 1595 | W28: 183491.3 | Y28: 0 | Z28: 155000 | AA28: 66059.613 | AE28: 2000 | AF28: 797186.06 | AG28: 398.59303 | AH28: 0 | AI28: 0 | AJ28: 0 | AL28: 0 | AN28: 合計チェック | AO28: 0 | AP28: 949.51363 | AR28: ok
A29: 20200200003 | B29: 万田酵素超熟分包2.5g×5 | C29: 製品課 | E29: 12.5 | F29: D | G29: 1.3499631 | H29: 0 | J29: 0 | K29: 300 | L29: =E29*K29 -> 3750 | M29: 5062.3615 | N29: 5403.8977 | S29: 203.84191 | T29: 61152.572 | U29: 48346.264 | V29: 470 | W29: 54069.536 | Y29: 0 | Z29: 3750 | AA29: 1598.2165 | AE29: 300 | AF29: 109417.91 | AG29: 364.72638 | AH29: 0 | AI29: 0 | AJ29: 0 | AL29: 0 | AP29: 0 | AR29: ok
A30: 20211100014 | B30: 特選EXプラス分包70g(2.5g×28包) | C30: 製品課 | E30: 70 | F30: DC | G30: 2.5414453 | H30: 0 | J30: 0 | K30: 5665 | L30: =E30*K30 -> 396550 | M30: 1007810.1 | N30: 1075802.8 | S30: 219.41091 | T30: 1242962.8 | U30: 982666.91 | V30: 8100 | W30: 931836.69 | Y30: 0 | Z30: 396550 | AA30: 169006.06 | AE30: 5665 | AF30: 3159312.5 | AG30: 557.68976 | AH30: 0 | AI30: 0 | AJ30: 0 | AL30: 0 | AP30: 0 | AR30: ok
A31: 20211100015 | B31: 特選EXプラス分包150g(2.5g×60包) | C31: 製品課 | E31: 150 | F31: DC | G31: 2.5414453 | H31: 0 | J31: 0 | K31: 3060 | L31: =E31*K31 -> 459000 | M31: 1166523.4 | N31: 1245223.8 | S31: 371.06034 | T31: 1135444.6 | U31: 897664.73 | V31: 7830 | W31: 900775.47 | Y31: 0 | Z31: 459000 | AA31: 195621.69 | AE31: 3060 | AF31: 3239285.7 | AG31: 1058.5901 | AH31: 0 | AI31: 0 | AJ31: 0 | AL31: 0 | AP31: 209.03947 | AR31: ok
A32: 20071200005 | B32: 試供品 ｽｰﾊﾟｰ万田酵素(赤) 5g | C32: 製品課 | E32: 5 | F32: EB | G32: 1.3583252 | H32: 0 | J32: 0 | K32: 25100 | L32: =E32*K32 -> 125500 | M32: 170469.81 | N32: 181970.68 | S32: 8.6917813 | T32: 218163.71 | U32: 172476.81 | V32: 2855 | W32: 328443.67 | Y32: 0 | Z32: 125500 | AA32: 53486.977 | AE32: 25100 | AF32: 736378.14 | AG32: 29.337775 | AH32: 0 | AI32: 0 | AJ32: 0 | AL32: 0 | AO32: 0 | AP32: 0 | AR32: ok
A33: 20231100072 | B33: ｽｰﾊﾟｰ万田酵素 分包 35g | C33: 製品課 | E33: 35 | F33: EB | G33: 1.3583252 | H33: 0 | J33: 0 | K33: 3400 | L33: =E33*K33 -> 119000 | M33: 161640.69 | N33: 172545.91 | S33: 77.041259 | T33: 261940.28 | U33: 207085.88 | V33: 4435 | W33: 510209.35 | Y33: 0 | Z33: 119000 | AA33: 50716.735 | AE33: 3400 | AF33: 940557.87 | AG33: 276.63467 | AH33: 0 | AI33: 0 | AJ33: 0 | AL33: 0 | AO33: 0 | AP33: 130.25509 | AR33: ok
A34: 20231100073 | B34: ｽｰﾊﾟｰ万田酵素 分包150g | C34: 製品課 | E34: 150 | F34: EB | G34: 1.3583252 | H34: 0 | J34: 0 | K34: 880 | L34: =E34*K34 -> 132000 | M34: 179298.92 | N34: 191395.46 | S34: 201.10053 | T34: 176968.47 | U34: 139908.49 | V34: 2345 | W34: 269772.47 | Y34: 0 | Z34: 132000 | AA34: 56257.219 | AE34: 880 | AF34: 657333.65 | AG34: 746.97005 | AH34: 0 | AI34: 0 | AJ34: 0 | AL34: 0 | AO34: 0 | AP34: 130.25509 | AR34: ok
A35: 20231100074 | B35: ｽｰﾊﾟｰ万田酵素 分包450g | C35: 製品課 | E35: 450 | F35: EB | G35: 1.3583252 | H35: 0 | J35: 0 | K35: 350 | L35: =E35*K35 -> 157500 | M35: 213936.21 | N35: 228369.58 | S35: 1109.6177 | T35: 388366.19 | U35: 307036.22 | V35: 3040 | W35: 349726.36 | Y35: 0 | Z35: 157500 | AA35: 67125.091 | AE35: 350 | AF35: 952257.25 | AG35: 2720.735 | AH35: 0 | AI35: 0 | AJ35: 0 | AL35: 0 | AO35: 0 | AP35: 130.25509 | AR35: ok
A36: 20220600066 | B36: ｺﾞｰﾙﾄﾞEX155g | C36: 製品課 | E36: 155 | F36: FB | G36: 1.8947649 | H36: 0 | J36: 0 | K36: 1392 | L36: =E36*K36 -> 215760 | M36: 408814.48 | N36: 436395.46 | S36: 1525.2944 | T36: 2123209.7 | U36: 1678576.3 | V36: 5260 | W36: 605118.64 | Y36: 0 | Z36: 215760 | AA36: 91954.982 | AE36: 1392 | AF36: 2812045.4 | AG36: 2020.1476 | AH36: 0 | AI36: 0 | AJ36: 0 | AL36: 0 | AP36: 5.3945159 | AR36: ok
A37: 20221200022 | B37: ｺﾞｰﾙﾄﾞEX300g | C37: 製品課 | E37: 300 | F37: FB | G37: 1.8947649 | H37: 0 | J37: 0 | K37: 1080 | L37: =E37*K37 -> 324000 | M37: 613903.83 | N37: 655321.33 | S37: 1351.8023 | T37: 1459946.5 | U37: 1154210.8 | V37: 7075 | W37: 813919.08 | Y37: 0 | Z37: 324000 | AA37: 138085.9 | AE37: 1080 | AF37: 2761537.1 | AG37: 2556.9788 | AH37: 0 | AI37: 0 | AJ37: 0 | AL37: 0 | AP37: 0 | AR37: ok
A38: 20080100003 | B38: 試供品 万田酵素 MJ(5g) | C38: 製品課 | E38: 5 | F38: G | G38: 2.7753038 | H38: 0 | J38: 0 | K38: 1300 | L38: =E38*K38 -> 6500 | M38: 18039.475 | N38: 19256.522 | S38: 7.3021925 | T38: 9492.8502 | U38: 7504.8985 | V38: 225 | W38: 25884.352 | Y38: 0 | Z38: 6500 | AA38: 2770.2418 | AE38: 1300 | AF38: 55416.015 | AG38: 42.627704 | AH38: 0 | AI38: 0 | AJ38: 0 | AL38: 0 | AP38: 0 | AR38: ok
A39: 20110800295 | B39: 万田酵素 MJ | C39: 製品課 | E39: 90 | F39: G | G39: 2.7753038 | H39: 0 | J39: 0 | K39: 468 | L39: =E39*K39 -> 42120 | M39: 116895.8 | N39: 124782.26 | S39: 488.13626 | T39: 228447.77 | U39: 180607.22 | V39: 2295 | W39: 264020.4 | Y39: 0 | Z39: 42120 | AA39: 17951.167 | AE39: 468 | AF39: 587361.05 | AG39: 1255.045 | AH39: 0 | AI39: 0 | AJ39: 0 | AL39: 0 | AP39: 0 | AR39: ok
A40: 20231100078 | B40: 発酵しょうが 2.5g 支給用 | C40: 製品課 | E40: 2.5 | F40: GP | G40: 1.394799 | H40: 0 | J40: 0 | K40: 288000 | L40: =E40*K40 -> 720000 | M40: 1004255.3 | N40: 1072008.1 | S40: 0.43374357 | T40: 124918.15 | U40: 98758.328 | V40: 6020 | W40: 692550.23 | Y40: 0 | Z40: 720000 | AA40: 306857.56 | AE40: 288000 | AF40: 2170174.3 | AG40: 7.5353273 | AH40: 0 | AI40: 0 | AJ40: 0 | AL40: 0 | AR40: ok
A41: 20230600044 | B41: 万田酵素 ﾌﾟﾗｽ温 発酵しょうが 77.5g | C41: 製品課 | E41: 77.5 | F41: GP | G41: 1.394799 | H41: 0 | J41: 0 | K41: 190400 | L41: =E41*K41 -> 14756000 | M41: 20581654 | N41: 21970211 | S41: 33.686436 | T41: 6413897.3 | U41: 5070726.7 | V41: 43670 | W41: 5023865.2 | Y41: 0 | Z41: 14756000 | AA41: 6288875.2 | AE41: 190400 | AF41: 38353678 | AG41: 201.43739 | AH41: 0 | AI41: 0 | AJ41: 0 | AL41: 0 | AO41: 0 | AP41: 130.25509 | AR41: ok
A42: 20230600045 | B42: 万田酵素 ﾌﾟﾗｽ温 発酵しょうが 20g | C42: 製品課 | E42: 20 | F42: GP | G42: 1.394799 | H42: 0 | J42: 0 | K42: 8500 | L42: =E42*K42 -> 170000 | M42: 237115.83 | N42: 253113.03 | S42: 31.718523 | T42: 269607.44 | U42: 213147.42 | V42: 1945 | W42: 223755.85 | Y42: 0 | Z42: 170000 | AA42: 72452.479 | AE42: 8500 | AF42: 762468.78 | AG42: 89.702209 | AH42: 0 | AI42: 0 | AJ42: 0 | AL42: 0 | AO42: 0 | AP42: 130.25509 | AR42: ok
A43: 20230600046 | B43: 試供品 ﾌﾟﾗｽ温発酵しょうが 2.5g | C43: 製品課 | E43: 2.5 | F43: GP | G43: 1.394799 | H43: 0 | J43: 0 | K43: 212000 | L43: =E43*K43 -> 530000 | M43: 739243.47 | N43: 789117.11 | S43: 5.1292794 | T43: 1087407.2 | U43: 859687.11 | V43: 19655 | W43: 2261142 | Y43: 0 | Z43: 530000 | AA43: 225881.26 | AE43: 212000 | AF43: 4135827.5 | AG43: 19.50862 | AH43: 0 | AI43: 0 | AJ43: 0 | AL43: 0 | AO43: 0 | AP43: 130.25509 | AR43: ok
A44: 20241200012 | B44: 万田酵素ﾌﾟﾗｽ温発酵しょうが 75g 5g×15包 | C44: 製品課 | E44: 75 | F44: GP | G44: 1.394799 | H44: 0 | J44: 0 | K44: 300 | L44: =E44*K44 -> 22500 | M44: 31382.978 | N44: 33500.255 | S44: 670.33405 | T44: 201100.21 | U44: 158986.68 | V44: 930 | W44: 106988.66 | Y44: 0 | Z44: 22500 | AA44: 9589.2987 | AE44: 300 | AF44: 309064.89 | AG44: 1030.2163 | AH44: 0 | AI44: 0 | AJ44: 0 | AL44: 0 | AO44: 0 | AP44: 130.25509 | AR44: ok
A45: 20231200033 | B45: 万田酵素分包75g （中国虹越） | C45: 製品課 | E45: 75 | F45: KOL | G45: 1.3000228 | H45: 0 | J45: 0 | K45: 60 | L45: =E45*K45 -> 4500 | M45: 5850.1027 | N45: 6244.7845 | S45: 138.88233 | T45: 8332.9396 | U45: 6587.8914 | V45: 220 | W45: 25309.145 | Y45: 0 | Z45: 4500 | AA45: 1917.8597 | AE45: 60 | AF45: 40059.68 | AG45: 667.66134 | AH45: 0 | AI45: 0 | AJ45: 0 | AL45: 0 | AO45: 0 | AP45: 130.25509 | AR45: ok
A46: 20241100041 | B46: 試供品 万田酵素分包5g(中国虹越) | C46: 製品課 | E46: 5 | F46: KOL | G46: 1.3000228 | H46: 0 | J46: 0 | K46: 10000 | L46: =E46*K46 -> 50000 | M46: 65001.142 | N46: 69386.494 | S46: 1458.6349 | T46: 14586349 | U46: 11531739 | V46: 995 | W46: 114466.36 | Y46: 0 | Z46: 50000 | AA46: 21309.553 | AE46: 10000 | AF46: 11736902 | AG46: 1173.6902 | AH46: 0 | AI46: 0 | AJ46: 0 | AL46: 0 | AO46: 0 | AP46: 130.25509 | AR46: ok
A47: 20250300087 | B47: 万田酵素 分包150g (中国) | C47: 製品課 | E47: 150 | F47: KOL | G47: 1.3000228 | H47: 0 | J47: 0 | K47: 7000 | L47: =E47*K47 -> 1050000 | M47: 1365024 | N47: 1457116.4 | S47: 97.628938 | T47: 683402.57 | U47: 540287.36 | V47: 17560 | W47: 2020129.9 | Y47: 0 | Z47: 1050000 | AA47: 447500.61 | AE47: 7000 | AF47: 4465034.2 | AG47: 637.86204 | AH47: 0 | AI47: 0 | AJ47: 0 | AL47: 0 | AO47: 0 | AP47: 130.25509 | AR47: ok
A48: 20171000004 | B48: 万田酵素 MULBERRY 分包 77.5g | C48: 製品課 | E48: 77.5 | F48: MP | G48: 1.1798248 | H48: 0 | J48: 0 | K48: 187600 | L48: =E48*K48 -> 14539000 | M48: 17153473 | N48: 18310745 | S48: 36.096046 | T48: 6771618.2 | U48: 5353535.2 | V48: 42810 | W48: 4924929.5 | Y48: 0 | Z48: 14539000 | AA48: 6196391.7 | AE48: 187600 | AF48: 34785601 | AG48: 185.42431 | AH48: 0 | AI48: 0 | AJ48: 0 | AL48: 0 | AO48: 613.04597 | AP48: 1413.9773 | AR48: ok
A49: 20171000006 | B49: 万田酵素 MULBERRY 分包20g | C49: 製品課 | E49: 20 | F49: MP | G49: 1.1798248 | H49: 0 | J49: 0 | K49: 2000 | L49: =E49*K49 -> 40000 | M49: 47192.991 | N49: 50376.903 | S49: 26.4992 | T49: 52998.4 | U49: 41899.704 | V49: 795 | W49: 91458.045 | Y49: 0 | Z49: 40000 | AA49: 17047.642 | AE49: 2000 | AF49: 200782.29 | AG49: 100.39115 | AH49: 0 | AI49: 0 | AJ49: 0 | AL49: 0 | AO49: 218.00341 | AP49: 0 | AR49: ok
A50: 20171000010 | B50: 万田酵素 MULBERRY ﾁｭｰﾌﾞﾀｲﾌﾟ 26×3本 | C50: 製品課 | E50: 78 | F50: MP | G50: 1.1798248 | H50: 0 | J50: 0 | K50: 850 | L50: =E50*K50 -> 66300 | M50: 78222.383 | N50: 83499.717 | S50: 373.77788 | T50: 317711.2 | U50: 251177.49 | V50: 3050 | W50: 350876.78 | Y50: 0 | Z50: 66300 | AA50: 28256.467 | AE50: 850 | AF50: 713810.46 | AG50: 839.77701 | AH50: 0 | AI50: 0 | AJ50: 0 | AL50: 0 | AO50: 5182.303 | AP50: 0 | AR50: ok
A51: 20181100045 | B51: 万田酵素 MULBERRY 分包35g 2.5g×14包 | C51: 製品課 | E51: 35 | F51: MP | G51: 1.1798248 | H51: 0 | J51: 0 | K51: 300 | L51: =E51*K51 -> 10500 | M51: 12388.16 | N51: 13223.937 | S51: 44.454165 | T51: 13336.249 | U51: 10543.43 | V51: 195 | W51: 22433.105 | Y51: 0 | Z51: 10500 | AA51: 4475.0061 | AE51: 300 | AF51: 50675.478 | AG51: 168.91826 | AH51: 0 | AI51: 0 | AJ51: 0 | AL51: 0 | AP51: 2.6255878 | AR51: ok
A52: 20200200034 | B52: 万田酵素MULBERRY 分包 10g 2.5×4包 | C52: 製品課 | E52: 10 | F52: MP | G52: 1.1798248 | H52: 0 | J52: 0 | K52: 3945 | L52: =E52*K52 -> 39450 | M52: 46544.088 | N52: 49684.221 | S52: 161.36218 | T52: 636573.8 | U52: 503265.26 | V52: 3340 | W52: 384238.83 | Y52: 0 | Z52: 39450 | AA52: 16813.237 | AE52: 3945 | AF52: 954001.55 | AG52: 241.82549 | AH52: 0 | AI52: 0 | AJ52: 0 | AL52: 0 | AP52: 450.13475 | AR52: ok
A53: 20220100027 | B53: MULBERRY 2.5g 支給用 | C53: 製品課 | E53: 2.5 | F53: MP | G53: 1.1798248 | H53: 0 | J53: 0 | K53: 126000 | L53: =E53*K53 -> 315000 | M53: 371644.81 | N53: 396718.11 | S53: 0.45126549 | T53: 56859.452 | U53: 44952.191 | V53: 2780 | W53: 319815.56 | Y53: 0 | Z53: 315000 | AA53: 134250.18 | AE53: 126000 | AF53: 895736.04 | AG53: 7.1090162 | AH53: 0 | AI53: 0 | AJ53: 0 | AL53: 0 | AP53: 0 | AR53: ok
A54: 20230900058 | B54: 万田酵素 MULBERRY 分包12.5g | C54: 製品課 | E54: 12.5 | F54: MP | G54: 1.1798248 | H54: 0 | J54: 0 | K54: 3000 | L54: =E54*K54 -> 37500 | M54: 44243.429 | N54: 47228.347 | S54: 16.590992 | T54: 49772.976 | U54: 39349.734 | V54: 790 | W54: 90882.838 | Y54: 0 | Z54: 37500 | AA54: 15982.165 | AE54: 3000 | AF54: 193443.08 | AG54: 64.481028 | AH54: 0 | AI54: 0 | AJ54: 0 | AL54: 0 | AO54: 0 | AP54: 130.25509 | AR54: ok
A55: 20060200007 | B55: 万田酵素 金印145g | C55: 製品課 | E55: 145 | F55: O | G55: 1.3228108 | H55: 0 | J55: 0 | K55: 180 | L55: =E55*K55 -> 26100 | M55: 34525.363 | N55: 36854.643 | S55: 899.57608 | T55: 161923.69 | U55: 128014.33 | V55: 665 | W55: 76502.642 | Y55: 0 | Z55: 26100 | AA55: 11123.587 | AE55: 180 | AF55: 252495.2 | AG55: 1402.7511 | AH55: 0 | AI55: 0 | AJ55: 0 | AL55: 0 | AP55: 0 | AR55: ok
A56: 20071000014 | B56: 試供品 金印 5g | C56: 製品課 | E56: 5 | F56: O | G56: 1.3228108 | H56: 0 | J56: 0 | K56: 900 | L56: =E56*K56 -> 4500 | M56: 5952.6487 | N56: 6354.2488 | S56: 10.440942 | T56: 9396.8479 | U56: 7429.0006 | V56: 110 | W56: 12654.572 | Y56: 0 | Z56: 4500 | AA56: 1917.8597 | AE56: 900 | AF56: 28355.681 | AG56: 31.506313 | AH56: 0 | AI56: 0 | AJ56: 0 | AL56: 0 | AO56: 10.186684 | AP56: 67.070854 | AR56: ok
A57: 20071100028 | B57: 万田酵素 金印 分包150g | C57: 製品課 | E57: 150 | F57: O | G57: 1.3228108 | H57: 0 | J57: 0 | K57: 900 | L57: =E57*K57 -> 135000 | M57: 178579.46 | N57: 190627.46 | S57: 323.2873 | T57: 290958.57 | U57: 230027.29 | V57: 2200 | W57: 253091.45 | Y57: 0 | Z57: 135000 | AA57: 57535.792 | AE57: 900 | AF57: 731281.99 | AG57: 812.53554 | AH57: 0 | AI57: 0 | AJ57: 0 | AL57: 0 | AP57: 0 | AR57: ok
A58: 20110800312 | B58: MANDA KOHSO GOLD 145ｇ | C58: 製品課 | E58: 145 | F58: O | G58: 1.3228108 | H58: 0 | J58: 0 | K58: 144 | L58: =E58*K58 -> 20880 | M58: 27620.29 | N58: 29483.714 | S58: 2009.6203 | T58: 289385.32 | U58: 228783.49 | V58: 780 | W58: 89732.422 | Y58: 0 | Z58: 20880 | AA58: 8898.8692 | AE58: 144 | AF58: 356898.5 | AG58: 2478.4618 | AH58: 0 | AI58: 0 | AJ58: 0 | AL58: 0 | AP58: 209.27742 | AR58: ok
A59: 20140100011 | B59: Man-Koso GOLD 145g | C59: 製品課 | E59: 145 | F59: O | G59: 1.3228108 | H59: 0 | J59: 0 | K59: 166 | L59: =E59*K59 -> 24070 | M59: 31840.057 | N59: 33988.171 | S59: 2510.1255 | T59: 416680.83 | U59: 329421.33 | V59: 605 | W59: 69600.148 | Y59: 0 | Z59: 24070 | AA59: 10258.419 | AE59: 166 | AF59: 443268.07 | AG59: 2670.2896 | AH59: 0 | AI59: 0 | AJ59: 0 | AL59: 0 | AP59: 0 | AR59: ok
A60: 20061200012 | B60: 万田酵素 145g(販売店向け) | C60: 製品課 | E60: 145 | F60: P | G60: 1.2657092 | H60: 0 | J60: 0 | K60: 4950 | L60: =E60*K60 -> 717750 | M60: 908462.79 | N60: 969752.94 | S60: 225.63506 | T60: 1116893.5 | U60: 882998.52 | V60: 11710 | W60: 1347136.7 | Y60: 0 | Z60: 717750 | AA60: 305898.63 | AE60: 4950 | AF60: 3505786.8 | AG60: 708.23976 | AH60: 0 | AI60: 0 | AJ60: 0 | AL60: 0 | AO60: 16.136684 | AP60: 59.738819 | AR60: ok
A61: 20070300033 | B61: 万田酵素 分包150g(販売店向け) | C61: 製品課 | E61: 150 | F61: P | G61: 1.2657092 | H61: 0 | J61: 0 | K61: 13800 | L61: =E61*K61 -> 2070000 | M61: 2620018.1 | N61: 2796779.6 | S61: 106.38363 | T61: 1468094.1 | U61: 1160652.2 | V61: 29125 | W61: 3350585.6 | Y61: 0 | Z61: 2070000 | AA61: 882215.48 | AE61: 13800 | AF61: 8190233 | AG61: 593.49514 | AH61: 0 | AI61: 0 | AJ61: 0 | AL61: 0 | AP61: 0 | AR61: ok
A62: 20080100023 | B62: 試供品 万田酵素 5g(販売店向け) | C62: 製品課 | E62: 5 | F62: P | G62: 1.2657092 | H62: 0 | J62: 0 | K62: 98000 | L62: =E62*K62 -> 490000 | M62: 620197.52 | N62: 662039.62 | S62: 3.5972921 | T62: 352534.62 | U62: 278708.34 | V62: 10335 | W62: 1188954.6 | Y62: 0 | Z62: 490000 | AA62: 208833.62 | AE62: 98000 | AF62: 2338536.2 | AG62: 23.862614 | AH62: 0 | AI62: 0 | AJ62: 0 | AL62: 0 | AP62: 0 | AR62: ok
A63: 20090100014 | B63: 万田酵素 300g(販売店限定品) | C63: 製品課 | E63: 300 | F63: P | G63: 1.2657092 | H63: 0 | J63: 0 | K63: 414 | L63: =E63*K63 -> 124200 | M63: 157201.08 | N63: 167806.78 | S63: 931.17129 | T63: 385504.92 | U63: 304774.14 | V63: 3005 | W63: 345699.91 | Y63: 0 | Z63: 124200 | AA63: 52932.929 | AE63: 414 | AF63: 871213.76 | AG63: 2104.3811 | AH63: 0 | AI63: 0 | AJ63: 0 | AL63: 0 | AO63: 0 | AP63: 1248.6436 | AR63: ok
A64: 20090300004 | B64: 万田酵素 分包50g | C64: 製品課 | E64: 50 | F64: P | G64: 1.2657092 | H64: 0 | J64: 0 | K64: 750 | L64: =E64*K64 -> 37500 | M64: 47464.096 | N64: 50666.298 | S64: 401.99998 | T64: 301499.99 | U64: 238361.16 | V64: 1365 | W64: 157031.74 | Y64: 0 | Z64: 37500 | AA64: 15982.165 | AE64: 750 | AF64: 462041.36 | AG64: 616.05515 | AH64: 0 | AI64: 0 | AJ64: 0 | AL64: 0 | AP64: 0 | AR64: ok
A65: 20110300007 | B65: Man-Koso PREMIUM 145g | C65: 製品課 | E65: 145 | F65: P | G65: 1.2657092 | H65: 0 | J65: 0 | K65: 4454 | L65: =E65*K65 -> 645830 | M65: 817432.98 | N65: 872581.74 | S65: 638.1255 | T65: 2842211 | U65: 2247007.4 | V65: 9260 | W65: 1065284.9 | Y65: 0 | Z65: 645830 | AA65: 275246.97 | AE65: 4454 | AF65: 4460121 | AG65: 1001.3743 | AH65: 0 | AI65: 0 | AJ65: 0 | AL65: 0 | AP65: 0 | AR65: ok
A66: 20110800918 | B66: Man-Koso PREMIUM 分包150g | C66: 製品課 | E66: 150 | F66: P | G66: 1.2657092 | H66: 0 | J66: 0 | K66: 1523 | L66: =E66*K66 -> 228450 | M66: 289151.27 | N66: 308659.09 | S66: 1325.6438 | T66: 2018955.6 | U66: 1596154.6 | V66: 4850 | W66: 557951.6 | Y66: 0 | Z66: 228450 | AA66: 97363.346 | AE66: 1523 | AF66: 2560128.6 | AG66: 1680.9774 | AH66: 0 | AI66: 0 | AJ66: 0 | AL66: 0 | AP66: 383.89592 | AR66: ok
A67: 20210700007 | B67: MKﾐｸｽﾁｬｰ(ﾍﾟｰｽﾄ) 1kg 中栓付き容器 | C67: 製品課 | E67: 1000 | F67: P | G67: 1.2657092 | H67: 0 | J67: 0 | K67: 18 | L67: =E67*K67 -> 18000 | M67: 22782.766 | N67: 24319.823 | S67: 156.43322 | T67: 2815.798 | U67: 2226.1257 | V67: 330 | W67: 37963.717 | Y67: 0 | Z67: 18000 | AA67: 7671.439 | AE67: 18 | AF67: 72181.105 | AG67: 4010.0614 | AH67: 0 | AI67: 0 | AJ67: 0 | AL67: 0 | AP67: 0 | AR67: ok
A68: 20220100030 | B68: P 2.5g×2 支給用 | C68: 製品課 | E68: 5 | F68: P | G68: 1.2657092 | H68: 0 | J68: 0 | K68: 24000 | L68: =E68*K68 -> 120000 | M68: 151885.11 | N68: 162132.15 | S68: 1.6184867 | T68: 38843.682 | U68: 30709.206 | V68: 555 | W68: 63848.069 | Y68: 0 | Z68: 120000 | AA68: 51142.926 | AE68: 24000 | AF68: 307832.35 | AG68: 12.826348 | AH68: 0 | AI68: 0 | AJ68: 0 | AL68: 0 | AP68: 10.801915 | AR68: ok
A69: 20221200036 | B69: 植物発酵エキス 万田酵素 | C69: 製品課 | E69: 1000 | F69: P | G69: 1.2657092 | H69: 0 | J69: 0 | K69: 12 | L69: =E69*K69 -> 12000 | M69: 15188.511 | N69: 16213.215 | S69: 156.43322 | T69: 1877.1986 | U69: 1484.0838 | V69: 285 | W69: 32786.846 | Y69: 0 | Z69: 12000 | AA69: 5114.2926 | AE69: 12 | AF69: 55598.438 | AG69: 4633.2032 | AH69: 0 | AI69: 0 | AJ69: 0 | AL69: 0 | AP69: 0 | AR69: ok
A70: 20230700024 | B70: 万田酵素(宇宙用) | C70: 製品課 | E70: 5 | F70: P | G70: 1.2657092 | H70: 0 | J70: 0 | K70: 21 | L70: =E70*K70 -> 105 | M70: 132.89947 | N70: 141.86563 | S70: 194.78211 | T70: 4090.4243 | U70: 3233.8254 | V70: 310 | W70: 35662.886 | Y70: 0 | Z70: 105 | AA70: 44.750061 | AE70: 21 | AF70: 39083.327 | AG70: 1861.1108 | AH70: 0 | AI70: 0 | AJ70: 0 | AL70: 0 | AO70: 0 | AP70: 130.25509 | AR70: ok
A71: 20240400018 | B71: 万田酵素（宇宙用）2.5g×4包 店頭販売用 | C71: 製品課 | E71: 10 | F71: P | G71: 1.2657092 | H71: 0 | J71: 0 | K71: 404 | L71: =E71*K71 -> 4040 | M71: 5113.4652 | N71: 5458.4491 | S71: 360.69597 | T71: 145721.17 | U71: 115204.87 | V71: 985 | W71: 113315.94 | Y71: 0 | Z71: 4040 | AA71: 1721.8119 | AE71: 404 | AF71: 235701.08 | AG71: 583.41851 | AH71: 0 | AI71: 0 | AJ71: 0 | AL71: 0 | AO71: 0 | AP71: 130.25509 | AR71: ok
A72: 20240400019 | B72: 万田酵素（宇宙用）2.5g×8包 ｲﾍﾞﾝﾄｺﾗﾎﾞ用 | C72: 製品課 | E72: 20 | F72: P | G72: 1.2657092 | H72: 0 | J72: 0 | K72: 5004 | L72: =E72*K72 -> 100080 | M72: 126672.18 | N72: 135218.22 | S72: 68.543971 | T72: 342994.03 | U72: 271165.7 | V72: 6070 | W72: 698302.31 | Y72: 0 | Z72: 100080 | AA72: 42653.201 | AE72: 5004 | AF72: 1147339.4 | AG72: 229.28446 | AH72: 0 | AI72: 0 | AJ72: 0 | AL72: 0 | AO72: 0 | AP72: 130.25509 | AR72: ok
A73: 20240400020 | B73: 万田酵素(宇宙用) 2.5g×8包 通信販売用 | C73: 製品課 | E73: 20 | F73: P | G73: 1.2657092 | H73: 0 | J73: 0 | K73: 1000 | L73: =E73*K73 -> 20000 | M73: 25314.184 | N73: 27022.025 | S73: 167.48118 | T73: 167481.18 | U73: 132407.99 | V73: 1145 | W73: 131722.59 | Y73: 0 | Z73: 20000 | AA73: 8523.8211 | AE73: 1000 | AF73: 299676.43 | AG73: 299.67643 | AH73: 0 | AI73: 0 | AJ73: 0 | AL73: 0 | AO73: 0 | AP73: 130.25509 | AR73: ok
A74: 20170400004 | B74: 試供品 万田酵素 GINGER 2.5g | C74: 製品課 | E74: 2.5 | F74: PE | G74: 1.1499334 | H74: 0 | J74: 0 | K74: 187200 | L74: =E74*K74 -> 468000 | M74: 538168.81 | N74: 574476.78 | S74: 2.706436 | T74: 506644.82 | U74: 400545.45 | V74: 17615 | W74: 2026457.2 | Y74: 0 | Z74: 468000 | AA74: 199457.41 | AE74: 187200 | AF74: 3200936.8 | AG74: 17.099022 | AH74: 0 | AI74: 0 | AJ74: 0 | AL74: 0 | AP74: 0 | AR74: ok
A75: 20170400005 | B75: 万田酵素 GINGER 分包20g | C75: 製品課 | E75: 20 | F75: PE | G75: 1.1499334 | H75: 0 | J75: 0 | K75: 4000 | L75: =E75*K75 -> 80000 | M75: 91994.668 | N75: 98201.16 | S75: 26.569678 | T75: 106278.71 | U75: 84022.283 | V75: 695 | W75: 79953.889 | Y75: 0 | Z75: 80000 | AA75: 34095.284 | AE75: 4000 | AF75: 296272.62 | AG75: 74.068154 | AH75: 0 | AI75: 0 | AJ75: 0 | AL75: 0 | AP75: 0 | AR75: ok
A76: 20170400006 | B76: 万田酵素GINGER分包77.5g | C76: 製品課 | E76: 77.5 | F76: PE | G76: 1.1499334 | H76: 0 | J76: 0 | K76: 420200 | L76: =E76*K76 -> 32565500 | M76: 37448155 | N76: 39974623 | S76: 30.431406 | T76: 12787277 | U76: 10109421 | V76: 96955 | W76: 11153855 | Y76: 0 | Z76: 32565500 | AA76: 13879125 | AE76: 420200 | AF76: 75117024 | AG76: 178.76493 | AH76: 0 | AI76: 0 | AJ76: 0 | AL76: 0 | AP76: 0 | AR76: ok
A77: 20170400017 | B77: 万田酵素 GINGER 分包 35g | C77: 製品課 | E77: 35 | F77: PE | G77: 1.1499334 | H77: 0 | J77: 0 | K77: 550 | L77: =E77*K77 -> 19250 | M77: 22136.217 | N77: 23629.654 | S77: 56.048379 | T77: 30826.608 | U77: 24371.033 | V77: 385 | W77: 44291.003 | Y77: 0 | Z77: 19250 | AA77: 8204.1778 | AE77: 550 | AF77: 100495.87 | AG77: 182.71976 | AH77: 0 | AI77: 0 | AJ77: 0 | AL77: 0 | AO77: 579.93393 | AP77: 775.36993 | AR77: ok
A78: 20171000009 | B78: 万田酵素GINGERﾁｭｰﾌﾞﾀｲﾌﾟ26×3本 | C78: 製品課 | E78: 78 | F78: PE | G78: 1.1499334 | H78: 0 | J78: 0 | K78: 900 | L78: =E78*K78 -> 70200 | M78: 80725.321 | N78: 86171.518 | S78: 373.77738 | T78: 336399.64 | U78: 265952.28 | V78: 2730 | W78: 314063.48 | Y78: 0 | Z78: 70200 | AA78: 29918.612 | AE78: 900 | AF78: 696105.89 | AG78: 773.45099 | AH78: 0 | AI78: 0 | AJ78: 0 | AL78: 0 | AO78: 488.0448 | AP78: 3032.0312 | AR78: ok
A79: 20181100042 | B79: 万田酵素 GINGER2.5g×4包 | C79: 製品課 | E79: 10 | F79: PE | G79: 1.1499334 | H79: 0 | J79: 0 | K79: 900 | L79: =E79*K79 -> 9000 | M79: 10349.4 | N79: 11047.63 | S79: 62.609483 | T79: 56348.535 | U79: 44548.268 | V79: 940 | W79: 108139.07 | Y79: 0 | Z79: 9000 | AA79: 3835.7195 | AE79: 900 | AF79: 167570.69 | AG79: 186.18966 | AH79: 0 | AI79: 0 | AJ79: 0 | AL79: 0 | AP79: 0 | AR79: ok
A80: 20190100014 | B80: 万田酵素GINGER分包50ｇ | C80: 製品課 | E80: 50 | F80: PE | G80: 1.1499334 | H80: 0 | J80: 0 | K80: 6000 | L80: =E80*K80 -> 300000 | M80: 344980.01 | N80: 368254.35 | S80: 42.97312 | T80: 257838.72 | U80: 203843.25 | V80: 1760 | W80: 202473.16 | Y80: 0 | Z80: 300000 | AA80: 127857.32 | AE80: 6000 | AF80: 902428.07 | AG80: 150.40468 | AH80: 0 | AI80: 0 | AJ80: 0 | AL80: 0 | AO80: 27.511771 | AP80: 124.33255 | AR80: ok
A81: 20220100028 | B81: GINGER 2.5g 支給用 | C81: 製品課 | E81: 2.5 | F81: PE | G81: 1.1499334 | H81: 0 | J81: 0 | K81: 110000 | L81: =E81*K81 -> 275000 | M81: 316231.67 | N81: 337566.49 | S81: 0.46513795 | T81: 51165.174 | U81: 40450.385 | V81: 2345 | W81: 269772.47 | Y81: 0 | Z81: 275000 | AA81: 117202.54 | AE81: 110000 | AF81: 764991.88 | AG81: 6.9544717 | AH81: 0 | AI81: 0 | AJ81: 0 | AL81: 0 | AP81: 16.248724 | AR81: ok
A82: 20050700013 | B82: 万田酵素 ｊ 分包150g | C82: 製品課 | E82: 150 | F82: PG | G82: 1.4973298 | H82: 0 | J82: 0 | K82: 150 | L82: =E82*K82 -> 22500 | M82: 33689.92 | N82: 35962.837 | S82: 418.80133 | T82: 62820.199 | U82: 49664.665 | V82: 455 | W82: 52343.913 | Y82: 0 | Z82: 22500 | AA82: 9589.2987 | AE82: 150 | AF82: 147560.71 | AG82: 983.73809 | AH82: 0 | AI82: 0 | AJ82: 0 | AL82: 0 | AP82: 0 | AR82: ok
A83: 20080300003 | B83: 試供品 万田酵素 ｊ 5g | C83: 製品課 | E83: 5 | F83: PG | G83: 1.4973298 | H83: 0 | J83: 0 | K83: 3500 | L83: =E83*K83 -> 17500 | M83: 26203.271 | N83: 27971.095 | S83: 13.150839 | T83: 46027.935 | U83: 36388.964 | V83: 1245 | W83: 143226.75 | Y83: 0 | Z83: 17500 | AA83: 7458.3434 | AE83: 3500 | AF83: 215045.15 | AG83: 61.441472 | AH83: 0 | AI83: 0 | AJ83: 0 | AL83: 0 | AP83: 0 | AR83: ok
A84: 20091200010 | B84: MANDA CARE PLUS 75g(梅) | C84: 製品課 | E84: 75 | F84: PG | G84: 1.4973298 | H84: 0 | J84: 0 | K84: 1380 | L84: =E84*K84 -> 103500 | M84: 154973.63 | N84: 165429.05 | S84: 143.75837 | T84: 198386.55 | U84: 156841.3 | V84: 1990 | W84: 228932.72 | Y84: 0 | Z84: 103500 | AA84: 44110.774 | AE84: 1380 | AF84: 595313.84 | AG84: 431.38684 | AH84: 0 | AI84: 0 | AJ84: 0 | AL84: 0 | AO84: 51.993684 | AP84: 0 | AR84: ok
A85: 20091200011 | B85: MANDA CARE PLUS 5g(梅) | C85: 製品課 | E85: 5 | F85: PG | G85: 1.4973298 | H85: 0 | J85: 0 | K85: 180 | L85: =E85*K85 -> 900 | M85: 1347.5968 | N85: 1438.5135 | S85: 27.501403 | T85: 4950.2526 | U85: 3913.5921 | V85: 190 | W85: 21857.898 | Y85: 0 | Z85: 900 | AA85: 383.57195 | AE85: 180 | AF85: 27593.575 | AG85: 153.29764 | AH85: 0 | AI85: 0 | AJ85: 0 | AL85: 0 | AO85: 0 | AP85: 1528.5209 | AR85: ok
A86: 20221100028 | B86: 万田酵素 j 分包50ｇ | C86: 製品課 | E86: 50 | F86: PG | G86: 1.4973298 | H86: 0 | J86: 0 | K86: 100 | L86: =E86*K86 -> 5000 | M86: 7486.6489 | N86: 7991.7415 | S86: 160.23895 | T86: 16023.895 | U86: 12668.24 | V86: 175 | W86: 20132.274 | Y86: 0 | Z86: 5000 | AA86: 2130.9553 | AE86: 100 | AF86: 42923.211 | AG86: 429.23211 | AH86: 0 | AI86: 0 | AJ86: 0 | AL86: 0 | AP86: 0 | AR86: ok
A87: 20091200015 | B87: ﾅﾁｭﾗﾙ酵素ﾌﾞﾙｰﾍﾞﾘｰﾌﾟﾗｽ 分包150g | C87: 製品課 | E87: 150 | F87: PR | G87: 1.8060342 | H87: 0 | J87: 0 | K87: 3000 | L87: =E87*K87 -> 450000 | M87: 812715.37 | N87: 867545.84 | S87: 3936.6387 | T87: 11809916 | U87: 9336734.6 | V87: 10085 | W87: 1160194.2 | Y87: 0 | Z87: 450000 | AA87: 191785.97 | AE87: 3000 | AF87: 11556261 | AG87: 3852.0869 | AH87: 0 | AI87: 0 | AJ87: 0 | AL87: 0 | AO87: 134.24327 | AP87: 454.60488 | AR87: ok
A88: 20091200016 | B88: 試供品 ﾅﾁｭﾗﾙ酵素ﾌﾞﾙｰﾍﾞﾘｰﾌﾟﾗｽ 5g | C88: 製品課 | E88: 5 | F88: PR | G88: 1.8060342 | H88: 0 | J88: 0 | K88: 3000 | L88: =E88*K88 -> 15000 | M88: 27090.512 | N88: 28918.195 | S88: 1934.1849 | T88: 5802554.8 | U88: 4587408.9 | V88: 315 | W88: 36238.093 | Y88: 0 | Z88: 15000 | AA88: 6392.8658 | AE88: 3000 | AF88: 4658958 | AG88: 1552.986 | AH88: 0 | AI88: 0 | AJ88: 0 | AL88: 0 | AP88: 0 | AR88: ok
A89: 20120900082 | B89: NONI酵素 分包60g | C89: 製品課 | E89: 60 | F89: PSA | G89: 1.7935093 | H89: 0 | J89: 0 | K89: 23000 | L89: =E89*K89 -> 1380000 | M89: 2475042.8 | N89: 2642023.5 | S89: 67.898378 | T89: 1561662.7 | U89: 1234626 | V89: 34435 | W89: 3961456.3 | Y89: 0 | Z89: 1380000 | AA89: 588143.65 | AE89: 23000 | AF89: 8426249.5 | AG89: 366.35867 | AH89: 0 | AI89: 0 | AJ89: 0 | AL89: 0 | AP89: 4993.4274 | AR89: ok
A90: 20130100001 | B90: NONI酵素 300g ファミリーサイズ | C90: 製品課 | E90: 300 | F90: PSA | G90: 1.7935093 | H90: 0 | J90: 0 | K90: 1800 | L90: =E90*K90 -> 540000 | M90: 968495 | N90: 1033835.3 | S90: 550.96919 | T90: 991744.53 | U90: 784057.68 | V90: 10030 | W90: 1153866.9 | Y90: 0 | Z90: 540000 | AA90: 230143.17 | AE90: 1800 | AF90: 3201903 | AG90: 1778.835 | AH90: 0 | AI90: 0 | AJ90: 0 | AL90: 0 | AP90: 0 | AR90: ok
A91: 20240600040 | B91: NONI酵素 分包14g 2g×7包 | C91: 製品課 | E91: 14 | F91: PSA | G91: 1.7935093 | H91: 0 | J91: 0 | K91: 2000 | L91: =E91*K91 -> 28000 | M91: 50218.259 | N91: 53606.273 | S91: 113.46495 | T91: 226929.91 | U91: 179407.22 | V91: 1695 | W91: 194995.46 | Y91: 0 | Z91: 28000 | AA91: 11933.35 | AE91: 2000 | AF91: 439942.3 | AG91: 219.97115 | AH91: 0 | AI91: 0 | AJ91: 0 | AL91: 0 | AO91: 0 | AP91: 130.25509 | AR91: ok
A92: 20170400007 | B92: 試供品 万田酵素 STANDARD 2.5g | C92: 製品課 | E92: 2.5 | F92: PX | G92: 1.2530514 | H92: 0 | J92: 0 | K92: 58000 | L92: =E92*K92 -> 145000 | M92: 181692.45 | N92: 193950.47 | S92: 2.9489439 | T92: 171038.74 | U92: 135220.55 | V92: 5595 | W92: 643657.57 | Y92: 0 | Z92: 145000 | AA92: 61797.703 | AE92: 58000 | AF92: 1034626.3 | AG92: 17.838384 | AH92: 0 | AI92: 0 | AJ92: 0 | AL92: 0 | AP92: 0 | AR92: ok
A93: 20170400008 | B93: 万田酵素 STANDARD 分包20g | C93: 製品課 | E93: 20 | F93: PX | G93: 1.2530514 | H93: 0 | J93: 0 | K93: 1000 | L93: =E93*K93 -> 20000 | M93: 25061.028 | N93: 26751.789 | S93: 26.819383 | T93: 26819.383 | U93: 21202.984 | V93: 245 | W93: 28185.184 | Y93: 0 | Z93: 20000 | AA93: 8523.8211 | AE93: 1000 | AF93: 84663.778 | AG93: 84.663778 | AH93: 0 | AI93: 0 | AJ93: 0 | AL93: 0 | AP93: 0 | AR93: ok
A94: 20170400009 | B94: 万田酵素STANDARD分包77.5g | C94: 製品課 | E94: 77.5 | F94: PX | G94: 1.2530514 | H94: 0 | J94: 0 | K94: 127600 | L94: =E94*K94 -> 9889000 | M94: 12391425 | N94: 13227422 | S94: 36.475339 | T94: 4654253.3 | U94: 3679579.6 | V94: 49810 | W94: 5730220.4 | Y94: 0 | Z94: 9889000 | AA94: 4214603.3 | AE94: 127600 | AF94: 26851826 | AG94: 210.4375 | AH94: 0 | AI94: 0 | AJ94: 0 | AL94: 0 | AP94: 0 | AR94: ok
A95: 20170400016 | B95: 万田酵素 STANDARD 分包35g | C95: 製品課 | E95: 35 | F95: PX | G95: 1.2530514 | H95: 0 | J95: 0 | K95: 950 | L95: =E95*K95 -> 33250 | M95: 41663.958 | N95: 44474.85 | S95: 287.17036 | T95: 272811.85 | U95: 215680.77 | V95: 665 | W95: 76502.642 | Y95: 0 | Z95: 33250 | AA95: 14170.853 | AE95: 950 | AF95: 350829.11 | AG95: 369.2938 | AH95: 0 | AI95: 0 | AJ95: 0 | AL95: 0 | AP95: 0 | AR95: ok
A96: 20171000008 | B96: 万田酵素STANDARDﾁｭｰﾌﾞﾀｲﾌﾟ26×3本 | C96: 製品課 | E96: 78 | F96: PX | G96: 1.2530514 | H96: 0 | J96: 0 | K96: 500 | L96: =E96*K96 -> 39000 | M96: 48869.004 | N96: 52165.989 | S96: 373.77788 | T96: 186888.94 | U96: 147751.47 | V96: 1640 | W96: 188668.17 | Y96: 0 | Z96: 39000 | AA96: 16621.451 | AE96: 500 | AF96: 405207.08 | AG96: 810.41415 | AH96: 0 | AI96: 0 | AJ96: 0 | AL96: 0 | AO96: 397.21884 | AP96: 2021.4052 | AR96: ok
A97: 20180500084 | B97: 万田酵素 STANDARD 分包50g | C97: 製品課 | E97: 50 | F97: PX | G97: 1.2530514 | H97: 0 | J97: 0 | K97: 23000 | L97: =E97*K97 -> 1150000 | M97: 1441009.1 | N97: 1538227.9 | S97: 46.391094 | T97: 1066995.2 | U97: 843549.64 | V97: 7125 | W97: 819671.16 | Y97: 0 | Z97: 1150000 | AA97: 490119.71 | AE97: 23000 | AF97: 3691568.4 | AG97: 160.50297 | AH97: 0 | AI97: 0 | AJ97: 0 | AL97: 0 | AO97: 599.9 | AP97: 7041.3756 | AR97: ok
A98: 20181100040 | B98: 万田酵素 STANDARD2.5g×4包 | C98: 製品課 | E98: 10 | F98: PX | G98: 1.2530514 | H98: 0 | J98: 0 | K98: 600 | L98: =E98*K98 -> 6000 | M98: 7518.3083 | N98: 8025.5368 | S98: 62.604336 | T98: 37562.601 | U98: 29696.404 | V98: 770 | W98: 88582.006 | Y98: 0 | Z98: 6000 | AA98: 2557.1463 | AE98: 600 | AF98: 128861.09 | AG98: 214.76849 | AH98: 0 | AI98: 0 | AJ98: 0 | AL98: 0 | AP98: 0 | AR98: ok
A99: 20191200078 | B99: MANDA WELLNESS SUPERFOOD 31×2.5 | C99: 製品課 | E99: 77.5 | F99: PX | G99: 1.2530514 | H99: 0 | J99: 0 | K99: 300 | L99: =E99*K99 -> 23250 | M99: 29133.445 | N99: 31098.955 | S99: 539.29469 | T99: 161788.41 | U99: 127907.38 | V99: 745 | W99: 85705.967 | Y99: 0 | Z99: 23250 | AA99: 9908.942 | AE99: 300 | AF99: 254621.24 | AG99: 848.73747 | AH99: 0 | AI99: 0 | AJ99: 0 | AL99: 0 | AO99: 26.762994 | AP99: 144.49464 | AR99: ok
A100: 20201100053 | B100: 万田酵素MANUKA HONEY 分包77.5g | C100: 製品課 | E100: 77.5 | F100: PXM | G100: 4.0081229 | H100: 0 | J100: 0 | K100: 5900 | L100: =E100*K100 -> 457250 | M100: 1832714.2 | N100: 1956359.7 | S100: 102.41805 | T100: 604266.47 | U100: 477723.59 | V100: 2995 | W100: 344549.49 | Y100: 0 | Z100: 457250 | AA100: 194875.86 | AE100: 5900 | AF100: 2973508.7 | AG100: 503.98452 | AH100: 0 | AI100: 0 | AJ100: 0 | AL100: 0 | AP100: 0 | AR100: ok
...

Sheet 製品課発生原価サマリ
E1: 前工程費単価 | G1: 仕掛品（製品課）原価
E2: 仕掛品（製造部）原価 | H2: 製造費用
E3: グラム単価 | G3: 生産量 | H3: 製造部 | I3: 製品課 | M3: グラム単価 | N3: 製造部＋製品課 | O3: グラム単価 | Q3: check | S3: #製品課発生 グラム単価内訳
E4: 38期実際 | H4: 前工程費 | I4: 資材費 | J4: 労務費 | K4: 経費 | L4: 小計:製品課 | M4: # | N4: 計：製造費用 | S4: 資材費 | T4: 労務費 | U4: 経費
D5: 製品アイテム数 | G5: g | H5: \ | I5: \ | J5: \ | K5: \ | L5: \ | M5: 円/g | N5: \ | O5: 円/g | S5: 円/g | T5: 円/g | U5: 円/g
E6: a | G6: b | H6: c=a*b | I6: d | J6: e | K6: f | L6: h=d+e+f | M6: i=h/b | N6: j=c+h | O6: k=j/b | Q6: c=a*b
A7: 製品課生産分 | B7: 1 | C7: 5A | D7: =COUNTIF('4.仕掛品(製品課) _作業用(値)'!F:F,製品課発生原価サマリ!C7) -> 2 | E7: 5.1725294 | G7: =SUMIF('4.仕掛品(製品課) _作業用(値)'!$F:$F,$C7,'4.仕掛品(製品課) _作業用(値)'!L:L) -> 155650 | H7: =SUMIF('4.仕掛品(製品課) _作業用(値)'!$F:$F,$C7,'4.仕掛品(製品課) _作業用(値)'!M:M) -> 805104.19 | I7: =SUMIF('4.仕掛品(製品課) _作業用(値)'!$F:$F,$C7,'4.仕掛品(製品課) _作業用(値)'!U:U) -> 105088.77 | J7: =SUMIF('4.仕掛品(製品課) _作業用(値)'!$F:$F,$C7,'4.仕掛品(製品課) _作業用(値)'!W:W) -> 289329.54 | K7: =SUMIF('4.仕掛品(製品課) _作業用(値)'!$F:$F,$C7,'4.仕掛品(製品課) _作業用(値)'!AA:AA) -> 66336.638 | L7: =SUM(I7:K7) -> 460754.95 | M7: =L7/G7 -> 2.9601988 | N7: =SUM(H7:K7) -> 1265859.1 | O7: =N7/G7 -> 8.1327282 | Q7: =E7*G7 -> 805104.19 | R7: =H7-Q7 -> 0 | S7: =I7/$G7 -> 0.67516075 | T7: =J7/$G7 -> 1.858847 | U7: =K7/$G7 -> 0.42619105
B8: 2 | C8: B | D8: =COUNTIF('4.仕掛品(製品課) _作業用(値)'!F:F,製品課発生原価サマリ!C8) -> 4 | E8: 1.3486947 | G8: =SUMIF('4.仕掛品(製品課) _作業用(値)'!$F:$F,$C8,'4.仕掛品(製品課) _作業用(値)'!L:L) -> 482490 | H8: =SUMIF('4.仕掛品(製品課) _作業用(値)'!$F:$F,$C8,'4.仕掛品(製品課) _作業用(値)'!M:M) -> 650731.7 | I8: =SUMIF('4.仕掛品(製品課) _作業用(値)'!$F:$F,$C8,'4.仕掛品(製品課) _作業用(値)'!U:U) -> 1039070.8 | J8: =SUMIF('4.仕掛品(製品課) _作業用(値)'!$F:$F,$C8,'4.仕掛品(製品課) _作業用(値)'!W:W) -> 1056656.8 | K8: =SUMIF('4.仕掛品(製品課) _作業用(値)'!$F:$F,$C8,'4.仕掛品(製品課) _作業用(値)'!AA:AA) -> 205632.92 | L8: =SUM(I8:K8) -> 2301360.5 | M8: =L8/G8 -> 4.7697579 | N8: =SUM(H8:K8) -> 2952092.2 | O8: =N8/G8 -> 6.1184526 | Q8: =E8*G8 -> 650731.7 | R8: =H8-Q8 -> 0 | S8: =I8/$G8 -> 2.1535592 | T8: =J8/$G8 -> 2.1900076 | U8: =K8/$G8 -> 0.42619105
B9: 3 | C9: BE | D9: 3 | E9: 1.6947416 | G9: =SUMIF('4.仕掛品(製品課) _作業用(値)'!$F:$F,$C9,'4.仕掛品(製品課) _作業用(値)'!L:L) -> 252300 | H9: =SUMIF('4.仕掛品(製品課) _作業用(値)'!$F:$F,$C9,'4.仕掛品(製品課) _作業用(値)'!M:M) -> 427583.31 | I9: =SUMIF('4.仕掛品(製品課) _作業用(値)'!$F:$F,$C9,'4.仕掛品(製品課) _作業用(値)'!U:U) -> 798541.2 | J9: =SUMIF('4.仕掛品(製品課) _作業用(値)'!$F:$F,$C9,'4.仕掛品(製品課) _作業用(値)'!W:W) -> 881793.61 | K9: =SUMIF('4.仕掛品(製品課) _作業用(値)'!$F:$F,$C9,'4.仕掛品(製品課) _作業用(値)'!AA:AA) -> 107528 | L9: =SUM(I9:K9) -> 1787862.8 | M9: =L9/G9 -> 7.0862577 | N9: =SUM(H9:K9) -> 2215446.1 | O9: =N9/G9 -> 8.7809993 | Q9: =E9*G9 -> 427583.31 | R9: =H9-Q9 -> 0 | S9: =I9/$G9 -> 3.1650464 | T9: =J9/$G9 -> 3.4950202 | U9: =K9/$G9 -> 0.42619105
B10: 4 | C10: BM | D10: =COUNTIF('4.仕掛品(製品課) _作業用(値)'!F:F,製品課発生原価サマリ!C10) -> 1 | E10: 4.5002042 | G10: =SUMIF('4.仕掛品(製品課) _作業用(値)'!$F:$F,$C10,'4.仕掛品(製品課) _作業用(値)'!L:L) -> 1139250 | H10: =SUMIF('4.仕掛品(製品課) _作業用(値)'!$F:$F,$C10,'4.仕掛品(製品課) _作業用(値)'!M:M) -> 5126857.6 | I10: =SUMIF('4.仕掛品(製品課) _作業用(値)'!$F:$F,$C10,'4.仕掛品(製品課) _作業用(値)'!U:U) -> 633714.18 | J10: =SUMIF('4.仕掛品(製品課) _作業用(値)'!$F:$F,$C10,'4.仕掛品(製品課) _作業用(値)'!W:W) -> 770778.5 | K10: =SUMIF('4.仕掛品(製品課) _作業用(値)'!$F:$F,$C10,'4.仕掛品(製品課) _作業用(値)'!AA:AA) -> 485538.16 | L10: =SUM(I10:K10) -> 1890030.8 | M10: =L10/G10 -> 1.6590132 | N10: =SUM(H10:K10) -> 7016888.5 | O10: =N10/G10 -> 6.1592174 | Q10: =E10*G10 -> 5126857.6 | R10: =H10-Q10 -> 0 | S10: =I10/$G10 -> 0.55625559 | T10: =J10/$G10 -> 0.6765666 | U10: =K10/$G10 -> 0.42619105
B11: 5 | C11: C | D11: =COUNTIF('4.仕掛品(製品課) _作業用(値)'!F:F,製品課発生原価サマリ!C11) -> 1 | E11: 1.0344858 | G11: =SUMIF('4.仕掛品(製品課) _作業用(値)'!$F:$F,$C11,'4.仕掛品(製品課) _作業用(値)'!L:L) -> 23635 | H11: =SUMIF('4.仕掛品(製品課) _作業用(値)'!$F:$F,$C11,'4.仕掛品(製品課) _作業用(値)'!M:M) -> 24450.072 | I11: =SUMIF('4.仕掛品(製品課) _作業用(値)'!$F:$F,$C11,'4.仕掛品(製品課) _作業用(値)'!U:U) -> 228880.85 | J11: =SUMIF('4.仕掛品(製品課) _作業用(値)'!$F:$F,$C11,'4.仕掛品(製品課) _作業用(値)'!W:W) -> 118492.81 | K11: =SUMIF('4.仕掛品(製品課) _作業用(値)'!$F:$F,$C11,'4.仕掛品(製品課) _作業用(値)'!AA:AA) -> 10073.026 | L11: =SUM(I11:K11) -> 357446.69 | M11: =L11/G11 -> 15.123617 | N11: =SUM(H11:K11) -> 381896.76 | O11: =N11/G11 -> 16.158103 | Q11: =E11*G11 -> 24450.072 | R11: =H11-Q11 -> 0 | S11: =I11/$G11 -> 9.6839791 | T11: =J11/$G11 -> 5.0134467 | U11: =K11/$G11 -> 0.42619105
B12: 6 | C12: D | D12: =COUNTIF('4.仕掛品(製品課) _作業用(値)'!F:F,製品課発生原価サマリ!C12) -> 2 | E12: 1.3499631 | G12: =SUMIF('4.仕掛品(製品課) _作業用(値)'!$F:$F,$C12,'4.仕掛品(製品課) _作業用(値)'!L:L) -> 158750 | H12: =SUMIF('4.仕掛品(製品課) _作業用(値)'!$F:$F,$C12,'4.仕掛品(製品課) _作業用(値)'!M:M) -> 214306.64 | I12: =SUMIF('4.仕掛品(製品課) _作業用(値)'!$F:$F,$C12,'4.仕掛品(製品課) _作業用(値)'!U:U) -> 372620.31 | J12: =SUMIF('4.仕掛品(製品課) _作業用(値)'!$F:$F,$C12,'4.仕掛品(製品課) _作業用(値)'!W:W) -> 237560.84 | K12: =SUMIF('4.仕掛品(製品課) _作業用(値)'!$F:$F,$C12,'4.仕掛品(製品課) _作業用(値)'!AA:AA) -> 67657.83 | L12: =SUM(I12:K12) -> 677838.97 | M12: =L12/G12 -> 4.2698518 | N12: =SUM(H12:K12) -> 892145.61 | O12: =N12/G12 -> 5.6198149 | Q12: =E12*G12 -> 214306.64 | R12: =H12-Q12 -> 0 | S12: =I12/$G12 -> 2.3472145 | T12: =J12/$G12 -> 1.4964462 | U12: =K12/$G12 -> 0.42619105
B13: 7 | C13: DC | D13: =COUNTIF('4.仕掛品(製品課) _作業用(値)'!F:F,製品課発生原価サマリ!C13) -> 2 | E13: 2.5414453 | G13: =SUMIF('4.仕掛品(製品課) _作業用(値)'!$F:$F,$C13,'4.仕掛品(製品課) _作業用(値)'!L:L) -> 855550 | H13: =SUMIF('4.仕掛品(製品課) _作業用(値)'!$F:$F,$C13,'4.仕掛品(製品課) _作業用(値)'!M:M) -> 2174333.6 | I13: =SUMIF('4.仕掛品(製品課) _作業用(値)'!$F:$F,$C13,'4.仕掛品(製品課) _作業用(値)'!U:U) -> 1880331.6 | J13: =SUMIF('4.仕掛品(製品課) _作業用(値)'!$F:$F,$C13,'4.仕掛品(製品課) _作業用(値)'!W:W) -> 1832612.2 | K13: =SUMIF('4.仕掛品(製品課) _作業用(値)'!$F:$F,$C13,'4.仕掛品(製品課) _作業用(値)'!AA:AA) -> 364627.76 | L13: =SUM(I13:K13) -> 4077571.5 | M13: =L13/G13 -> 4.7660237 | N13: =SUM(H13:K13) -> 6251905.1 | O13: =N13/G13 -> 7.307469 | Q13: =E13*G13 -> 2174333.6 | R13: =H13-Q13 -> 0 | S13: =I13/$G13 -> 2.1978045 | T13: =J13/$G13 -> 2.1420281 | U13: =K13/$G13 -> 0.42619105
B14: 8 | C14: EB | D14: =COUNTIF('4.仕掛品(製品課) _作業用(値)'!F:F,製品課発生原価サマリ!C14) -> 5 | E14: 1.3583252 | G14: =SUMIF('4.仕掛品(製品課) _作業用(値)'!$F:$F,$C14,'4.仕掛品(製品課) _作業用(値)'!L:L) -> 534000 | H14: =SUMIF('4.仕掛品(製品課) _作業用(値)'!$F:$F,$C14,'4.仕掛品(製品課) _作業用(値)'!M:M) -> 725345.63 | I14: =SUMIF('4.仕掛品(製品課) _作業用(値)'!$F:$F,$C14,'4.仕掛品(製品課) _作業用(値)'!U:U) -> 826507.4 | J14: =SUMIF('4.仕掛品(製品課) _作業用(値)'!$F:$F,$C14,'4.仕掛品(製品課) _作業用(値)'!W:W) -> 1458151.9 | K14: =SUMIF('4.仕掛品(製品課) _作業用(値)'!$F:$F,$C14,'4.仕掛品(製品課) _作業用(値)'!AA:AA) -> 227586.02 | L14: =SUM(I14:K14) -> 2512245.3 | M14: =L14/G14 -> 4.7045792 | N14: =SUM(H14:K14) -> 3237590.9 | O14: =N14/G14 -> 6.0629043 | Q14: =E14*G14 -> 725345.63 | R14: =H14-Q14 -> 0 | S14: =I14/$G14 -> 1.5477667 | T14: =J14/$G14 -> 2.7306215 | U14: =K14/$G14 -> 0.42619105
B15: 9 | C15: FB | D15: =COUNTIF('4.仕掛品(製品課) _作業用(値)'!F:F,製品課発生原価サマリ!C15) -> 2 | E15: 1.8947649 | G15: =SUMIF('4.仕掛品(製品課) _作業用(値)'!$F:$F,$C15,'4.仕掛品(製品課) _作業用(値)'!L:L) -> 539760 | H15: =SUMIF('4.仕掛品(製品課) _作業用(値)'!$F:$F,$C15,'4.仕掛品(製品課) _作業用(値)'!M:M) -> 1022718.3 | I15: =SUMIF('4.仕掛品(製品課) _作業用(値)'!$F:$F,$C15,'4.仕掛品(製品課) _作業用(値)'!U:U) -> 2832787.1 | J15: =SUMIF('4.仕掛品(製品課) _作業用(値)'!$F:$F,$C15,'4.仕掛品(製品課) _作業用(値)'!W:W) -> 1419037.7 | K15: =SUMIF('4.仕掛品(製品課) _作業用(値)'!$F:$F,$C15,'4.仕掛品(製品課) _作業用(値)'!AA:AA) -> 230040.88 | L15: =SUM(I15:K15) -> 4481865.7 | M15: =L15/G15 -> 8.3034418 | N15: =SUM(H15:K15) -> 5504584 | O15: =N15/G15 -> 10.198207 | Q15: =E15*G15 -> 1022718.3 | R15: =H15-Q15 -> 0 | S15: =I15/$G15 -> 5.2482346 | T15: =J15/$G15 -> 2.6290161 | U15: =K15/$G15 -> 0.42619105
B16: 10 | C16: G | D16: =COUNTIF('4.仕掛品(製品課) _作業用(値)'!F:F,製品課発生原価サマリ!C16) -> 2 | E16: 2.7753038 | G16: =SUMIF('4.仕掛品(製品課) _作業用(値)'!$F:$F,$C16,'4.仕掛品(製品課) _作業用(値)'!L:L) -> 48620 | H16: =SUMIF('4.仕掛品(製品課) _作業用(値)'!$F:$F,$C16,'4.仕掛品(製品課) _作業用(値)'!M:M) -> 134935.27 | I16: =SUMIF('4.仕掛品(製品課) _作業用(値)'!$F:$F,$C16,'4.仕掛品(製品課) _作業用(値)'!U:U) -> 188112.12 | J16: =SUMIF('4.仕掛品(製品課) _作業用(値)'!$F:$F,$C16,'4.仕掛品(製品課) _作業用(値)'!W:W) -> 289904.75 | K16: =SUMIF('4.仕掛品(製品課) _作業用(値)'!$F:$F,$C16,'4.仕掛品(製品課) _作業用(値)'!AA:AA) -> 20721.409 | L16: =SUM(I16:K16) -> 498738.28 | M16: =L16/G16 -> 10.257883 | N16: =SUM(H16:K16) -> 633673.55 | O16: =N16/G16 -> 13.033187 | Q16: =E16*G16 -> 134935.27 | R16: =H16-Q16 -> 0 | S16: =I16/$G16 -> 3.8690276 | T16: =J16/$G16 -> 5.9626645 | U16: =K16/$G16 -> 0.42619105
B17: 11 | C17: GP | D17: =COUNTIF('4.仕掛品(製品課) _作業用(値)'!F:F,製品課発生原価サマリ!C17) -> 6 | E17: 1.394799 | G17: =SUMIF('4.仕掛品(製品課) _作業用(値)'!$F:$F,$C17,'4.仕掛品(製品課) _作業用(値)'!L:L) -> 16198500 | H17: =SUMIF('4.仕掛品(製品課) _作業用(値)'!$F:$F,$C17,'4.仕掛品(製品課) _作業用(値)'!M:M) -> 22593652 | I17: =SUMIF('4.仕掛品(製品課) _作業用(値)'!$F:$F,$C17,'4.仕掛品(製品課) _作業用(値)'!U:U) -> 6401306.2 | J17: =SUMIF('4.仕掛品(製品課) _作業用(値)'!$F:$F,$C17,'4.仕掛品(製品課) _作業用(値)'!W:W) -> 8308301.9 | K17: =SUMIF('4.仕掛品(製品課) _作業用(値)'!$F:$F,$C17,'4.仕掛品(製品課) _作業用(値)'!AA:AA) -> 6903655.8 | L17: =SUM(I17:K17) -> 21613264 | M17: =L17/G17 -> 1.3342756 | N17: =SUM(H17:K17) -> 44206916 | O17: =N17/G17 -> 2.7290746 | Q17: =E17*G17 -> 22593652 | R17: =H17-Q17 -> 0 | S17: =I17/$G17 -> 0.39517895 | T17: =J17/$G17 -> 0.51290564 | U17: =K17/$G17 -> 0.42619105
B18: 12 | C18: KOL | D18: =COUNTIF('4.仕掛品(製品課) _作業用(値)'!F:F,製品課発生原価サマリ!C18) -> 3 | E18: 1.3000228 | G18: =SUMIF('4.仕掛品(製品課) _作業用(値)'!$F:$F,$C18,'4.仕掛品(製品課) _作業用(値)'!L:L) -> 1104500 | H18: =SUMIF('4.仕掛品(製品課) _作業用(値)'!$F:$F,$C18,'4.仕掛品(製品課) _作業用(値)'!M:M) -> 1435875.2 | I18: =SUMIF('4.仕掛品(製品課) _作業用(値)'!$F:$F,$C18,'4.仕掛品(製品課) _作業用(値)'!U:U) -> 12078614 | J18: =SUMIF('4.仕掛品(製品課) _作業用(値)'!$F:$F,$C18,'4.仕掛品(製品課) _作業用(値)'!W:W) -> 2159905.4 | K18: =SUMIF('4.仕掛品(製品課) _作業用(値)'!$F:$F,$C18,'4.仕掛品(製品課) _作業用(値)'!AA:AA) -> 470728.02 | L18: =SUM(I18:K18) -> 14709248 | M18: =L18/G18 -> 13.317563 | N18: =SUM(H18:K18) -> 16145123 | O18: =N18/G18 -> 14.617585 | Q18: =E18*G18 -> 1435875.2 | R18: =H18-Q18 -> 0 | S18: =I18/$G18 -> 10.935821 | T18: =J18/$G18 -> 1.9555504 | U18: =K18/$G18 -> 0.42619105
B19: 13 | C19: MP | D19: =COUNTIF('4.仕掛品(製品課) _作業用(値)'!F:F,製品課発生原価サマリ!C19) -> 8 | E19: 1.1798248 | G19: =SUMIF('4.仕掛品(製品課) _作業用(値)'!$F:$F,$C19,'4.仕掛品(製品課) _作業用(値)'!L:L) -> 15047750 | H19: =SUMIF('4.仕掛品(製品課) _作業用(値)'!$F:$F,$C19,'4.仕掛品(製品課) _作業用(値)'!M:M) -> 17753708 | I19: =SUMIF('4.仕掛品(製品課) _作業用(値)'!$F:$F,$C19,'4.仕掛品(製品課) _作業用(値)'!U:U) -> 6244723 | J19: =SUMIF('4.仕掛品(製品課) _作業用(値)'!$F:$F,$C19,'4.仕掛品(製品課) _作業用(値)'!W:W) -> 6184634.6 | K19: =SUMIF('4.仕掛品(製品課) _作業用(値)'!$F:$F,$C19,'4.仕掛品(製品課) _作業用(値)'!AA:AA) -> 6413216.4 | L19: =SUM(I19:K19) -> 18842574 | M19: =L19/G19 -> 1.2521855 | N19: =SUM(H19:K19) -> 36596282 | O19: =N19/G19 -> 2.4320103 | Q19: =E19*G19 -> 17753708 | R19: =H19-Q19 -> 0 | S19: =I19/$G19 -> 0.4149938 | T19: =J19/$G19 -> 0.41100062 | U19: =K19/$G19 -> 0.42619105
B20: 14 | C20: O | D20: =COUNTIF('4.仕掛品(製品課) _作業用(値)'!F:F,製品課発生原価サマリ!C20) -> 5 | E20: 1.3228108 | G20: =SUMIF('4.仕掛品(製品課) _作業用(値)'!$F:$F,$C20,'4.仕掛品(製品課) _作業用(値)'!L:L) -> 210550 | H20: =SUMIF('4.仕掛品(製品課) _作業用(値)'!$F:$F,$C20,'4.仕掛品(製品課) _作業用(値)'!M:M) -> 278517.82 | I20: =SUMIF('4.仕掛品(製品課) _作業用(値)'!$F:$F,$C20,'4.仕掛品(製品課) _作業用(値)'!U:U) -> 923675.45 | J20: =SUMIF('4.仕掛品(製品課) _作業用(値)'!$F:$F,$C20,'4.仕掛品(製品課) _作業用(値)'!W:W) -> 501581.23 | K20: =SUMIF('4.仕掛品(製品課) _作業用(値)'!$F:$F,$C20,'4.仕掛品(製品課) _作業用(値)'!AA:AA) -> 89734.526 | L20: =SUM(I20:K20) -> 1514991.2 | M20: =L20/G20 -> 7.1953987 | N20: =SUM(H20:K20) -> 1793509 | O20: =N20/G20 -> 8.5182096 | Q20: =E20*G20 -> 278517.82 | R20: =H20-Q20 -> 0 | S20: =I20/$G20 -> 4.3869648 | T20: =J20/$G20 -> 2.3822428 | U20: =K20/$G20 -> 0.42619105
B21: 15 | C21: P | D21: 14 | E21: 1.2657092 | G21: =SUM('4.仕掛品(製品課) _作業用(値)'!L60:L73) -> 4587955 | H21: =SUMIF('4.仕掛品(製品課) _作業用(値)'!$F:$F,$C21,'4.仕掛品(製品課) _作業用(値)'!M:M) -> 5807016.9 | I21: =SUMIF('4.仕掛品(製品課) _作業用(値)'!$F:$F,$C21,'4.仕掛品(製品課) _作業用(値)'!U:U) -> 7265088.2 | J21: =SUMIF('4.仕掛品(製品課) _作業用(値)'!$F:$F,$C21,'4.仕掛品(製品課) _作業用(値)'!W:W) -> 9126247.5 | K21: =SUMIF('4.仕掛品(製品課) _作業用(値)'!$F:$F,$C21,'4.仕掛品(製品課) _作業用(値)'!AA:AA) -> 1955345.4 | L21: =SUM(I21:K21) -> 18346681 | M21: =L21/G21 -> 3.9988799 | N21: =SUM(H21:K21) -> 24153698 | O21: =N21/G21 -> 5.2645891 | Q21: =E21*G21 -> 5807016.9 | R21: =H21-Q21 -> 0 | S21: =I21/$G21 -> 1.5835134 | T21: =J21/$G21 -> 1.9891755 | U21: =K21/$G21 -> 0.42619105
B22: 16 | C22: PE | D22: =COUNTIF('4.仕掛品(製品課) _作業用(値)'!F:F,製品課発生原価サマリ!C22) -> 9 | E22: 1.1499334 | G22: =SUMIF('4.仕掛品(製品課) _作業用(値)'!$F:$F,$C22,'4.仕掛品(製品課) _作業用(値)'!L:L) -> 33786950 | H22: =SUMIF('4.仕掛品(製品課) _作業用(値)'!$F:$F,$C22,'4.仕掛品(製品課) _作業用(値)'!M:M) -> 38852741 | I22: =SUMIF('4.仕掛品(製品課) _作業用(値)'!$F:$F,$C22,'4.仕掛品(製品課) _作業用(値)'!U:U) -> 11173154 | J22: =SUMIF('4.仕掛品(製品課) _作業用(値)'!$F:$F,$C22,'4.仕掛品(製品課) _作業用(値)'!W:W) -> 14199005 | K22: =SUMIF('4.仕掛品(製品課) _作業用(値)'!$F:$F,$C22,'4.仕掛品(製品課) _作業用(値)'!AA:AA) -> 14399696 | L22: =SUM(I22:K22) -> 39771855 | M22: =L22/G22 -> 1.1771366 | N22: =SUM(H22:K22) -> 78624595 | O22: =N22/G22 -> 2.3270699 | Q22: =E22*G22 -> 38852741 | R22: =H22-Q22 -> 0 | S22: =I22/$G22 -> 0.33069435 | T22: =J22/$G22 -> 0.42025117 | U22: =K22/$G22 -> 0.42619105
B23: 17 | C23: PG | D23: =COUNTIF('4.仕掛品(製品課) _作業用(値)'!F:F,製品課発生原価サマリ!C23) -> 7 | E23: 1.4973298 | G23: =SUMIF('4.仕掛品(製品課) _作業用(値)'!$F:$F,$C23,'4.仕掛品(製品課) _作業用(値)'!L:L) -> 149400 | H23: =SUMIF('4.仕掛品(製品課) _作業用(値)'!$F:$F,$C23,'4.仕掛品(製品課) _作業用(値)'!M:M) -> 223701.07 | I23: =SUMIF('4.仕掛品(製品課) _作業用(値)'!$F:$F,$C23,'4.仕掛品(製品課) _作業用(値)'!U:U) -> 259476.76 | J23: =SUMIF('4.仕掛品(製品課) _作業用(値)'!$F:$F,$C23,'4.仕掛品(製品課) _作業用(値)'!W:W) -> 466493.55 | K23: =SUMIF('4.仕掛品(製品課) _作業用(値)'!$F:$F,$C23,'4.仕掛品(製品課) _作業用(値)'!AA:AA) -> 63672.943 | L23: =SUM(I23:K23) -> 789643.26 | M23: =L23/G23 -> 5.2854301 | N23: =SUM(H23:K23) -> 1013344.3 | O23: =N23/G23 -> 6.7827599 | Q23: =E23*G23 -> 223701.07 | R23: =H23-Q23 -> 0 | S23: =I23/$G23 -> 1.7367922 | T23: =J23/$G23 -> 3.1224468 | U23: =K23/$G23 -> 0.42619105
B24: 18 | C24: PR | D24: =COUNTIF('4.仕掛品(製品課) _作業用(値)'!F:F,製品課発生原価サマリ!C24) -> 2 | E24: 1.8060342 | G24: =SUMIF('4.仕掛品(製品課) _作業用(値)'!$F:$F,$C24,'4.仕掛品(製品課) _作業用(値)'!L:L) -> 465000 | H24: =SUMIF('4.仕掛品(製品課) _作業用(値)'!$F:$F,$C24,'4.仕掛品(製品課) _作業用(値)'!M:M) -> 839805.88 | I24: =SUMIF('4.仕掛品(製品課) _作業用(値)'!$F:$F,$C24,'4.仕掛品(製品課) _作業用(値)'!U:U) -> 13924143 | J24: =SUMIF('4.仕掛品(製品課) _作業用(値)'!$F:$F,$C24,'4.仕掛品(製品課) _作業用(値)'!W:W) -> 1196432.3 | K24: =SUMIF('4.仕掛品(製品課) _作業用(値)'!$F:$F,$C24,'4.仕掛品(製品課) _作業用(値)'!AA:AA) -> 198178.84 | L24: =SUM(I24:K24) -> 15318755 | M24: =L24/G24 -> 32.943558 | N24: =SUM(H24:K24) -> 16158560 | O24: =N24/G24 -> 34.749592 | Q24: =E24*G24 -> 839805.88 | R24: =H24-Q24 -> 0 | S24: =I24/$G24 -> 29.944394 | T24: =J24/$G24 -> 2.5729727 | U24: =K24/$G24 -> 0.42619105
B25: 19 | C25: PSA | D25: =COUNTIF('4.仕掛品(製品課) _作業用(値)'!F:F,製品課発生原価サマリ!C25) -> 3 | E25: 1.7935093 | G25: =SUMIF('4.仕掛品(製品課) _作業用(値)'!$F:$F,$C25,'4.仕掛品(製品課) _作業用(値)'!L:L) -> 1948000 | H25: =SUMIF('4.仕掛品(製品課) _作業用(値)'!$F:$F,$C25,'4.仕掛品(製品課) _作業用(値)'!M:M) -> 3493756 | I25: =SUMIF('4.仕掛品(製品課) _作業用(値)'!$F:$F,$C25,'4.仕掛品(製品課) _作業用(値)'!U:U) -> 2198090.9 | J25: =SUMIF('4.仕掛品(製品課) _作業用(値)'!$F:$F,$C25,'4.仕掛品(製品課) _作業用(値)'!W:W) -> 5310318.7 | K25: =SUMIF('4.仕掛品(製品課) _作業用(値)'!$F:$F,$C25,'4.仕掛品(製品課) _作業用(値)'!AA:AA) -> 830220.17 | L25: =SUM(I25:K25) -> 8338629.8 | M25: =L25/G25 -> 4.2806108 | N25: =SUM(H25:K25) -> 11832386 | O25: =N25/G25 -> 6.0741201 | Q25: =E25*G25 -> 3493756 | R25: =H25-Q25 -> 0 | S25: =I25/$G25 -> 1.1283834 | T25: =J25/$G25 -> 2.7260363 | U25: =K25/$G25 -> 0.42619105
B26: 20 | C26: PX | D26: =COUNTIF('4.仕掛品(製品課) _作業用(値)'!F:F,製品課発生原価サマリ!C26) -> 9 | E26: 1.2530514 | G26: =SUMIF('4.仕掛品(製品課) _作業用(値)'!$F:$F,$C26,'4.仕掛品(製品課) _作業用(値)'!L:L) -> 11305500 | H26: =SUMIF('4.仕掛品(製品課) _作業用(値)'!$F:$F,$C26,'4.仕掛品(製品課) _作業用(値)'!M:M) -> 14166372 | I26: =SUMIF('4.仕掛品(製品課) _作業用(値)'!$F:$F,$C26,'4.仕掛品(製品課) _作業用(値)'!U:U) -> 5200588.8 | J26: =SUMIF('4.仕掛品(製品課) _作業用(値)'!$F:$F,$C26,'4.仕掛品(製品課) _作業用(値)'!W:W) -> 7661193.1 | K26: =SUMIF('4.仕掛品(製品課) _作業用(値)'!$F:$F,$C26,'4.仕掛品(製品課) _作業用(値)'!AA:AA) -> 4818303 | L26: =SUM(I26:K26) -> 17680085 | M26: =L26/G26 -> 1.5638481 | N26: =SUM(H26:K26) -> 31846457 | O26: =N26/G26 -> 2.8168995 | Q26: =E26*G26 -> 14166372 | R26: =H26-Q26 -> 0 | S26: =I26/$G26 -> 0.4600052 | T26: =J26/$G26 -> 0.67765186 | U26: =K26/$G26 -> 0.42619105
B27: 21 | C27: PXM | D27: =COUNTIF('4.仕掛品(製品課) _作業用(値)'!F:F,製品課発生原価サマリ!C27) -> 3 | E27: 4.0081229 | G27: =SUMIF('4.仕掛品(製品課) _作業用(値)'!$F:$F,$C27,'4.仕掛品(製品課) _作業用(値)'!L:L) -> 692250 | H27: =SUMIF('4.仕掛品(製品課) _作業用(値)'!$F:$F,$C27,'4.仕掛品(製品課) _作業用(値)'!M:M) -> 2774623.1 | I27: =SUMIF('4.仕掛品(製品課) _作業用(値)'!$F:$F,$C27,'4.仕掛品(製品課) _作業用(値)'!U:U) -> 883377.84 | J27: =SUMIF('4.仕掛品(製品課) _作業用(値)'!$F:$F,$C27,'4.仕掛品(製品課) _作業用(値)'!W:W) -> 890421.73 | K27: =SUMIF('4.仕掛品(製品課) _作業用(値)'!$F:$F,$C27,'4.仕掛品(製品課) _作業用(値)'!AA:AA) -> 295030.76 | L27: =SUM(I27:K27) -> 2068830.3 | M27: =L27/G27 -> 2.9885595 | N27: =SUM(H27:K27) -> 4843453.4 | O27: =N27/G27 -> 6.9966825 | Q27: =E27*G27 -> 2774623.1 | R27: =H27-Q27 -> 0 | S27: =I27/$G27 -> 1.2760966 | T27: =J27/$G27 -> 1.2862719 | U27: =K27/$G27 -> 0.42619105
B28: 22 | C28: Q | D28: =COUNTIF('4.仕掛品(製品課) _作業用(値)'!F:F,製品課発生原価サマリ!C28) -> 1 | E28: 1.5486311 | G28: =SUMIF('4.仕掛品(製品課) _作業用(値)'!$F:$F,$C28,'4.仕掛品(製品課) _作業用(値)'!L:L) -> 150000 | H28: =SUMIF('4.仕掛品(製品課) _作業用(値)'!$F:$F,$C28,'4.仕掛品(製品課) _作業用(値)'!M:M) -> 232294.67 | I28: =SUMIF('4.仕掛品(製品課) _作業用(値)'!$F:$F,$C28,'4.仕掛品(製品課) _作業用(値)'!U:U) -> 462177.98 | J28: =SUMIF('4.仕掛品(製品課) _作業用(値)'!$F:$F,$C28,'4.仕掛品(製品課) _作業用(値)'!W:W) -> 496979.57 | K28: =SUMIF('4.仕掛品(製品課) _作業用(値)'!$F:$F,$C28,'4.仕掛品(製品課) _作業用(値)'!AA:AA) -> 63928.658 | L28: =SUM(I28:K28) -> 1023086.2 | M28: =L28/G28 -> 6.8205747 | N28: =SUM(H28:K28) -> 1255380.9 | O28: =N28/G28 -> 8.3692059 | Q28: =E28*G28 -> 232294.67 | R28: =H28-Q28 -> 0 | S28: =I28/$G28 -> 3.0811866 | T28: =J28/$G28 -> 3.3131971 | U28: =K28/$G28 -> 0.42619105
B29: 23 | C29: T | D29: 4 | E29: 1.5800702 | G29: =SUM('4.仕掛品(製品課) _作業用(値)'!L104:L107) -> 7735000 | H29: =SUMIF('4.仕掛品(製品課) _作業用(値)'!$F:$F,$C29,'4.仕掛品(製品課) _作業用(値)'!M:M) -> 12221843 | I29: =SUMIF('4.仕掛品(製品課) _作業用(値)'!$F:$F,$C29,'4.仕掛品(製品課) _作業用(値)'!U:U) -> 995809.28 | J29: =SUMIF('4.仕掛品(製品課) _作業用(値)'!$F:$F,$C29,'4.仕掛品(製品課) _作業用(値)'!W:W) -> 2637903.1 | K29: =SUMIF('4.仕掛品(製品課) _作業用(値)'!$F:$F,$C29,'4.仕掛品(製品課) _作業用(値)'!AA:AA) -> 3296587.8 | L29: =SUM(I29:K29) -> 6930300.2 | M29: =L29/G29 -> 0.89596641 | N29: =SUM(H29:K29) -> 19152143 | O29: =N29/G29 -> 2.4760366 | Q29: =E29*G29 -> 12221843 | R29: =H29-Q29 -> 0 | S29: =I29/$G29 -> 0.1287407 | T29: =J29/$G29 -> 0.34103466 | U29: =K29/$G29 -> 0.42619105
B30: 24 | C30: V | D30: =COUNTIF('4.仕掛品(製品課) _作業用(値)'!F:F,製品課発生原価サマリ!C30) -> 5 | E30: 1.2113727 | G30: =SUMIF('4.仕掛品(製品課) _作業用(値)'!$F:$F,$C30,'4.仕掛品(製品課) _作業用(値)'!L:L) -> 519300 | H30: =SUMIF('4.仕掛品(製品課) _作業用(値)'!$F:$F,$C30,'4.仕掛品(製品課) _作業用(値)'!M:M) -> 629065.84 | I30: =SUMIF('4.仕掛品(製品課) _作業用(値)'!$F:$F,$C30,'4.仕掛品(製品課) _作業用(値)'!U:U) -> 1147267.7 | J30: =SUMIF('4.仕掛品(製品課) _作業用(値)'!$F:$F,$C30,'4.仕掛品(製品課) _作業用(値)'!W:W) -> 1456426.2 | K30: =SUMIF('4.仕掛品(製品課) _作業用(値)'!$F:$F,$C30,'4.仕掛品(製品課) _作業用(値)'!AA:AA) -> 221321.01 | L30: =SUM(I30:K30) -> 2825014.9 | M30: =L30/G30 -> 5.4400441 | N30: =SUM(H30:K30) -> 3454080.7 | O30: =N30/G30 -> 6.6514168 | Q30: =E30*G30 -> 629065.84 | R30: =H30-Q30 -> 0 | S30: =I30/$G30 -> 2.209258 | T30: =J30/$G30 -> 2.8045951 | U30: =K30/$G30 -> 0.42619105
B31: 25 | C31: X | D31: 6 | E31: 1.5731245 | G31: =SUM('4.仕掛品(製品課) _作業用(値)'!L112:L117) -> 2391220 | H31: =SUMIF('4.仕掛品(製品課) _作業用(値)'!$F:$F,$C31,'4.仕掛品(製品課) _作業用(値)'!M:M) -> 3761686.8 | I31: =SUMIF('4.仕掛品(製品課) _作業用(値)'!$F:$F,$C31,'4.仕掛品(製品課) _作業用(値)'!U:U) -> 984327.29 | J31: =SUMIF('4.仕掛品(製品課) _作業用(値)'!$F:$F,$C31,'4.仕掛品(製品課) _作業用(値)'!W:W) -> 1359216.1 | K31: =SUMIF('4.仕掛品(製品課) _作業用(値)'!$F:$F,$C31,'4.仕掛品(製品課) _作業用(値)'!AA:AA) -> 1019116.6 | L31: =SUM(I31:K31) -> 3362660 | M31: =L31/G31 -> 1.4062529 | N31: =SUM(H31:K31) -> 7124346.8 | O31: =N31/G31 -> 2.9793774 | Q31: =E31*G31 -> 3761686.8 | R31: =H31-Q31 -> 0 | S31: =I31/$G31 -> 0.4116423 | T31: =J31/$G31 -> 0.56841951 | U31: =K31/$G31 -> 0.42619105
B32: 26 | C32: XC | D32: =COUNTIF('4.仕掛品(製品課) _作業用(値)'!F:F,製品課発生原価サマリ!C32) -> 3 | E32: 2.7031088 | G32: =SUMIF('4.仕掛品(製品課) _作業用(値)'!$F:$F,$C32,'4.仕掛品(製品課) _作業用(値)'!L:L) -> 1599000 | H32: =SUMIF('4.仕掛品(製品課) _作業用(値)'!$F:$F,$C32,'4.仕掛品(製品課) _作業用(値)'!M:M) -> 4322270.9 | I32: =SUMIF('4.仕掛品(製品課) _作業用(値)'!$F:$F,$C32,'4.仕掛品(製品課) _作業用(値)'!U:U) -> 947270.75 | J32: =SUMIF('4.仕掛品(製品課) _作業用(値)'!$F:$F,$C32,'4.仕掛品(製品課) _作業用(値)'!W:W) -> 931836.69 | K32: =SUMIF('4.仕掛品(製品課) _作業用(値)'!$F:$F,$C32,'4.仕掛品(製品課) _作業用(値)'!AA:AA) -> 681479.49 | L32: =SUM(I32:K32) -> 2560586.9 | M32: =L32/G32 -> 1.6013677 | N32: =SUM(H32:K32) -> 6882857.9 | O32: =N32/G32 -> 4.3044765 | Q32: =E32*G32 -> 4322270.9 | R32: =H32-Q32 -> 0 | S32: =I32/$G32 -> 0.59241448 | T32: =J32/$G32 -> 0.58276216 | U32: =K32/$G32 -> 0.42619105
B33: 27 | C33: Y | D33: =COUNTIF('4.仕掛品(製品課) _作業用(値)'!F:F,製品課発生原価サマリ!C33) -> 3 | E33: 1.6405741 | G33: =SUMIF('4.仕掛品(製品課) _作業用(値)'!$F:$F,$C33,'4.仕掛品(製品課) _作業用(値)'!L:L) -> 290450 | H33: =SUMIF('4.仕掛品(製品課) _作業用(値)'!$F:$F,$C33,'4.仕掛品(製品課) _作業用(値)'!M:M) -> 476504.75 | I33: =SUMIF('4.仕掛品(製品課) _作業用(値)'!$F:$F,$C33,'4.仕掛品(製品課) _作業用(値)'!U:U) -> 2817237.9 | J33: =SUMIF('4.仕掛品(製品課) _作業用(値)'!$F:$F,$C33,'4.仕掛品(製品課) _作業用(値)'!W:W) -> 596490.52 | K33: =SUMIF('4.仕掛品(製品課) _作業用(値)'!$F:$F,$C33,'4.仕掛品(製品課) _作業用(値)'!AA:AA) -> 123787.19 | L33: =SUM(I33:K33) -> 3537515.6 | M33: =L33/G33 -> 12.17943 | N33: =SUM(H33:K33) -> 4014020.3 | O33: =N33/G33 -> 13.820005 | Q33: =E33*G33 -> 476504.75 | R33: =H33-Q33 -> 0 | S33: =I33/$G33 -> 9.6995623 | T33: =J33/$G33 -> 2.0536771 | U33: =K33/$G33 -> 0.42619105
B34: 28 | C34: YA | D34: =COUNTIF('4.仕掛品(製品課) _作業用(値)'!F:F,製品課発生原価サマリ!C34) -> 1 | E34: 1.4901065 | G34: =SUMIF('4.仕掛品(製品課) _作業用(値)'!$F:$F,$C34,'4.仕掛品(製品課) _作業用(値)'!L:L) -> 3960 | H34: =SUMIF('4.仕掛品(製品課) _作業用(値)'!$F:$F,$C34,'4.仕掛品(製品課) _作業用(値)'!M:M) -> 5900.8219 | I34: =SUMIF('4.仕掛品(製品課) _作業用(値)'!$F:$F,$C34,'4.仕掛品(製品課) _作業用(値)'!U:U) -> 20843.872 | J34: =SUMIF('4.仕掛品(製品課) _作業用(値)'!$F:$F,$C34,'4.仕掛品(製品課) _作業用(値)'!W:W) -> 67874.524 | K34: =SUMIF('4.仕掛品(製品課) _作業用(値)'!$F:$F,$C34,'4.仕掛品(製品課) _作業用(値)'!AA:AA) -> 1687.7166 | L34: =SUM(I34:K34) -> 90406.113 | M34: =L34/G34 -> 22.829826 | N34: =SUM(H34:K34) -> 96306.935 | O34: =N34/G34 -> 24.319933 | Q34: =E34*G34 -> 5900.8219 | R34: =H34-Q34 -> 0 | S34: =I34/$G34 -> 5.263604 | T34: =J34/$G34 -> 17.140031 | U34: =K34/$G34 -> 0.42619105
B35: 29 | C35: YC | D35: =COUNTIF('4.仕掛品(製品課) _作業用(値)'!F:F,製品課発生原価サマリ!C35) -> 1 | E35: 5.4526805 | G35: =SUMIF('4.仕掛品(製品課) _作業用(値)'!$F:$F,$C35,'4.仕掛品(製品課) _作業用(値)'!L:L) -> 24420 | H35: =SUMIF('4.仕掛品(製品課) _作業用(値)'!$F:$F,$C35,'4.仕掛品(製品課) _作業用(値)'!M:M) -> 133154.46 | I35: =SUMIF('4.仕掛品(製品課) _作業用(値)'!$F:$F,$C35,'4.仕掛品(製品課) _作業用(値)'!U:U) -> 105691.69 | J35: =SUMIF('4.仕掛品(製品課) _作業用(値)'!$F:$F,$C35,'4.仕掛品(製品課) _作業用(値)'!W:W) -> 293355.99 | K35: =SUMIF('4.仕掛品(製品課) _作業用(値)'!$F:$F,$C35,'4.仕掛品(製品課) _作業用(値)'!AA:AA) -> 10407.586 | L35: =SUM(I35:K35) -> 409455.27 | M35: =L35/G35 -> 16.76721 | N35: =SUM(H35:K35) -> 542609.73 | O35: =N35/G35 -> 22.219891 | Q35: =E35*G35 -> 133154.46 | R35: =H35-Q35 -> 0 | S35: =I35/$G35 -> 4.3280792 | T35: =J35/$G35 -> 12.01294 | U35: =K35/$G35 -> 0.42619105
B36: 30 | C36: ZA | D36: =COUNTIF('4.仕掛品(製品課) _作業用(値)'!F:F,製品課発生原価サマリ!C36) -> 3 | E36: 2.2073146 | G36: =SUMIF('4.仕掛品(製品課) _作業用(値)'!$F:$F,$C36,'4.仕掛品(製品課) _作業用(値)'!L:L) -> 146250 | H36: =SUMIF('4.仕掛品(製品課) _作業用(値)'!$F:$F,$C36,'4.仕掛品(製品課) _作業用(値)'!M:M) -> 322819.77 | I36: =SUMIF('4.仕掛品(製品課) _作業用(値)'!$F:$F,$C36,'4.仕掛品(製品課) _作業用(値)'!U:U) -> 253495.51 | J36: =SUMIF('4.仕掛品(製品課) _作業用(値)'!$F:$F,$C36,'4.仕掛品(製品課) _作業用(値)'!W:W) -> 433131.5 | K36: =SUMIF('4.仕掛品(製品課) _作業用(値)'!$F:$F,$C36,'4.仕掛品(製品課) _作業用(値)'!AA:AA) -> 62330.442 | L36: =SUM(I36:K36) -> 748957.45 | M36: =L36/G36 -> 5.1210766 | N36: =SUM(H36:K36) -> 1071777.2 | O36: =N36/G36 -> 7.3283912 | Q36: =E36*G36 -> 322819.77 | R36: =H36-Q36 -> 0 | S36: =I36/$G36 -> 1.7333026 | T36: =J36/$G36 -> 2.9615829 | U36: =K36/$G36 -> 0.42619105
D37: =SUM(D7:D36) -> 120 | G37: =SUM(G7:G36) -> 102545960 | H37: =SUM(H7:H36) -> 1.4163168e+08 | I37: =SUM(I7:I36) -> 83192015 | J37: =SUM(J7:J36) -> 72632068 | K37: =SUM(K7:K36) -> 43704171 | L37: =SUM(L7:L36) -> 1.9952825e+08 | M37: =L37/G37 -> 1.9457447 | N37: =SUM(N7:N36) -> 3.4115993e+08 | O37: =N37/G37 -> 3.3268978 | Q37: =SUM(Q7:Q36) -> 1.4163168e+08 | R37: =H37-Q37 -> 0 | S37: =I37/$G37 -> 0.81126565 | T37: =J37/$G37 -> 0.70828795 | U37: =K37/$G37 -> 0.42619105

Sheet 4.仕掛品(製品課) (2)
A1: 第37期 仕掛品(製品課)
F3: 製品記号 | H3: 期首棚卸 | K3: 当期投入 | AD3: 当期商品製造原価 | AG3: 在庫調整 | AI3: 期末棚卸
H4: 数量 | L4: 仕掛品(製品課製造分) | N4: 仕掛品(外注品内製分) | P4: 仕掛品(製造部製造分) | R4: 資材費 | U4: 労務費(製品課) | W4: 労務費(製造部) | Y4: 経費 | AA4: 外注加工費 | AB4: 別コードに振替 | AI4: 数量
A5: SCコード | B5: 商品名 | C5: 区分 | D5: 半製品 | E5: 内容量(g) | F5: 製品記号 | G5: ｸﾞﾗﾑ単価 | H5: 数量 | I5: 進捗度 | J5: 金額 | K5: 数量 | L5: 配賦係数 | M5: 金額 | N5: 配賦係数 | O5: 金額 | P5: 配賦係数 | Q5: 金額 | R5: 包材価格 | S5: 配賦係数 | T5: 金額 | U5: 配賦係数 | V5: 金額 | W5: 配賦係数 | X5: 金額 | Y5: 配賦係数 | Z5: 金額 | AA5: (原液原価込み) | AB5: 数量 | AC5: 金額 | AD5: 数量 | AE5: 金額 | AF5: 単価 | AG5: 数量 | AH5: 原価 | AI5: 数量 | AJ5: 進捗度 | AK5: 金額 | AN5: 34期資材 | AO5: 34期単価 | AQ5: 絞り込み
A6: 20110300023 | B6: EH酵素 6g(2g 3連包) | C6: 半製品 | D6: 半製品 | E6: 6 | F6: CE | G6: =IFERROR(VLOOKUP(F6,'[1]2.仕掛品(製造部)'!MY:NB,4,0),0) -> 0 | H6: 0 | J6: 0 | AI6: =IFERROR(SUMIFS('4.3期末全在庫'!$G:$G,'4.3期末全在庫'!$B:$B,'4.仕掛品(製品課) (2)'!A6,'4.3期末全在庫'!$K:$K,"半製品"),"") -> 0 | AK6: =AF6*AI6 -> 0 | AO6: 0
A7: 20110801125 | B7: 【瓶】ｽｰﾊﾟｰ万田酵素 氣Ⅰ | C7: 半製品 | D7: 半製品 | G7: =IFERROR(VLOOKUP(F7,'[1]2.仕掛品(製造部)'!MY:NB,4,0),0) -> 0 | H7: 0 | J7: 0 | AI7: =IFERROR(SUMIFS('4.3期末全在庫'!$G:$G,'4.3期末全在庫'!$B:$B,'4.仕掛品(製品課) (2)'!A7,'4.3期末全在庫'!$K:$K,"半製品"),"") -> 0 | AK7: =AF7*AI7 -> 0 | AN7: 248.93192 | AO7: 0
A8: 20110801128 | B8: 【瓶】ｴｺｺﾞｰﾙﾄﾞEX 180g | C8: 半製品 | D8: 半製品 | G8: =IFERROR(VLOOKUP(F8,'[1]2.仕掛品(製造部)'!MY:NB,4,0),0) -> 0 | H8: 0 | J8: 0 | AI8: =IFERROR(SUMIFS('4.3期末全在庫'!$G:$G,'4.3期末全在庫'!$B:$B,'4.仕掛品(製品課) (2)'!A8,'4.3期末全在庫'!$K:$K,"半製品"),"") -> 0 | AK8: =AF8*AI8 -> 0 | AO8: 12.902551
A9: 20110801129 | B9: 【ﾎﾞﾄﾙ】Jﾎﾞﾄﾙ 丸型細口 1ﾘｯﾄﾙ | C9: 半製品 | D9: 半製品 | G9: =IFERROR(VLOOKUP(F9,'[1]2.仕掛品(製造部)'!MY:NB,4,0),0) -> 0 | H9: 0 | J9: 0 | AI9: =IFERROR(SUMIFS('4.3期末全在庫'!$G:$G,'4.3期末全在庫'!$B:$B,'4.仕掛品(製品課) (2)'!A9,'4.3期末全在庫'!$K:$K,"半製品"),"") -> 0 | AK9: =AF9*AI9 -> 0 | AO9: 6.7658564
A10: 20110801131 | B10: 【瓶】155g S-130 白 | C10: 半製品 | D10: 半製品 | G10: =IFERROR(VLOOKUP(F10,'[1]2.仕掛品(製造部)'!MY:NB,4,0),0) -> 0 | H10: 0 | J10: 0 | AI10: =IFERROR(SUMIFS('4.3期末全在庫'!$G:$G,'4.3期末全在庫'!$B:$B,'4.仕掛品(製品課) (2)'!A10,'4.3期末全在庫'!$K:$K,"半製品"),"") -> 0 | AK10: =AF10*AI10 -> 0 | AO10: 7.5356885
A11: 20110801132 | B11: 【瓶】145g E-100 六角（白） | C11: 半製品 | D11: 半製品 | G11: =IFERROR(VLOOKUP(F11,'[1]2.仕掛品(製造部)'!MY:NB,4,0),0) -> 0 | H11: 0 | J11: 0 | AI11: =IFERROR(SUMIFS('4.3期末全在庫'!$G:$G,'4.3期末全在庫'!$B:$B,'4.仕掛品(製品課) (2)'!A11,'4.3期末全在庫'!$K:$K,"半製品"),"") -> 0 | AK11: =AF11*AI11 -> 0 | AO11: 0
A12: 20110801133 | B12: 【瓶】EC-500 | C12: 半製品 | D12: 半製品 | G12: =IFERROR(VLOOKUP(F12,'[1]2.仕掛品(製造部)'!MY:NB,4,0),0) -> 0 | H12: 0 | J12: 0 | AI12: =IFERROR(SUMIFS('4.3期末全在庫'!$G:$G,'4.3期末全在庫'!$B:$B,'4.仕掛品(製品課) (2)'!A12,'4.3期末全在庫'!$K:$K,"半製品"),"") -> 0 | AK12: =AF12*AI12 -> 0 | AO12: 0
A13: 20110801134 | B13: 【瓶】M-70 6角 茶 | C13: 半製品 | D13: 半製品 | G13: =IFERROR(VLOOKUP(F13,'[1]2.仕掛品(製造部)'!MY:NB,4,0),0) -> 0 | H13: 0 | J13: 0 | AI13: =IFERROR(SUMIFS('4.3期末全在庫'!$G:$G,'4.3期末全在庫'!$B:$B,'4.仕掛品(製品課) (2)'!A13,'4.3期末全在庫'!$K:$K,"半製品"),"") -> 0 | AK13: =AF13*AI13 -> 0 | AO13: 0
A14: 20110801135 | B14: 【瓶】六角茶色 145g E-100 | C14: 半製品 | D14: 半製品 | G14: =IFERROR(VLOOKUP(F14,'[1]2.仕掛品(製造部)'!MY:NB,4,0),0) -> 0 | H14: 0 | J14: 0 | AI14: =IFERROR(SUMIFS('4.3期末全在庫'!$G:$G,'4.3期末全在庫'!$B:$B,'4.仕掛品(製品課) (2)'!A14,'4.3期末全在庫'!$K:$K,"半製品"),"") -> 0 | AK14: =AF14*AI14 -> 0 | AO14: 0
A15: 20110801137 | B15: 【瓶】食品8角 310g | C15: 半製品 | D15: 半製品 | G15: =IFERROR(VLOOKUP(F15,'[1]2.仕掛品(製造部)'!MY:NB,4,0),0) -> 0 | H15: 0 | J15: 0 | AI15: =IFERROR(SUMIFS('4.3期末全在庫'!$G:$G,'4.3期末全在庫'!$B:$B,'4.仕掛品(製品課) (2)'!A15,'4.3期末全在庫'!$K:$K,"半製品"),"") -> 0 | AK15: =AF15*AI15 -> 0 | AO15: 6.1045485
A16: 20110801139 | B16: 【瓶】E-90 | C16: 半製品 | D16: 半製品 | G16: =IFERROR(VLOOKUP(F16,'[1]2.仕掛品(製造部)'!MY:NB,4,0),0) -> 0 | H16: 0 | J16: 0 | AI16: =IFERROR(SUMIFS('4.3期末全在庫'!$G:$G,'4.3期末全在庫'!$B:$B,'4.仕掛品(製品課) (2)'!A16,'4.3期末全在庫'!$K:$K,"半製品"),"") -> 0 | AK16: =AF16*AI16 -> 0 | AO16: 0
A17: 20110801142 | B17: 万田酵素 145g (販売店向け) 半 | C17: 半製品 | D17: 半製品 | E17: 145 | F17: P | G17: =IFERROR(VLOOKUP(F17,'[1]2.仕掛品(製造部)'!MY:NB,4,0),0) -> 1.2657092 | H17: 0 | J17: 0 | AI17: =IFERROR(SUMIFS('4.3期末全在庫'!$G:$G,'4.3期末全在庫'!$B:$B,'4.仕掛品(製品課) (2)'!A17,'4.3期末全在庫'!$K:$K,"半製品"),"") -> 0 | AK17: =AF17*AI17 -> 0 | AO17: 0
A18: 20110801143 | B18: 万田酵素 300g (販売店） 半 | C18: 半製品 | D18: 半製品 | G18: =IFERROR(VLOOKUP(F18,'[1]2.仕掛品(製造部)'!MY:NB,4,0),0) -> 0 | H18: 0 | J18: 0 | AI18: =IFERROR(SUMIFS('4.3期末全在庫'!$G:$G,'4.3期末全在庫'!$B:$B,'4.仕掛品(製品課) (2)'!A18,'4.3期末全在庫'!$K:$K,"半製品"),"") -> 0 | AK18: =AF18*AI18 -> 0 | AO18: 0 | AQ18: =IF(SUM(H18:AK18)=0,0,"ok") -> 0
A19: 20110801158 | B19: PG 2.5g×2 | C19: 半製品 | D19: 半製品 | E19: 5 | F19: PG | G19: =IFERROR(VLOOKUP(F19,'[3]2'!MY:NB,4,0),0) -> 0 | H19: 180 | J19: 1110.9506 | AI19: =IFERROR(SUMIFS('4.3期末全在庫'!$G:$G,'4.3期末全在庫'!$B:$B,'4.仕掛品(製品課) (2)'!A19,'4.3期末全在庫'!$K:$K,"半製品"),"") -> 1350 | AK19: =AI19*AF175/E19*E175 -> 82945.988 | AO19: 0 | AQ19: =IF(SUM(H19:AK19)=0,0,"ok") -> ok
A20: 20110801159 | B20: ZA 2.5g×2 | C20: 半製品 | D20: 半製品 | E20: 5 | F20: ZA | G20: =IFERROR(VLOOKUP(F20,'[1]2.仕掛品(製造部)'!MY:NB,4,0),0) -> 2.2073146 | H20: 4500 | J20: 37735.653 | AI20: =IFERROR(SUMIFS('4.3期末全在庫'!$G:$G,'4.3期末全在庫'!$B:$B,'4.仕掛品(製品課) (2)'!A20,'4.3期末全在庫'!$K:$K,"半製品"),"") -> 0 | AK20: =AF20*AI20 -> 0 | AO20: 0 | AQ20: =IF(SUM(H20:AK20)=0,0,"ok") -> ok
A21: 20110801161 | B21: BE 2.5g×2 | C21: 半製品 | D21: 半製品 | E21: 5 | F21: BE | G21: =IFERROR(VLOOKUP(F21,'[1]2.仕掛品(製造部)'!MY:NB,4,0),0) -> 1.6947416 | H21: 3800 | J21: 25204.237 | AI21: =IFERROR(SUMIFS('4.3期末全在庫'!$G:$G,'4.3期末全在庫'!$B:$B,'4.仕掛品(製品課) (2)'!A21,'4.3期末全在庫'!$K:$K,"半製品"),"") -> 0 | AK21: =AF21*AI21 -> 0 | AO21: 7.1801316 | AQ21: =IF(SUM(H21:AK21)=0,0,"ok") -> ok
A22: 20110801164 | B22: ｊPG 2.5g×2 | C22: 半製品 | D22: 半製品 | E22: 5 | F22: PG | G22: =IFERROR(VLOOKUP(F22,'[1]2.仕掛品(製造部)'!MY:NB,4,0),0) -> 1.4973298 | H22: 900 | J22: 5554.7532 | AI22: =IFERROR(SUMIFS('4.3期末全在庫'!$G:$G,'4.3期末全在庫'!$B:$B,'4.仕掛品(製品課) (2)'!A22,'4.3期末全在庫'!$K:$K,"半製品"),"") -> 1800 | AK22: =AI22*AF175/E22*E175 -> 110594.65 | AO22: 0 | AQ22: =IF(SUM(H22:AK22)=0,0,"ok") -> ok
A23: 20110801167 | B23: W 2.5g×2 | C23: 半製品 | D23: 半製品 | E23: 5 | F23: W | G23: =IFERROR(VLOOKUP(F23,'[1]2.仕掛品(製造部)'!MY:NB,4,0),0) -> 0 | H23: 0 | J23: 0 | AI23: =IFERROR(SUMIFS('4.3期末全在庫'!$G:$G,'4.3期末全在庫'!$B:$B,'4.仕掛品(製品課) (2)'!A23,'4.3期末全在庫'!$K:$K,"半製品"),"") -> 0 | AK23: =AF23*AI23 -> 0 | AN23: 11.488231 | AO23: 67.62891 | AQ23: =IF(SUM(H23:AK23)=0,0,"ok") -> 0
A24: 20110801168 | B24: PE 2.5g×2 | C24: 半製品 | D24: 半製品 | E24: 5 | F24: PE | G24: =IFERROR(VLOOKUP(F24,'[1]2.仕掛品(製造部)'!MY:NB,4,0),0) -> 1.1499334 | H24: 0 | J24: 0 | AI24: =IFERROR(SUMIFS('4.3期末全在庫'!$G:$G,'4.3期末全在庫'!$B:$B,'4.仕掛品(製品課) (2)'!A24,'4.3期末全在庫'!$K:$K,"半製品"),"") -> 0 | AK24: =AF24*AI24 -> 0 | AO24: 1328.0203 | AQ24: =IF(SUM(H24:AK24)=0,0,"ok") -> 0
A25: 20110801169 | B25: L 5000 (海外向け) Y 5g×3 | C25: 半製品 | D25: 半製品 | E25: 15 | F25: Y | G25: =IFERROR(VLOOKUP(F25,'[1]2.仕掛品(製造部)'!MY:NB,4,0),0) -> 1.6405741 | H25: 0 | J25: 0 | AI25: =IFERROR(SUMIFS('4.3期末全在庫'!$G:$G,'4.3期末全在庫'!$B:$B,'4.仕掛品(製品課) (2)'!A25,'4.3期末全在庫'!$K:$K,"半製品"),"") -> 0 | AK25: =AF25*AI25 -> 0 | AN25: 20.138231 | AO25: 72.320673 | AQ25: =IF(SUM(H25:AK25)=0,0,"ok") -> 0
A26: 20110801179 | B26: FB 2.5g×2 | C26: 半製品 | D26: 半製品 | E26: 5 | F26: FB | G26: =IFERROR(VLOOKUP(F26,'[1]2.仕掛品(製造部)'!MY:NB,4,0),0) -> 1.8947649 | H26: 0 | J26: 0 | AI26: =IFERROR(SUMIFS('4.3期末全在庫'!$G:$G,'4.3期末全在庫'!$B:$B,'4.仕掛品(製品課) (2)'!A26,'4.3期末全在庫'!$K:$K,"半製品"),"") -> 0 | AK26: =AF26*AI26 -> 0 | AN26: 140.76441 | AO26: 427.69344 | AQ26: =IF(SUM(H26:AK26)=0,0,"ok") -> 0
A27: 20110801204 | B27: D 1.67g×2 | C27: 半製品 | D27: 半製品 | E27: 3.34 | F27: D | G27: =IFERROR(VLOOKUP(F27,'[1]2.仕掛品(製造部)'!MY:NB,4,0),0) -> 1.3499631 | H27: 0 | J27: 0 | AI27: =IFERROR(SUMIFS('4.3期末全在庫'!$G:$G,'4.3期末全在庫'!$B:$B,'4.仕掛品(製品課) (2)'!A27,'4.3期末全在庫'!$K:$K,"半製品"),"") -> 0 | AK27: =AF27*AI27 -> 0 | AN27: 762.89597 | AO27: 1582.157 | AQ27: =IF(SUM(H27:AK27)=0,0,"ok") -> 0
A28: 20110801206 | B28: L 5000(ﾀﾅｶ向け) Y 5g×3 | C28: 半製品 | D28: 半製品 | E28: 15 | F28: Y | G28: =IFERROR(VLOOKUP(F28,'[1]2.仕掛品(製造部)'!MY:NB,4,0),0) -> 1.6405741 | H28: 0 | J28: 0 | AI28: =IFERROR(SUMIFS('4.3期末全在庫'!$G:$G,'4.3期末全在庫'!$B:$B,'4.仕掛品(製品課) (2)'!A28,'4.3期末全在庫'!$K:$K,"半製品"),"") -> 0 | AK28: =AF28*AI28 -> 0 | AO28: 0 | AQ28: =IF(SUM(H28:AK28)=0,0,"ok") -> 0
A29: 20110801213 | B29: CE 2g×3 | C29: 半製品 | D29: 半製品 | E29: 6 | F29: CE | G29: =IFERROR(VLOOKUP(F29,'[1]2.仕掛品(製造部)'!MY:NB,4,0),0) -> 0 | H29: 0 | J29: 0 | AI29: =IFERROR(SUMIFS('4.3期末全在庫'!$G:$G,'4.3期末全在庫'!$B:$B,'4.仕掛品(製品課) (2)'!A29,'4.3期末全在庫'!$K:$K,"半製品"),"") -> 0 | AK29: =AF29*AI29 -> 0 | AN29: 192.77056 | AO29: 0 | AQ29: =IF(SUM(H29:AK29)=0,0,"ok") -> 0
A30: 20110801215 | B30: 5A 5g×2 | C30: 半製品 | D30: 半製品 | E30: 10 | F30: 5A | G30: =IFERROR(VLOOKUP(F30,'[1]2.仕掛品(製造部)'!MY:NB,4,0),0) -> 5.1725294 | H30: 0 | J30: 0 | AI30: =IFERROR(SUMIFS('4.3期末全在庫'!$G:$G,'4.3期末全在庫'!$B:$B,'4.仕掛品(製品課) (2)'!A30,'4.3期末全在庫'!$K:$K,"半製品"),"") -> 0 | AK30: =AF30*AI30 -> 0 | AN30: 82.903661 | AO30: 0 | AQ30: =IF(SUM(H30:AK30)=0,0,"ok") -> 0
A31: 20110801216 | B31: 新･MKF-Ⅱ 30g 半 | C31: 半製品 | D31: 半製品 | G31: =IFERROR(VLOOKUP(F31,'[1]2.仕掛品(製造部)'!MY:NB,4,0),0) -> 0 | H31: 0 | J31: 0 | AI31: =IFERROR(SUMIFS('4.3期末全在庫'!$G:$G,'4.3期末全在庫'!$B:$B,'4.仕掛品(製品課) (2)'!A31,'4.3期末全在庫'!$K:$K,"半製品"),"") -> 0 | AK31: =AF31*AI31 -> 0 | AN31: 92.267501 | AO31: 0 | AQ31: =IF(SUM(H31:AK31)=0,0,"ok") -> 0
A32: 20110801217 | B32: MKF-Ⅱ 5A ﾘｷｯﾄﾞ 30g 半 | C32: 半製品 | D32: 半製品 | G32: =IFERROR(VLOOKUP(F32,'[1]2.仕掛品(製造部)'!MY:NB,4,0),0) -> 0 | H32: 0 | J32: 0 | AI32: =IFERROR(SUMIFS('4.3期末全在庫'!$G:$G,'4.3期末全在庫'!$B:$B,'4.仕掛品(製品課) (2)'!A32,'4.3期末全在庫'!$K:$K,"半製品"),"") -> 0 | AK32: =AF32*AI32 -> 0 | AO32: 0 | AQ32: =IF(SUM(H32:AK32)=0,0,"ok") -> 0
A33: 20110801221 | B33: DC 2.5g×2 | C33: 半製品 | D33: 半製品 | E33: 5 | F33: DC | G33: =IFERROR(VLOOKUP(F33,'[1]2.仕掛品(製造部)'!MY:NB,4,0),0) -> 2.5414453 | H33: 0 | J33: 0 | AI33: =IFERROR(SUMIFS('4.3期末全在庫'!$G:$G,'4.3期末全在庫'!$B:$B,'4.仕掛品(製品課) (2)'!A33,'4.3期末全在庫'!$K:$K,"半製品"),"") -> 0 | AK33: =AF33*AI33 -> 0 | AO33: 0 | AQ33: =IF(SUM(H33:AK33)=0,0,"ok") -> 0
A34: 20110801223 | B34: ﾅﾁｭﾗﾙ酵素 ﾌﾞﾙｰﾍﾞﾘｰﾌﾟﾗｽ 2.5g×3 | C34: 半製品 | D34: 半製品 | E34: 7.5 | F34: PR | G34: =IFERROR(VLOOKUP(F34,'[1]2.仕掛品(製造部)'!MY:NB,4,0),0) -> 1.8060342 | H34: 0 | J34: 0 | AI34: =IFERROR(SUMIFS('4.3期末全在庫'!$G:$G,'4.3期末全在庫'!$B:$B,'4.仕掛品(製品課) (2)'!A34,'4.3期末全在庫'!$K:$K,"半製品"),"") -> 0 | AK34: =AF34*AI34 -> 0 | AN34: 471.83603 | AO34: 3237.5045 | AQ34: =IF(SUM(H34:AK34)=0,0,"ok") -> 0
A35: 20110801234 | B35: Man-Koso P 2.5g×4 | C35: 半製品 | D35: 半製品 | E35: 10 | F35: P | G35: =IFERROR(VLOOKUP(F35,'[1]2.仕掛品(製造部)'!MY:NB,4,0),0) -> 1.2657092 | H35: 0 | J35: 0 | AI35: =IFERROR(SUMIFS('4.3期末全在庫'!$G:$G,'4.3期末全在庫'!$B:$B,'4.仕掛品(製品課) (2)'!A35,'4.3期末全在庫'!$K:$K,"半製品"),"") -> 0 | AK35: =AF35*AI35 -> 0 | AN35: 815.61763 | AO35: 0 | AQ35: =IF(SUM(H35:AK35)=0,0,"ok") -> 0
A36: 20110801266 | B36: B 2.5g×2 | C36: 半製品 | D36: 半製品 | E36: 5 | F36: B | G36: =IFERROR(VLOOKUP(F36,'[1]2.仕掛品(製造部)'!MY:NB,4,0),0) -> 1.3486947 | H36: 0 | J36: 0 | AI36: =IFERROR(SUMIFS('4.3期末全在庫'!$G:$G,'4.3期末全在庫'!$B:$B,'4.仕掛品(製品課) (2)'!A36,'4.3期末全在庫'!$K:$K,"半製品"),"") -> 0 | AK36: =AF36*AI36 -> 0 | AN36: 484.84922 | AO36: 1826.5396 | AQ36: =IF(SUM(H36:AK36)=0,0,"ok") -> 0
A37: 20110801267 | B37: EB 2.5g×2 | C37: 半製品 | D37: 半製品 | E37: 5 | F37: EB | G37: =IFERROR(VLOOKUP(F37,'[1]2.仕掛品(製造部)'!MY:NB,4,0),0) -> 1.3583252 | H37: 4500 | J37: 19728.659 | AI37: =IFERROR(SUMIFS('4.3期末全在庫'!$G:$G,'4.3期末全在庫'!$B:$B,'4.仕掛品(製品課) (2)'!A37,'4.3期末全在庫'!$K:$K,"半製品"),"") -> 12600 | AK37: =AI37*AF172/E37*E172 -> 369655.96 | AO37: 2136.147 | AQ37: =IF(SUM(H37:AK37)=0,0,"ok") -> ok
A38: 20110801268 | B38: V 2.5g×2 | C38: 半製品 | D38: 半製品 | E38: 5 | F38: V | G38: =IFERROR(VLOOKUP(F38,'[1]2.仕掛品(製造部)'!MY:NB,4,0),0) -> 1.2113727 | H38: 0 | J38: 0 | AI38: =IFERROR(SUMIFS('4.3期末全在庫'!$G:$G,'4.3期末全在庫'!$B:$B,'4.仕掛品(製品課) (2)'!A38,'4.3期末全在庫'!$K:$K,"半製品"),"") -> 12700 | AK38: =AI38*AF178/E38*E178 -> 337292.91 | AN38: 594.95854 | AO38: 2504.1591 | AQ38: =IF(SUM(H38:AK38)=0,0,"ok") -> ok
A39: 20110801270 | B39: I 2.5g×2 | C39: 半製品 | D39: 半製品 | E39: 5 | F39: I | G39: =IFERROR(VLOOKUP(F39,'[1]2.仕掛品(製造部)'!MY:NB,4,0),0) -> 2.6770701 | H39: 0 | J39: 0 | AI39: =IFERROR(SUMIFS('4.3期末全在庫'!$G:$G,'4.3期末全在庫'!$B:$B,'4.仕掛品(製品課) (2)'!A39,'4.3期末全在庫'!$K:$K,"半製品"),"") -> 0 | AK39: =AF39*AI39 -> 0 | AN39: 244.44922 | AO39: 914.29186 | AQ39: =IF(SUM(H39:AK39)=0,0,"ok") -> 0
A40: 20110801272 | B40: MANDA KOSO 2.5g×2 | C40: 半製品 | D40: 半製品 | E40: 5 | F40: P | G40: =IFERROR(VLOOKUP(F40,'[1]2.仕掛品(製造部)'!MY:NB,4,0),0) -> 1.2657092 | H40: 0 | J40: 0 | AI40: =IFERROR(SUMIFS('4.3期末全在庫'!$G:$G,'4.3期末全在庫'!$B:$B,'4.仕掛品(製品課) (2)'!A40,'4.3期末全在庫'!$K:$K,"半製品"),"") -> 0 | AK40: =AF40*AI40 -> 0 | AN40: 204.85381 | AO40: 1187.3955 | AQ40: =IF(SUM(H40:AK40)=0,0,"ok") -> 0
A41: 20110801273 | B41: P 2.5g×2 | C41: 半製品 | D41: 半製品 | E41: 5 | F41: P | G41: =IFERROR(VLOOKUP(F41,'[1]2.仕掛品(製造部)'!MY:NB,4,0),0) -> 1.2657092 | H41: 124800 | J41: 599836.36 | AI41: =IFERROR(SUMIFS('4.3期末全在庫'!$G:$G,'4.3期末全在庫'!$B:$B,'4.仕掛品(製品課) (2)'!A41,'4.3期末全在庫'!$K:$K,"半製品"),"") -> 52300 | AK41: =AI41*AF336/E41*E336 -> 670818.01 | AN41: 68.967368 | AO41: 729.09329 | AQ41: =IF(SUM(H41:AK41)=0,0,"ok") -> ok
A42: 20110801274 | B42: O 2.5g×2 | C42: 半製品 | D42: 半製品 | E42: 5 | F42: O | G42: =IFERROR(VLOOKUP(F42,'[1]2.仕掛品(製造部)'!MY:NB,4,0),0) -> 1.3228108 | H42: 0 | J42: 0 | AI42: =IFERROR(SUMIFS('4.3期末全在庫'!$G:$G,'4.3期末全在庫'!$B:$B,'4.仕掛品(製品課) (2)'!A42,'4.3期末全在庫'!$K:$K,"半製品"),"") -> 0 | AK42: =AF42*AI42 -> 0 | AN42: 44.058684 | AO42: 433.65191 | AQ42: =IF(SUM(H42:AK42)=0,0,"ok") -> 0
A43: 20110801277 | B43: ﾌﾞﾙｰﾍﾞﾘｰﾌﾟﾗｽ 2.5g×2 | C43: 半製品 | D43: 半製品 | E43: 5 | F43: PR | G43: =IFERROR(VLOOKUP(F43,'[1]2.仕掛品(製造部)'!MY:NB,4,0),0) -> 1.8060342 | H43: 0 | J43: 0 | AI43: =IFERROR(SUMIFS('4.3期末全在庫'!$G:$G,'4.3期末全在庫'!$B:$B,'4.仕掛品(製品課) (2)'!A43,'4.3期末全在庫'!$K:$K,"半製品"),"") -> 0 | AK43: =AF43*AI43 -> 0 | AN43: 124.25737 | AO43: 655.0643 | AQ43: =IF(SUM(H43:AK43)=0,0,"ok") -> 0
A44: 20110801280 | B44: G 2.5g×2 | C44: 半製品 | D44: 半製品 | E44: 5 | F44: G | G44: =IFERROR(VLOOKUP(F44,'[1]2.仕掛品(製造部)'!MY:NB,4,0),0) -> 2.7753038 | H44: 0 | J44: 0 | AI44: =IFERROR(SUMIFS('4.3期末全在庫'!$G:$G,'4.3期末全在庫'!$B:$B,'4.仕掛品(製品課) (2)'!A44,'4.3期末全在庫'!$K:$K,"半製品"),"") -> 0 | AK44: =AF44*AI44 -> 0 | AO44: 4034.3004 | AQ44: =IF(SUM(H44:AK44)=0,0,"ok") -> 0
A45: 20110801283 | B45: 5A 2.5g×2 | C45: 半製品 | D45: 半製品 | E45: 5 | F45: 5A | G45: =IFERROR(VLOOKUP(F45,'[1]2.仕掛品(製造部)'!MY:NB,4,0),0) -> 5.1725294 | H45: 0 | J45: 0 | AI45: =IFERROR(SUMIFS('4.3期末全在庫'!$G:$G,'4.3期末全在庫'!$B:$B,'4.仕掛品(製品課) (2)'!A45,'4.3期末全在庫'!$K:$K,"半製品"),"") -> 0 | AK45: =AF45*AI45 -> 0 | AO45: 3237.3253 | AQ45: =IF(SUM(H45:AK45)=0,0,"ok") -> 0
A46: 20110801300 | B46: X 1ml×2 | C46: 半製品 | D46: 半製品 | E46: 2.6 | F46: X | G46: =IFERROR(VLOOKUP(F46,'[1]2.仕掛品(製造部)'!MY:NB,4,0),0) -> 1.5731245 | H46: 0 | J46: 0 | AI46: =IFERROR(SUMIFS('4.3期末全在庫'!$G:$G,'4.3期末全在庫'!$B:$B,'4.仕掛品(製品課) (2)'!A46,'4.3期末全在庫'!$K:$K,"半製品"),"") -> 0 | AK46: =AF46*AI46 -> 0 | AN46: 141.81276 | AO46: 3712.8163 | AQ46: =IF(SUM(H46:AK46)=0,0,"ok") -> 0
A47: 20110801492 | B47: 新･MKF-Ⅱ 30g TOMⅢ-30 №3 | C47: 半製品 | D47: 半製品 | G47: =IFERROR(VLOOKUP(F47,'[1]2.仕掛品(製造部)'!MY:NB,4,0),0) -> 0 | H47: 0 | J47: 0 | AI47: =IFERROR(SUMIFS('4.3期末全在庫'!$G:$G,'4.3期末全在庫'!$B:$B,'4.仕掛品(製品課) (2)'!A47,'4.3期末全在庫'!$K:$K,"半製品"),"") -> 0 | AK47: =AF47*AI47 -> 0 | AN47: 175 | AO47: 3082.7114 | AQ47: =IF(SUM(H47:AK47)=0,0,"ok") -> 0
A48: 20110801505 | B48: 六角茶色瓶 145g E-100 | C48: 半製品 | D48: 半製品 | G48: =IFERROR(VLOOKUP(F48,'[1]2.仕掛品(製造部)'!MY:NB,4,0),0) -> 0 | H48: 0 | J48: 0 | AI48: =IFERROR(SUMIFS('4.3期末全在庫'!$G:$G,'4.3期末全在庫'!$B:$B,'4.仕掛品(製品課) (2)'!A48,'4.3期末全在庫'!$K:$K,"半製品"),"") -> 0 | AK48: =AF48*AI48 -> 0 | AN48: 550.8769 | AO48: 1685.6497 | AQ48: =IF(SUM(H48:AK48)=0,0,"ok") -> 0
A49: 20110801533 | B49: 食品8角 310g 瓶 大商硝子 | C49: 半製品 | D49: 半製品 | G49: =IFERROR(VLOOKUP(F49,'[1]2.仕掛品(製造部)'!MY:NB,4,0),0) -> 0 | H49: 0 | J49: 0 | AI49: =IFERROR(SUMIFS('4.3期末全在庫'!$G:$G,'4.3期末全在庫'!$B:$B,'4.仕掛品(製品課) (2)'!A49,'4.3期末全在庫'!$K:$K,"半製品"),"") -> 0 | AK49: =AF49*AI49 -> 0 | AO49: 0 | AQ49: =IF(SUM(H49:AK49)=0,0,"ok") -> 0
A50: 20110801536 | B50: 分包ﾌｨﾙﾑ (無地) 幅70mm ﾀｶﾗ | C50: 半製品 | D50: 半製品 | G50: =IFERROR(VLOOKUP(F50,'[1]2.仕掛品(製造部)'!MY:NB,4,0),0) -> 0 | H50: 0 | J50: 0 | AI50: =IFERROR(SUMIFS('4.3期末全在庫'!$G:$G,'4.3期末全在庫'!$B:$B,'4.仕掛品(製品課) (2)'!A50,'4.3期末全在庫'!$K:$K,"半製品"),"") -> 0 | AK50: =AF50*AI50 -> 0 | AN50: 82.800699 | AO50: 390.40495 | AQ50: =IF(SUM(H50:AK50)=0,0,"ok") -> 0
A51: 20110801549 | B51: Jﾎﾞﾄﾙ 丸型細口(ﾅﾁｭﾗﾙ) 1ﾘｯﾄﾙ | C51: 半製品 | D51: 半製品 | G51: =IFERROR(VLOOKUP(F51,'[1]2.仕掛品(製造部)'!MY:NB,4,0),0) -> 0 | H51: 0 | J51: 0 | AI51: =IFERROR(SUMIFS('4.3期末全在庫'!$G:$G,'4.3期末全在庫'!$B:$B,'4.仕掛品(製品課) (2)'!A51,'4.3期末全在庫'!$K:$K,"半製品"),"") -> 0 | AK51: =AF51*AI51 -> 0 | AO51: 8.7154732 | AQ51: =IF(SUM(H51:AK51)=0,0,"ok") -> 0
A52: 20110801604 | B52: 食品8角 310gｷｬｯﾌﾟ(大調和ﾏｰｸ入) | C52: 半製品 | D52: 半製品 | G52: =IFERROR(VLOOKUP(F52,'[1]2.仕掛品(製造部)'!MY:NB,4,0),0) -> 0 | H52: 0 | J52: 0 | AI52: =IFERROR(SUMIFS('4.3期末全在庫'!$G:$G,'4.3期末全在庫'!$B:$B,'4.仕掛品(製品課) (2)'!A52,'4.3期末全在庫'!$K:$K,"半製品"),"") -> 0 | AK52: =AF52*AI52 -> 0 | AO52: 6.4400381 | AQ52: =IF(SUM(H52:AK52)=0,0,"ok") -> 0
A53: 20110801610 | B53: 新･MKF-Ⅱ 30g TOMⅢ-CAP №1 | C53: 半製品 | D53: 半製品 | G53: =IFERROR(VLOOKUP(F53,'[1]2.仕掛品(製造部)'!MY:NB,4,0),0) -> 0 | H53: 0 | J53: 0 | AI53: =IFERROR(SUMIFS('4.3期末全在庫'!$G:$G,'4.3期末全在庫'!$B:$B,'4.仕掛品(製品課) (2)'!A53,'4.3期末全在庫'!$K:$K,"半製品"),"") -> 0 | AK53: =AF53*AI53 -> 0 | AO53: 0 | AQ53: =IF(SUM(H53:AK53)=0,0,"ok") -> 0
A54: 20110801621 | B54: 70g用ｷｬｯﾌﾟ（大調和ﾏｰｸ入） | C54: 半製品 | D54: 半製品 | G54: =IFERROR(VLOOKUP(F54,'[1]2.仕掛品(製造部)'!MY:NB,4,0),0) -> 0 | H54: 0 | J54: 0 | AI54: =IFERROR(SUMIFS('4.3期末全在庫'!$G:$G,'4.3期末全在庫'!$B:$B,'4.仕掛品(製品課) (2)'!A54,'4.3期末全在庫'!$K:$K,"半製品"),"") -> 0 | AK54: =AF54*AI54 -> 0 | AO54: 7.4080624 | AQ54: =IF(SUM(H54:AK54)=0,0,"ok") -> 0
A55: 20110801622 | B55: 145ｇ用 ｷｬｯﾌﾟ（大調和ﾏｰｸ入り） | C55: 半製品 | D55: 半製品 | G55: =IFERROR(VLOOKUP(F55,'[1]2.仕掛品(製造部)'!MY:NB,4,0),0) -> 0 | H55: 0 | J55: 0 | AI55: =IFERROR(SUMIFS('4.3期末全在庫'!$G:$G,'4.3期末全在庫'!$B:$B,'4.仕掛品(製品課) (2)'!A55,'4.3期末全在庫'!$K:$K,"半製品"),"") -> 0 | AK55: =AF55*AI55 -> 0 | AO55: 0 | AQ55: =IF(SUM(H55:AK55)=0,0,"ok") -> 0
A56: 20110801624 | B56: 70ｇ用ｷｬｯﾌﾟ（刻印なし） | C56: 半製品 | D56: 半製品 | G56: =IFERROR(VLOOKUP(F56,'[1]2.仕掛品(製造部)'!MY:NB,4,0),0) -> 0 | H56: 0 | J56: 0 | AI56: =IFERROR(SUMIFS('4.3期末全在庫'!$G:$G,'4.3期末全在庫'!$B:$B,'4.仕掛品(製品課) (2)'!A56,'4.3期末全在庫'!$K:$K,"半製品"),"") -> 0 | AK56: =AF56*AI56 -> 0 | AO56: 6.1625532 | AQ56: =IF(SUM(H56:AK56)=0,0,"ok") -> 0
A57: 20110801689 | B57: 新･MKF-Ⅱ 30g TOCAP用 | C57: 半製品 | D57: 半製品 | G57: =IFERROR(VLOOKUP(F57,'[1]2.仕掛品(製造部)'!MY:NB,4,0),0) -> 0 | H57: 0 | J57: 0 | AI57: =IFERROR(SUMIFS('4.3期末全在庫'!$G:$G,'4.3期末全在庫'!$B:$B,'4.仕掛品(製品課) (2)'!A57,'4.3期末全在庫'!$K:$K,"半製品"),"") -> 0 | AK57: =AF57*AI57 -> 0 | AO57: 0 | AQ57: =IF(SUM(H57:AK57)=0,0,"ok") -> 0
A58: 20110801698 | B58: 食品8角 310g SPPﾊｲｼｰﾄ 大商硝子 | C58: 半製品 | D58: 半製品 | G58: =IFERROR(VLOOKUP(F58,'[1]2.仕掛品(製造部)'!MY:NB,4,0),0) -> 0 | H58: 0 | J58: 0 | AI58: =IFERROR(SUMIFS('4.3期末全在庫'!$G:$G,'4.3期末全在庫'!$B:$B,'4.仕掛品(製品課) (2)'!A58,'4.3期末全在庫'!$K:$K,"半製品"),"") -> 0 | AK58: =AF58*AI58 -> 0 | AO58: 0 | AQ58: =IF(SUM(H58:AK58)=0,0,"ok") -> 0
A59: 20110803102 | B59: 食品8角 310g 瓶ｼｭﾘﾝｸ 大商硝子 | C59: 半製品 | D59: 半製品 | G59: =IFERROR(VLOOKUP(F59,'[1]2.仕掛品(製造部)'!MY:NB,4,0),0) -> 0 | H59: 0 | J59: 0 | AI59: =IFERROR(SUMIFS('4.3期末全在庫'!$G:$G,'4.3期末全在庫'!$B:$B,'4.仕掛品(製品課) (2)'!A59,'4.3期末全在庫'!$K:$K,"半製品"),"") -> 0 | AK59: =AF59*AI59 -> 0 | AO59: 3.7627945 | AQ59: =IF(SUM(H59:AK59)=0,0,"ok") -> 0
A60: 20110900030 | B60: PE 2.5g | C60: 半製品 | D60: 半製品 | E60: 2.5 | F60: PE | H60: 0 | J60: 0 | AI60: =IFERROR(SUMIFS('4.3期末全在庫'!$G:$G,'4.3期末全在庫'!$B:$B,'4.仕掛品(製品課) (2)'!A60,'4.3期末全在庫'!$K:$K,"半製品"),"") -> 0 | AK60: =AF60*AI60 -> 0 | AO60: 132.80325 | AQ60: =IF(SUM(H60:AK60)=0,0,"ok") -> 0
A61: 20111000018 | B61: MKﾐｸｽﾁｬｰ(ﾍﾟｰｽﾄ)㎏ 半 | C61: 半製品 | D61: 半製品 | G61: =IFERROR(VLOOKUP(F61,'[1]2.仕掛品(製造部)'!MY:NB,4,0),0) -> 0 | H61: 0 | J61: 0 | AI61: =IFERROR(SUMIFS('4.3期末全在庫'!$G:$G,'4.3期末全在庫'!$B:$B,'4.仕掛品(製品課) (2)'!A61,'4.3期末全在庫'!$K:$K,"半製品"),"") -> 0 | AK61: =AF61*AI61 -> 0 | AO61: 6.4280051 | AQ61: =IF(SUM(H61:AK61)=0,0,"ok") -> 0
A62: 20111000019 | B62: MKﾐｸｽﾁｬｰ(ﾘｷｯﾄﾞ)㎏ 半 | C62: 半製品 | D62: 半製品 | G62: =IFERROR(VLOOKUP(F62,'[1]2.仕掛品(製造部)'!MY:NB,4,0),0) -> 0 | H62: 0 | J62: 0 | AI62: =IFERROR(SUMIFS('4.3期末全在庫'!$G:$G,'4.3期末全在庫'!$B:$B,'4.仕掛品(製品課) (2)'!A62,'4.3期末全在庫'!$K:$K,"半製品"),"") -> 0 | AK62: =AF62*AI62 -> 0 | AO62: 0 | AQ62: =IF(SUM(H62:AK62)=0,0,"ok") -> 0
A63: 20111000949 | B63: 表示用無地ﾗﾍﾞﾙ 63×50 | C63: 半製品 | D63: 半製品 | G63: =IFERROR(VLOOKUP(F63,'[1]2.仕掛品(製造部)'!MY:NB,4,0),0) -> 0 | H63: 0 | J63: 0 | AI63: =IFERROR(SUMIFS('4.3期末全在庫'!$G:$G,'4.3期末全在庫'!$B:$B,'4.仕掛品(製品課) (2)'!A63,'4.3期末全在庫'!$K:$K,"半製品"),"") -> 0 | AK63: =AF63*AI63 -> 0 | AO63: 406.82861 | AQ63: =IF(SUM(H63:AK63)=0,0,"ok") -> 0
A64: 20111000967 | B64: 延寿酵素 OLIGO PLUS 145g 半 | C64: 半製品 | D64: 半製品 | E64: 145 | F64: PT | G64: =IFERROR(VLOOKUP(F64,'[1]2.仕掛品(製造部)'!MY:NB,4,0),0) -> 0 | H64: 0 | J64: 0 | AI64: =IFERROR(SUMIFS('4.3期末全在庫'!$G:$G,'4.3期末全在庫'!$B:$B,'4.仕掛品(製品課) (2)'!A64,'4.3期末全在庫'!$K:$K,"半製品"),"") -> 0 | AK64: =AF64*AI64 -> 0 | AN64: 719.47185 | AO64: 2035.457 | AQ64: =IF(SUM(H64:AK64)=0,0,"ok") -> 0
A65: 20111100047 | B65: PT 2.5×2 | C65: 半製品 | D65: 半製品 | E65: 5 | F65: PT | G65: =IFERROR(VLOOKUP(F65,'[1]2.仕掛品(製造部)'!MY:NB,4,0),0) -> 0 | H65: 0 | J65: 0 | AI65: =IFERROR(SUMIFS('4.3期末全在庫'!$G:$G,'4.3期末全在庫'!$B:$B,'4.仕掛品(製品課) (2)'!A65,'4.3期末全在庫'!$K:$K,"半製品"),"") -> 0 | AK65: =AF65*AI65 -> 0 | AN65: 912.30041 | AO65: 1981.9319 | AQ65: =IF(SUM(H65:AK65)=0,0,"ok") -> 0
A66: 20120300043 | B66: Man-Koso LIFE Y 5g×3 | C66: 半製品 | D66: 半製品 | E66: 15 | F66: Y | G66: =IFERROR(VLOOKUP(F66,'[1]2.仕掛品(製造部)'!MY:NB,4,0),0) -> 1.6405741 | H66: 0 | J66: 0 | AI66: =IFERROR(SUMIFS('4.3期末全在庫'!$G:$G,'4.3期末全在庫'!$B:$B,'4.仕掛品(製品課) (2)'!A66,'4.3期末全在庫'!$K:$K,"半製品"),"") -> 0 | AK66: =AF66*AI66 -> 0 | AO66: 0 | AQ66: =IF(SUM(H66:AK66)=0,0,"ok") -> 0
A67: 20120900071 | B67: PE 2.5g | C67: 半製品 | D67: 半製品 | E67: 2.5 | F67: PE | G67: =IFERROR(VLOOKUP(F67,'[1]2.仕掛品(製造部)'!MY:NB,4,0),0) -> 1.1499334 | H67: 0 | J67: 0 | AI67: =IFERROR(SUMIFS('4.3期末全在庫'!$G:$G,'4.3期末全在庫'!$B:$B,'4.仕掛品(製品課) (2)'!A67,'4.3期末全在庫'!$K:$K,"半製品"),"") -> 0 | AK67: =AF67*AI67 -> 0 | AO67: 0 | AQ67: =IF(SUM(H67:AK67)=0,0,"ok") -> 0
A68: 20121000006 | B68: ﾉﾆ酵素 2g×2 | C68: 半製品 | D68: 半製品 | E68: 4 | F68: PSA | G68: =IFERROR(VLOOKUP(F68,'[1]2.仕掛品(製造部)'!MY:NB,4,0),0) -> 1.7935093 | H68: 0 | J68: 0 | AI68: =IFERROR(SUMIFS('4.3期末全在庫'!$G:$G,'4.3期末全在庫'!$B:$B,'4.仕掛品(製品課) (2)'!A68,'4.3期末全在庫'!$K:$K,"半製品"),"") -> 0 | AK68: =AF68*AI68 -> 0 | AO68: 0 | AQ68: =IF(SUM(H68:AK68)=0,0,"ok") -> 0
A69: 20121000043 | B69: Q 2.5g×2 | C69: 半製品 | D69: 半製品 | E69: 5 | F69: Q | G69: =IFERROR(VLOOKUP(F69,'[1]2.仕掛品(製造部)'!MY:NB,4,0),0) -> 1.5486311 | H69: 0 | J69: 0 | AI69: =IFERROR(SUMIFS('4.3期末全在庫'!$G:$G,'4.3期末全在庫'!$B:$B,'4.仕掛品(製品課) (2)'!A69,'4.3期末全在庫'!$K:$K,"半製品"),"") -> 0 | AK69: =AF69*AI69 -> 0 | AO69: 0 | AQ69: =IF(SUM(H69:AK69)=0,0,"ok") -> 0
A70: 20130100020 | B70: 食品8角310g瓶(刻印なし)新ｷｬｯﾌﾟ | C70: 半製品 | D70: 半製品 | G70: =IFERROR(VLOOKUP(F70,'[1]2.仕掛品(製造部)'!MY:NB,4,0),0) -> 0 | H70: 0 | J70: 0 | AI70: =IFERROR(SUMIFS('4.3期末全在庫'!$G:$G,'4.3期末全在庫'!$B:$B,'4.仕掛品(製品課) (2)'!A70,'4.3期末全在庫'!$K:$K,"半製品"),"") -> 0 | AK70: =AF70*AI70 -> 0 | AO70: 0 | AQ70: =IF(SUM(H70:AK70)=0,0,"ok") -> 0
A71: 20130100025 | B71: NONI酵素 300g ﾌｧﾐﾘｰｻｲｽﾞ 半 | C71: 半製品 | D71: 半製品 | G71: =IFERROR(VLOOKUP(F71,'[1]2.仕掛品(製造部)'!MY:NB,4,0),0) -> 0 | H71: 0 | J71: 0 | AI71: =IFERROR(SUMIFS('4.3期末全在庫'!$G:$G,'4.3期末全在庫'!$B:$B,'4.仕掛品(製品課) (2)'!A71,'4.3期末全在庫'!$K:$K,"半製品"),"") -> 0 | AK71: =AF71*AI71 -> 0 | AO71: 0 | AQ71: =IF(SUM(H71:AK71)=0,0,"ok") -> 0
A72: 20130200022 | B72: CE 2g×3 540g用 | C72: 半製品 | D72: 半製品 | E72: 6 | F72: CE | G72: =IFERROR(VLOOKUP(F72,'[1]2.仕掛品(製造部)'!MY:NB,4,0),0) -> 0 | H72: 0 | J72: 0 | AI72: =IFERROR(SUMIFS('4.3期末全在庫'!$G:$G,'4.3期末全在庫'!$B:$B,'4.仕掛品(製品課) (2)'!A72,'4.3期末全在庫'!$K:$K,"半製品"),"") -> 0 | AK72: =AF72*AI72 -> 0 | AO72: 0 | AQ72: =IF(SUM(H72:AK72)=0,0,"ok") -> 0
A73: 20130400028 | B73: 3年3ヶ月以上発酵熟成酵素 70g 半 | C73: 半製品 | D73: 半製品 | E73: 70 | F73: P | G73: =IFERROR(VLOOKUP(F73,'[1]2.仕掛品(製造部)'!MY:NB,4,0),0) -> 1.2657092 | H73: 0 | J73: 0 | AI73: =IFERROR(SUMIFS('4.3期末全在庫'!$G:$G,'4.3期末全在庫'!$B:$B,'4.仕掛品(製品課) (2)'!A73,'4.3期末全在庫'!$K:$K,"半製品"),"") -> 0 | AK73: =AF73*AI73 -> 0 | AO73: 0 | AQ73: =IF(SUM(H73:AK73)=0,0,"ok") -> 0
A74: 20130400029 | B74: 3年3ヶ月発酵熟成酵素 2.5g×2 | C74: 半製品 | D74: 半製品 | E74: 5 | F74: P | G74: =IFERROR(VLOOKUP(F74,'[1]2.仕掛品(製造部)'!MY:NB,4,0),0) -> 1.2657092 | H74: 0 | J74: 0 | AI74: =IFERROR(SUMIFS('4.3期末全在庫'!$G:$G,'4.3期末全在庫'!$B:$B,'4.仕掛品(製品課) (2)'!A74,'4.3期末全在庫'!$K:$K,"半製品"),"") -> 0 | AK74: =AF74*AI74 -> 0 | AO74: 0 | AQ74: =IF(SUM(H74:AK74)=0,0,"ok") -> 0
A75: 20130900009 | B75: JA 2.5g×2 無地 | C75: 半製品 | D75: 半製品 | E75: 5 | F75: JA | G75: =IFERROR(VLOOKUP(F75,'[1]2.仕掛品(製造部)'!MY:NB,4,0),0) -> 0 | H75: 0 | J75: 0 | AI75: =IFERROR(SUMIFS('4.3期末全在庫'!$G:$G,'4.3期末全在庫'!$B:$B,'4.仕掛品(製品課) (2)'!A75,'4.3期末全在庫'!$K:$K,"半製品"),"") -> 0 | AK75: =AF75*AI75 -> 0 | AO75: 0 | AQ75: =IF(SUM(H75:AK75)=0,0,"ok") -> 0
A76: 20131000001 | B76: 3SPPΦ68.3×1.5ﾊｲｼ-ﾄ | C76: 半製品 | D76: 半製品 | G76: =IFERROR(VLOOKUP(F76,'[1]2.仕掛品(製造部)'!MY:NB,4,0),0) -> 0 | H76: 0 | J76: 0 | AI76: =IFERROR(SUMIFS('4.3期末全在庫'!$G:$G,'4.3期末全在庫'!$B:$B,'4.仕掛品(製品課) (2)'!A76,'4.3期末全在庫'!$K:$K,"半製品"),"") -> 0 | AK76: =AF76*AI76 -> 0 | AO76: 0 | AQ76: =IF(SUM(H76:AK76)=0,0,"ok") -> 0
A77: 20131100008 | B77: NONI分包ｱﾙﾐﾌｨﾙﾑ(新ロゴ） | C77: 半製品 | D77: 半製品 | G77: =IFERROR(VLOOKUP(F77,'[1]2.仕掛品(製造部)'!MY:NB,4,0),0) -> 0 | H77: 0 | J77: 0 | AI77: =IFERROR(SUMIFS('4.3期末全在庫'!$G:$G,'4.3期末全在庫'!$B:$B,'4.仕掛品(製品課) (2)'!A77,'4.3期末全在庫'!$K:$K,"半製品"),"") -> 0 | AK77: =AF77*AI77 -> 0 | AO77: 0 | AQ77: =IF(SUM(H77:AK77)=0,0,"ok") -> 0
A78: 20131100013 | B78: NONI300g 表ﾗﾍﾞﾙ(新ロゴ) | C78: 半製品 | D78: 半製品 | G78: =IFERROR(VLOOKUP(F78,'[1]2.仕掛品(製造部)'!MY:NB,4,0),0) -> 0 | H78: 0 | J78: 0 | AI78: =IFERROR(SUMIFS('4.3期末全在庫'!$G:$G,'4.3期末全在庫'!$B:$B,'4.仕掛品(製品課) (2)'!A78,'4.3期末全在庫'!$K:$K,"半製品"),"") -> 0 | AK78: =AF78*AI78 -> 0 | AO78: 0 | AQ78: =IF(SUM(H78:AK78)=0,0,"ok") -> 0
A79: 20131200048 | B79: ｴｺｺﾞｰﾙﾄﾞEX180ｇ 検 | C79: 半製品 | D79: 半製品 | G79: =IFERROR(VLOOKUP(F79,'[1]2.仕掛品(製造部)'!MY:NB,4,0),0) -> 0 | H79: 0 | J79: 0 | AI79: =IFERROR(SUMIFS('4.3期末全在庫'!$G:$G,'4.3期末全在庫'!$B:$B,'4.仕掛品(製品課) (2)'!A79,'4.3期末全在庫'!$K:$K,"半製品"),"") -> 0 | AK79: =AF79*AI79 -> 0 | AO79: 0 | AQ79: =IF(SUM(H79:AK79)=0,0,"ok") -> 0
A80: 20140100009 | B80: 万田酵素145g(販売店向け)表ﾗﾍﾞﾙ | C80: 半製品 | D80: 半製品 | G80: =IFERROR(VLOOKUP(F80,'[1]2.仕掛品(製造部)'!MY:NB,4,0),0) -> 0 | H80: 0 | J80: 0 | AI80: =IFERROR(SUMIFS('4.3期末全在庫'!$G:$G,'4.3期末全在庫'!$B:$B,'4.仕掛品(製品課) (2)'!A80,'4.3期末全在庫'!$K:$K,"半製品"),"") -> 0 | AK80: =AF80*AI80 -> 0 | AO80: 0 | AQ80: =IF(SUM(H80:AK80)=0,0,"ok") -> 0
A81: 20140100078 | B81: 万田酵素300g 表ラベル 税 | C81: 半製品 | D81: 半製品 | G81: =IFERROR(VLOOKUP(F81,'[1]2.仕掛品(製造部)'!MY:NB,4,0),0) -> 0 | H81: 0 | J81: 0 | AI81: =IFERROR(SUMIFS('4.3期末全在庫'!$G:$G,'4.3期末全在庫'!$B:$B,'4.仕掛品(製品課) (2)'!A81,'4.3期末全在庫'!$K:$K,"半製品"),"") -> 0 | AK81: =AF81*AI81 -> 0 | AO81: 0 | AQ81: =IF(SUM(H81:AK81)=0,0,"ok") -> 0
A82: 20140800032 | B82: PV 2.5g×2 | C82: 半製品 | D82: 半製品 | E82: 5 | F82: PV | G82: =IFERROR(VLOOKUP(F82,'[1]2.仕掛品(製造部)'!MY:NB,4,0),0) -> 1.9177072 | H82: 0 | J82: 0 | AI82: =IFERROR(SUMIFS('4.3期末全在庫'!$G:$G,'4.3期末全在庫'!$B:$B,'4.仕掛品(製品課) (2)'!A82,'4.3期末全在庫'!$K:$K,"半製品"),"") -> 0 | AK82: =AF82*AI82 -> 0 | AO82: 0 | AQ82: =IF(SUM(H82:AK82)=0,0,"ok") -> 0
A83: 20140900009 | B83: Vitalize 2.5g×2 | C83: 半製品 | D83: 半製品 | E83: 2.5 | F83: B | G83: =IFERROR(VLOOKUP(F83,'[1]2.仕掛品(製造部)'!MY:NB,4,0),0) -> 1.3486947 | H83: 0 | J83: 0 | AI83: =IFERROR(SUMIFS('4.3期末全在庫'!$G:$G,'4.3期末全在庫'!$B:$B,'4.仕掛品(製品課) (2)'!A83,'4.3期末全在庫'!$K:$K,"半製品"),"") -> 0 | AK83: =AF83*AI83 -> 0 | AO83: 0 | AQ83: =IF(SUM(H83:AK83)=0,0,"ok") -> 0
A84: 20141100018 | B84: PPﾊｲｼｰﾄ 145g用 高久産業 | C84: 半製品 | D84: 半製品 | G84: =IFERROR(VLOOKUP(F84,'[1]2.仕掛品(製造部)'!MY:NB,4,0),0) -> 0 | H84: 0 | J84: 0 | AI84: =IFERROR(SUMIFS('4.3期末全在庫'!$G:$G,'4.3期末全在庫'!$B:$B,'4.仕掛品(製品課) (2)'!A84,'4.3期末全在庫'!$K:$K,"半製品"),"") -> 0 | AK84: =AF84*AI84 -> 0 | AO84: 0 | AQ84: =IF(SUM(H84:AK84)=0,0,"ok") -> 0
A85: 20151200008 | B85: P 2.5g | C85: 半製品 | D85: 半製品 | E85: 2.5 | F85: P | G85: =IFERROR(VLOOKUP(F85,'[1]2.仕掛品(製造部)'!MY:NB,4,0),0) -> 1.2657092 | H85: 0 | J85: 0 | AI85: =IFERROR(SUMIFS('4.3期末全在庫'!$G:$G,'4.3期末全在庫'!$B:$B,'4.仕掛品(製品課) (2)'!A85,'4.3期末全在庫'!$K:$K,"半製品"),"") -> 0 | AK85: =AF85*AI85 -> 0 | AO85: 0 | AQ85: =IF(SUM(H85:AK85)=0,0,"ok") -> 0
A86: 20160800001 | B86: EC-500用 ｷｬｯﾌﾟ(ｿﾌﾄﾛﾝ79.5×1.5) | C86: 半製品 | D86: 半製品 | G86: =IFERROR(VLOOKUP(F86,'[1]2.仕掛品(製造部)'!MY:NB,4,0),0) -> 0 | H86: 0 | J86: 0 | AI86: =IFERROR(SUMIFS('4.3期末全在庫'!$G:$G,'4.3期末全在庫'!$B:$B,'4.仕掛品(製品課) (2)'!A86,'4.3期末全在庫'!$K:$K,"半製品"),"") -> 0 | AK86: =AF86*AI86 -> 0 | AO86: 0 | AQ86: =IF(SUM(H86:AK86)=0,0,"ok") -> 0
A87: 20170300033 | B87: 145gﾋﾞﾝ用ﾛｰﾙｼｭﾘﾝｸﾌｨﾙﾑ | C87: 半製品 | D87: 半製品 | G87: =IFERROR(VLOOKUP(F87,'[1]2.仕掛品(製造部)'!MY:NB,4,0),0) -> 0 | H87: 0 | J87: 0 | AI87: =IFERROR(SUMIFS('4.3期末全在庫'!$G:$G,'4.3期末全在庫'!$B:$B,'4.仕掛品(製品課) (2)'!A87,'4.3期末全在庫'!$K:$K,"半製品"),"") -> 0 | AK87: =AF87*AI87 -> 0 | AO87: 0 | AQ87: =IF(SUM(H87:AK87)=0,0,"ok") -> 0
A88: 20170400032 | B88: 万田酵素 STANDARD 分包ﾌｨﾙﾑ | C88: 半製品 | D88: 半製品 | G88: =IFERROR(VLOOKUP(F88,'[1]2.仕掛品(製造部)'!MY:NB,4,0),0) -> 0 | H88: 0 | J88: 0 | AI88: =IFERROR(SUMIFS('4.3期末全在庫'!$G:$G,'4.3期末全在庫'!$B:$B,'4.仕掛品(製品課) (2)'!A88,'4.3期末全在庫'!$K:$K,"半製品"),"") -> 0 | AK88: =AF88*AI88 -> 0 | AO88: 0 | AQ88: =IF(SUM(H88:AK88)=0,0,"ok") -> 0
A89: 20170400033 | B89: 万田酵素 GINGER 分包ﾌｨﾙﾑ | C89: 半製品 | D89: 半製品 | G89: =IFERROR(VLOOKUP(F89,'[1]2.仕掛品(製造部)'!MY:NB,4,0),0) -> 0 | H89: 0 | J89: 0 | AI89: =IFERROR(SUMIFS('4.3期末全在庫'!$G:$G,'4.3期末全在庫'!$B:$B,'4.仕掛品(製品課) (2)'!A89,'4.3期末全在庫'!$K:$K,"半製品"),"") -> 0 | AK89: =AF89*AI89 -> 0 | AO89: 0 | AQ89: =IF(SUM(H89:AK89)=0,0,"ok") -> 0
A90: 20170500057 | B90: GINGER 2.5g | C90: 半製品 | D90: 半製品 | E90: 2.5 | F90: PE | G90: =IFERROR(VLOOKUP(F90,'[1]2.仕掛品(製造部)'!MY:NB,4,0),0) -> 1.1499334 | H90: 31600 | J90: 67389.992 | AI90: =IFERROR(SUMIFS('4.3期末全在庫'!$G:$G,'4.3期末全在庫'!$B:$B,'4.仕掛品(製品課) (2)'!A90,'4.3期末全在庫'!$K:$K,"半製品"),"") -> 18000 | AK90: =AI90*AF334/E109*E334 -> 125180.49 | AO90: 0 | AQ90: =IF(SUM(H90:AK90)=0,0,"ok") -> ok
A91: 20170500058 | B91: STANDARD 2.5g | C91: 半製品 | D91: 半製品 | E91: 2.5 | F91: PX | G91: =IFERROR(VLOOKUP(F91,'[1]2.仕掛品(製造部)'!MY:NB,4,0),0) -> 1.2530514 | H91: 8400 | J91: 20308.946 | AI91: =IFERROR(SUMIFS('4.3期末全在庫'!$G:$G,'4.3期末全在庫'!$B:$B,'4.仕掛品(製品課) (2)'!A91,'4.3期末全在庫'!$K:$K,"半製品"),"") -> 26000 | AK91: =AF273*AI91/E91*E273 -> 463797.99 | AO91: 0 | AQ91: =IF(SUM(H91:AK91)=0,0,"ok") -> ok
A92: 20170700070 | B92: XC 1ml×2 | C92: 半製品 | D92: 半製品 | E92: 2.6 | F92: XC | G92: =IFERROR(VLOOKUP(F92,'[1]2.仕掛品(製造部)'!MY:NB,4,0),0) -> 2.7031088 | H92: 0 | J92: 0 | AI92: =IFERROR(SUMIFS('4.3期末全在庫'!$G:$G,'4.3期末全在庫'!$B:$B,'4.仕掛品(製品課) (2)'!A92,'4.3期末全在庫'!$K:$K,"半製品"),"") -> 0 | AK92: =AF92*AI92 -> 0 | AO92: 0 | AQ92: =IF(SUM(H92:AK92)=0,0,"ok") -> 0
A93: 20171100054 | B93: 145g ｷｬｯﾌﾟ(刻印なし) H | C93: 半製品 | D93: 半製品 | G93: =IFERROR(VLOOKUP(F93,'[1]2.仕掛品(製造部)'!MY:NB,4,0),0) -> 0 | H93: 0 | J93: 0 | AI93: =IFERROR(SUMIFS('4.3期末全在庫'!$G:$G,'4.3期末全在庫'!$B:$B,'4.仕掛品(製品課) (2)'!A93,'4.3期末全在庫'!$K:$K,"半製品"),"") -> 0 | AK93: =AF93*AI93 -> 0 | AO93: 0 | AQ93: =IF(SUM(H93:AK93)=0,0,"ok") -> 0
A94: 20180300010 | B94: STANDARD 26g ﾁｭｰﾌﾞ一式 | C94: 半製品 | D94: 半製品 | G94: =IFERROR(VLOOKUP(F94,'[1]2.仕掛品(製造部)'!MY:NB,4,0),0) -> 0 | H94: 0 | J94: 0 | AI94: =IFERROR(SUMIFS('4.3期末全在庫'!$G:$G,'4.3期末全在庫'!$B:$B,'4.仕掛品(製品課) (2)'!A94,'4.3期末全在庫'!$K:$K,"半製品"),"") -> 0 | AK94: =AF94*AI94 -> 0 | AO94: 0 | AQ94: =IF(SUM(H94:AK94)=0,0,"ok") -> 0
A95: 20180400012 | B95: NONI300g 裏ベル(新ﾛｺﾞ)② | C95: 半製品 | D95: 半製品 | G95: =IFERROR(VLOOKUP(F95,'[1]2.仕掛品(製造部)'!MY:NB,4,0),0) -> 0 | H95: 0 | J95: 0 | AI95: =IFERROR(SUMIFS('4.3期末全在庫'!$G:$G,'4.3期末全在庫'!$B:$B,'4.仕掛品(製品課) (2)'!A95,'4.3期末全在庫'!$K:$K,"半製品"),"") -> 0 | AK95: =AF95*AI95 -> 0 | AN95: 341.64818 | AO95: 1056.8317 | AQ95: =IF(SUM(H95:AK95)=0,0,"ok") -> 0
A96: 20180400027 | B96: GINGER ﾁｭｰﾌﾞﾀｲﾌﾟ 26g | C96: 半製品 | D96: 半製品 | E96: 26 | F96: PE | G96: =IFERROR(VLOOKUP(F96,'[1]2.仕掛品(製造部)'!MY:NB,4,0),0) -> 1.1499334 | H96: 0 | J96: 0 | AI96: =IFERROR(SUMIFS('4.3期末全在庫'!$G:$G,'4.3期末全在庫'!$B:$B,'4.仕掛品(製品課) (2)'!A96,'4.3期末全在庫'!$K:$K,"半製品"),"") -> 0 | AK96: =AF96*AI96 -> 0 | AN96: 95.723269 | AO96: 329.00288 | AQ96: =IF(SUM(H96:AK96)=0,0,"ok") -> 0
A97: 20180400028 | B97: STANDARD ﾁｭｰﾌﾞﾀｲﾌﾟ 26g | C97: 半製品 | D97: 半製品 | E97: 26 | F97: PX | G97: =IFERROR(VLOOKUP(F97,'[1]2.仕掛品(製造部)'!MY:NB,4,0),0) -> 1.2530514 | H97: 0 | J97: 0 | AI97: =IFERROR(SUMIFS('4.3期末全在庫'!$G:$G,'4.3期末全在庫'!$B:$B,'4.仕掛品(製品課) (2)'!A97,'4.3期末全在庫'!$K:$K,"半製品"),"") -> 0 | AK97: =AF97*AI97 -> 0 | AN97: 550.64155 | AO97: 2161.6618 | AQ97: =IF(SUM(H97:AK97)=0,0,"ok") -> 0
A98: 20180400029 | B98: MULBERRY ﾁｭｰﾌﾞﾀｲﾌﾟ 26g | C98: 半製品 | D98: 半製品 | E98: 26 | F98: MP | G98: =IFERROR(VLOOKUP(F98,'[1]2.仕掛品(製造部)'!MY:NB,4,0),0) -> 1.1798248 | H98: 0 | J98: 0 | AI98: =IFERROR(SUMIFS('4.3期末全在庫'!$G:$G,'4.3期末全在庫'!$B:$B,'4.仕掛品(製品課) (2)'!A98,'4.3期末全在庫'!$K:$K,"半製品"),"") -> 0 | AK98: =AF98*AI98 -> 0 | AN98: 721.07321 | AO98: 3984.9366 | AQ98: =IF(SUM(H98:AK98)=0,0,"ok") -> 0
A99: 20180700008 | B99: MULBERRY 2.5g | C99: 半製品 | D99: 半製品 | E99: 2.5 | F99: MP | G99: =IFERROR(VLOOKUP(F99,'[1]2.仕掛品(製造部)'!MY:NB,4,0),0) -> 1.1798248 | H99: 40000 | J99: 87224.699 | AI99: =IFERROR(SUMIFS('4.3期末全在庫'!$G:$G,'4.3期末全在庫'!$B:$B,'4.仕掛品(製品課) (2)'!A99,'4.3期末全在庫'!$K:$K,"半製品"),"") -> 24200 | AK99: =AF333*AI99/E99*E333 -> 172038.19 | AN99: 1775.9687 | AO99: 7296.6701 | AQ99: =IF(SUM(H99:AK99)=0,0,"ok") -> ok
A100: 20191200054 | B100: 新・MKF-Ⅱ 30g ﾗﾍﾞﾙ（改）② | C100: 半製品 | D100: 半製品 | G100: =IFERROR(VLOOKUP(F100,'[1]2.仕掛品(製造部)'!MY:NB,4,0),0) -> 0 | H100: 0 | J100: 0 | AI100: =IFERROR(SUMIFS('4.3期末全在庫'!$G:$G,'4.3期末全在庫'!$B:$B,'4.仕掛品(製品課) (2)'!A100,'4.3期末全在庫'!$K:$K,"半製品"),"") -> 0 | AK100: =AF100*AI100 -> 0 | AN100: 138.98756 | AO100: 293.86191 | AQ100: =IF(SUM(H100:AK100)=0,0,"ok") -> 0
A101: 20191200056 | B101: MKF-Ⅱ 5A ﾘｷｯﾄﾞ 30g ﾗﾍﾞﾙ(改)② | C101: 半製品 | D101: 半製品 | G101: =IFERROR(VLOOKUP(F101,'[1]2.仕掛品(製造部)'!MY:NB,4,0),0) -> 0 | H101: 0 | J101: 0 | AI101: =IFERROR(SUMIFS('4.3期末全在庫'!$G:$G,'4.3期末全在庫'!$B:$B,'4.仕掛品(製品課) (2)'!A101,'4.3期末全在庫'!$K:$K,"半製品"),"") -> 0 | AK101: =AF101*AI101 -> 0 | AN101: 970.35569 | AO101: 4245.3617 | AQ101: =IF(SUM(H101:AK101)=0,0,"ok") -> 0
...

Sheet 4.仕掛品(製品課)
A1: 第37期 仕掛品(製品課)
F3: 製品記号 | H3: 期首棚卸 | K3: 当期投入 | AD3: 当期商品製造原価 | AG3: 在庫調整 | AI3: 期末棚卸
H4: 数量 | L4: 仕掛品(製品課製造分) | N4: 仕掛品(外注品内製分) | P4: 仕掛品(製造部製造分) | R4: 資材費 | U4: 労務費(製品課) | W4: 労務費(製造部) | Y4: 経費 | AA4: 外注加工費 | AB4: 別コードに振替 | AI4: 数量
A5: SCコード | B5: 商品名 | C5: 区分 | D5: 半製品 | E5: 内容量(g) | F5: 製品記号 | G5: ｸﾞﾗﾑ単価 | H5: 数量 | I5: 進捗度 | J5: 金額 | K5: 数量 | L5: 配賦係数 | M5: 金額 | N5: 配賦係数 | O5: 金額 | P5: 配賦係数 | Q5: 金額 | R5: 包材価格 | S5: 配賦係数 | T5: 金額 | U5: 配賦係数 | V5: 金額 | W5: 配賦係数 | X5: 金額 | Y5: 配賦係数 | Z5: 金額 | AA5: (原液原価込み) | AB5: 数量 | AC5: 金額 | AD5: 数量 | AE5: 金額 | AF5: 単価 | AG5: 数量 | AH5: 原価 | AI5: 数量 | AJ5: 進捗度 | AK5: 金額 | AN5: 34期資材 | AO5: 34期単価 | AQ5: 絞り込み
A6: 20110300023 | B6: EH酵素 6g(2g 3連包) | C6: 半製品 | D6: 半製品 | E6: 6 | F6: CE | G6: =IFERROR(VLOOKUP(F6,'[1]2.仕掛品(製造部)'!MY:NB,4,0),0) -> 0 | H6: 0 | J6: 0 | AI6: =IFERROR(SUMIFS('4.3期末全在庫'!$G:$G,'4.3期末全在庫'!$B:$B,'4.仕掛品(製品課)'!A6,'4.3期末全在庫'!$K:$K,"半製品"),"") -> 0 | AK6: =AF6*AI6 -> 0 | AO6: 0
A7: 20110801125 | B7: 【瓶】ｽｰﾊﾟｰ万田酵素 氣Ⅰ | C7: 半製品 | D7: 半製品 | G7: =IFERROR(VLOOKUP(F7,'[1]2.仕掛品(製造部)'!MY:NB,4,0),0) -> 0 | H7: 0 | J7: 0 | AI7: =IFERROR(SUMIFS('4.3期末全在庫'!$G:$G,'4.3期末全在庫'!$B:$B,'4.仕掛品(製品課)'!A7,'4.3期末全在庫'!$K:$K,"半製品"),"") -> 0 | AK7: =AF7*AI7 -> 0 | AN7: 248.93192 | AO7: 0
A8: 20110801128 | B8: 【瓶】ｴｺｺﾞｰﾙﾄﾞEX 180g | C8: 半製品 | D8: 半製品 | G8: =IFERROR(VLOOKUP(F8,'[1]2.仕掛品(製造部)'!MY:NB,4,0),0) -> 0 | H8: 0 | J8: 0 | AI8: =IFERROR(SUMIFS('4.3期末全在庫'!$G:$G,'4.3期末全在庫'!$B:$B,'4.仕掛品(製品課)'!A8,'4.3期末全在庫'!$K:$K,"半製品"),"") -> 0 | AK8: =AF8*AI8 -> 0 | AO8: 12.902551
A9: 20110801129 | B9: 【ﾎﾞﾄﾙ】Jﾎﾞﾄﾙ 丸型細口 1ﾘｯﾄﾙ | C9: 半製品 | D9: 半製品 | G9: =IFERROR(VLOOKUP(F9,'[1]2.仕掛品(製造部)'!MY:NB,4,0),0) -> 0 | H9: 0 | J9: 0 | AI9: =IFERROR(SUMIFS('4.3期末全在庫'!$G:$G,'4.3期末全在庫'!$B:$B,'4.仕掛品(製品課)'!A9,'4.3期末全在庫'!$K:$K,"半製品"),"") -> 0 | AK9: =AF9*AI9 -> 0 | AO9: 6.7658564
A10: 20110801131 | B10: 【瓶】155g S-130 白 | C10: 半製品 | D10: 半製品 | G10: =IFERROR(VLOOKUP(F10,'[1]2.仕掛品(製造部)'!MY:NB,4,0),0) -> 0 | H10: 0 | J10: 0 | AI10: =IFERROR(SUMIFS('4.3期末全在庫'!$G:$G,'4.3期末全在庫'!$B:$B,'4.仕掛品(製品課)'!A10,'4.3期末全在庫'!$K:$K,"半製品"),"") -> 0 | AK10: =AF10*AI10 -> 0 | AO10: 7.5356885
A11: 20110801132 | B11: 【瓶】145g E-100 六角（白） | C11: 半製品 | D11: 半製品 | G11: =IFERROR(VLOOKUP(F11,'[1]2.仕掛品(製造部)'!MY:NB,4,0),0) -> 0 | H11: 0 | J11: 0 | AI11: =IFERROR(SUMIFS('4.3期末全在庫'!$G:$G,'4.3期末全在庫'!$B:$B,'4.仕掛品(製品課)'!A11,'4.3期末全在庫'!$K:$K,"半製品"),"") -> 0 | AK11: =AF11*AI11 -> 0 | AO11: 0
A12: 20110801133 | B12: 【瓶】EC-500 | C12: 半製品 | D12: 半製品 | G12: =IFERROR(VLOOKUP(F12,'[1]2.仕掛品(製造部)'!MY:NB,4,0),0) -> 0 | H12: 0 | J12: 0 | AI12: =IFERROR(SUMIFS('4.3期末全在庫'!$G:$G,'4.3期末全在庫'!$B:$B,'4.仕掛品(製品課)'!A12,'4.3期末全在庫'!$K:$K,"半製品"),"") -> 0 | AK12: =AF12*AI12 -> 0 | AO12: 0
A13: 20110801134 | B13: 【瓶】M-70 6角 茶 | C13: 半製品 | D13: 半製品 | G13: =IFERROR(VLOOKUP(F13,'[1]2.仕掛品(製造部)'!MY:NB,4,0),0) -> 0 | H13: 0 | J13: 0 | AI13: =IFERROR(SUMIFS('4.3期末全在庫'!$G:$G,'4.3期末全在庫'!$B:$B,'4.仕掛品(製品課)'!A13,'4.3期末全在庫'!$K:$K,"半製品"),"") -> 0 | AK13: =AF13*AI13 -> 0 | AO13: 0
A14: 20110801135 | B14: 【瓶】六角茶色 145g E-100 | C14: 半製品 | D14: 半製品 | G14: =IFERROR(VLOOKUP(F14,'[1]2.仕掛品(製造部)'!MY:NB,4,0),0) -> 0 | H14: 0 | J14: 0 | AI14: =IFERROR(SUMIFS('4.3期末全在庫'!$G:$G,'4.3期末全在庫'!$B:$B,'4.仕掛品(製品課)'!A14,'4.3期末全在庫'!$K:$K,"半製品"),"") -> 0 | AK14: =AF14*AI14 -> 0 | AO14: 0
A15: 20110801137 | B15: 【瓶】食品8角 310g | C15: 半製品 | D15: 半製品 | G15: =IFERROR(VLOOKUP(F15,'[1]2.仕掛品(製造部)'!MY:NB,4,0),0) -> 0 | H15: 0 | J15: 0 | AI15: =IFERROR(SUMIFS('4.3期末全在庫'!$G:$G,'4.3期末全在庫'!$B:$B,'4.仕掛品(製品課)'!A15,'4.3期末全在庫'!$K:$K,"半製品"),"") -> 0 | AK15: =AF15*AI15 -> 0 | AO15: 6.1045485
A16: 20110801139 | B16: 【瓶】E-90 | C16: 半製品 | D16: 半製品 | G16: =IFERROR(VLOOKUP(F16,'[1]2.仕掛品(製造部)'!MY:NB,4,0),0) -> 0 | H16: 0 | J16: 0 | AI16: =IFERROR(SUMIFS('4.3期末全在庫'!$G:$G,'4.3期末全在庫'!$B:$B,'4.仕掛品(製品課)'!A16,'4.3期末全在庫'!$K:$K,"半製品"),"") -> 0 | AK16: =AF16*AI16 -> 0 | AO16: 0
A17: 20110801142 | B17: 万田酵素 145g (販売店向け) 半 | C17: 半製品 | D17: 半製品 | E17: 145 | F17: P | G17: =IFERROR(VLOOKUP(F17,'[1]2.仕掛品(製造部)'!MY:NB,4,0),0) -> 1.2657092 | H17: 0 | J17: 0 | AI17: =IFERROR(SUMIFS('4.3期末全在庫'!$G:$G,'4.3期末全在庫'!$B:$B,'4.仕掛品(製品課)'!A17,'4.3期末全在庫'!$K:$K,"半製品"),"") -> 0 | AK17: =AF17*AI17 -> 0 | AO17: 0
A18: 20110801143 | B18: 万田酵素 300g (販売店） 半 | C18: 半製品 | D18: 半製品 | G18: =IFERROR(VLOOKUP(F18,'[1]2.仕掛品(製造部)'!MY:NB,4,0),0) -> 0 | H18: 0 | J18: 0 | AI18: =IFERROR(SUMIFS('4.3期末全在庫'!$G:$G,'4.3期末全在庫'!$B:$B,'4.仕掛品(製品課)'!A18,'4.3期末全在庫'!$K:$K,"半製品"),"") -> 0 | AK18: =AF18*AI18 -> 0 | AO18: 0 | AQ18: =IF(SUM(H18:AK18)=0,0,"ok") -> 0
A19: 20110801158 | B19: PG 2.5g×2 | C19: 半製品 | D19: 半製品 | E19: 5 | F19: PG | G19: =IFERROR(VLOOKUP(F19,'[1]2.仕掛品(製造部)'!MY:NB,4,0),0) -> 1.4973298 | H19: 180 | J19: 1110.9506 | AI19: =IFERROR(SUMIFS('4.3期末全在庫'!$G:$G,'4.3期末全在庫'!$B:$B,'4.仕掛品(製品課)'!A19,'4.3期末全在庫'!$K:$K,"半製品"),"") -> 1350 | AK19: =AI19*AF175/E19*E175 -> 82945.988 | AO19: 0 | AQ19: =IF(SUM(H19:AK19)=0,0,"ok") -> ok
A20: 20110801159 | B20: ZA 2.5g×2 | C20: 半製品 | D20: 半製品 | E20: 5 | F20: ZA | G20: =IFERROR(VLOOKUP(F20,'[1]2.仕掛品(製造部)'!MY:NB,4,0),0) -> 2.2073146 | H20: 4500 | J20: 37735.653 | AI20: =IFERROR(SUMIFS('4.3期末全在庫'!$G:$G,'4.3期末全在庫'!$B:$B,'4.仕掛品(製品課)'!A20,'4.3期末全在庫'!$K:$K,"半製品"),"") -> 0 | AK20: =AF20*AI20 -> 0 | AO20: 0 | AQ20: =IF(SUM(H20:AK20)=0,0,"ok") -> ok
A21: 20110801161 | B21: BE 2.5g×2 | C21: 半製品 | D21: 半製品 | E21: 5 | F21: BE | G21: =IFERROR(VLOOKUP(F21,'[1]2.仕掛品(製造部)'!MY:NB,4,0),0) -> 1.6947416 | H21: 3800 | J21: 25204.237 | AI21: =IFERROR(SUMIFS('4.3期末全在庫'!$G:$G,'4.3期末全在庫'!$B:$B,'4.仕掛品(製品課)'!A21,'4.3期末全在庫'!$K:$K,"半製品"),"") -> 0 | AK21: =AF21*AI21 -> 0 | AO21: 7.1801316 | AQ21: =IF(SUM(H21:AK21)=0,0,"ok") -> ok
A22: 20110801164 | B22: ｊPG 2.5g×2 | C22: 半製品 | D22: 半製品 | E22: 5 | F22: PG | G22: =IFERROR(VLOOKUP(F22,'[1]2.仕掛品(製造部)'!MY:NB,4,0),0) -> 1.4973298 | H22: 900 | J22: 5554.7532 | AI22: =IFERROR(SUMIFS('4.3期末全在庫'!$G:$G,'4.3期末全在庫'!$B:$B,'4.仕掛品(製品課)'!A22,'4.3期末全在庫'!$K:$K,"半製品"),"") -> 1800 | AK22: =AI22*AF175/E22*E175 -> 110594.65 | AO22: 0 | AQ22: =IF(SUM(H22:AK22)=0,0,"ok") -> ok
A23: 20110801167 | B23: W 2.5g×2 | C23: 半製品 | D23: 半製品 | E23: 5 | F23: W | G23: =IFERROR(VLOOKUP(F23,'[1]2.仕掛品(製造部)'!MY:NB,4,0),0) -> 0 | H23: 0 | J23: 0 | AI23: =IFERROR(SUMIFS('4.3期末全在庫'!$G:$G,'4.3期末全在庫'!$B:$B,'4.仕掛品(製品課)'!A23,'4.3期末全在庫'!$K:$K,"半製品"),"") -> 0 | AK23: =AF23*AI23 -> 0 | AN23: 11.488231 | AO23: 67.62891 | AQ23: =IF(SUM(H23:AK23)=0,0,"ok") -> 0
A24: 20110801168 | B24: PE 2.5g×2 | C24: 半製品 | D24: 半製品 | E24: 5 | F24: PE | G24: =IFERROR(VLOOKUP(F24,'[1]2.仕掛品(製造部)'!MY:NB,4,0),0) -> 1.1499334 | H24: 0 | J24: 0 | AI24: =IFERROR(SUMIFS('4.3期末全在庫'!$G:$G,'4.3期末全在庫'!$B:$B,'4.仕掛品(製品課)'!A24,'4.3期末全在庫'!$K:$K,"半製品"),"") -> 0 | AK24: =AF24*AI24 -> 0 | AO24: 1328.0203 | AQ24: =IF(SUM(H24:AK24)=0,0,"ok") -> 0
A25: 20110801169 | B25: L 5000 (海外向け) Y 5g×3 | C25: 半製品 | D25: 半製品 | E25: 15 | F25: Y | G25: =IFERROR(VLOOKUP(F25,'[1]2.仕掛品(製造部)'!MY:NB,4,0),0) -> 1.6405741 | H25: 0 | J25: 0 | AI25: =IFERROR(SUMIFS('4.3期末全在庫'!$G:$G,'4.3期末全在庫'!$B:$B,'4.仕掛品(製品課)'!A25,'4.3期末全在庫'!$K:$K,"半製品"),"") -> 0 | AK25: =AF25*AI25 -> 0 | AN25: 20.138231 | AO25: 72.320673 | AQ25: =IF(SUM(H25:AK25)=0,0,"ok") -> 0
A26: 20110801179 | B26: FB 2.5g×2 | C26: 半製品 | D26: 半製品 | E26: 5 | F26: FB | G26: =IFERROR(VLOOKUP(F26,'[1]2.仕掛品(製造部)'!MY:NB,4,0),0) -> 1.8947649 | H26: 0 | J26: 0 | AI26: =IFERROR(SUMIFS('4.3期末全在庫'!$G:$G,'4.3期末全在庫'!$B:$B,'4.仕掛品(製品課)'!A26,'4.3期末全在庫'!$K:$K,"半製品"),"") -> 0 | AK26: =AF26*AI26 -> 0 | AN26: 140.76441 | AO26: 427.69344 | AQ26: =IF(SUM(H26:AK26)=0,0,"ok") -> 0
A27: 20110801204 | B27: D 1.67g×2 | C27: 半製品 | D27: 半製品 | E27: 3.34 | F27: D | G27: =IFERROR(VLOOKUP(F27,'[1]2.仕掛品(製造部)'!MY:NB,4,0),0) -> 1.3499631 | H27: 0 | J27: 0 | AI27: =IFERROR(SUMIFS('4.3期末全在庫'!$G:$G,'4.3期末全在庫'!$B:$B,'4.仕掛品(製品課)'!A27,'4.3期末全在庫'!$K:$K,"半製品"),"") -> 0 | AK27: =AF27*AI27 -> 0 | AN27: 762.89597 | AO27: 1582.157 | AQ27: =IF(SUM(H27:AK27)=0,0,"ok") -> 0
A28: 20110801206 | B28: L 5000(ﾀﾅｶ向け) Y 5g×3 | C28: 半製品 | D28: 半製品 | E28: 15 | F28: Y | G28: =IFERROR(VLOOKUP(F28,'[1]2.仕掛品(製造部)'!MY:NB,4,0),0) -> 1.6405741 | H28: 0 | J28: 0 | AI28: =IFERROR(SUMIFS('4.3期末全在庫'!$G:$G,'4.3期末全在庫'!$B:$B,'4.仕掛品(製品課)'!A28,'4.3期末全在庫'!$K:$K,"半製品"),"") -> 0 | AK28: =AF28*AI28 -> 0 | AO28: 0 | AQ28: =IF(SUM(H28:AK28)=0,0,"ok") -> 0
A29: 20110801213 | B29: CE 2g×3 | C29: 半製品 | D29: 半製品 | E29: 6 | F29: CE | G29: =IFERROR(VLOOKUP(F29,'[1]2.仕掛品(製造部)'!MY:NB,4,0),0) -> 0 | H29: 0 | J29: 0 | AI29: =IFERROR(SUMIFS('4.3期末全在庫'!$G:$G,'4.3期末全在庫'!$B:$B,'4.仕掛品(製品課)'!A29,'4.3期末全在庫'!$K:$K,"半製品"),"") -> 0 | AK29: =AF29*AI29 -> 0 | AN29: 192.77056 | AO29: 0 | AQ29: =IF(SUM(H29:AK29)=0,0,"ok") -> 0
A30: 20110801215 | B30: 5A 5g×2 | C30: 半製品 | D30: 半製品 | E30: 10 | F30: 5A | G30: =IFERROR(VLOOKUP(F30,'[1]2.仕掛品(製造部)'!MY:NB,4,0),0) -> 5.1725294 | H30: 0 | J30: 0 | AI30: =IFERROR(SUMIFS('4.3期末全在庫'!$G:$G,'4.3期末全在庫'!$B:$B,'4.仕掛品(製品課)'!A30,'4.3期末全在庫'!$K:$K,"半製品"),"") -> 0 | AK30: =AF30*AI30 -> 0 | AN30: 82.903661 | AO30: 0 | AQ30: =IF(SUM(H30:AK30)=0,0,"ok") -> 0
A31: 20110801216 | B31: 新･MKF-Ⅱ 30g 半 | C31: 半製品 | D31: 半製品 | G31: =IFERROR(VLOOKUP(F31,'[1]2.仕掛品(製造部)'!MY:NB,4,0),0) -> 0 | H31: 0 | J31: 0 | AI31: =IFERROR(SUMIFS('4.3期末全在庫'!$G:$G,'4.3期末全在庫'!$B:$B,'4.仕掛品(製品課)'!A31,'4.3期末全在庫'!$K:$K,"半製品"),"") -> 0 | AK31: =AF31*AI31 -> 0 | AN31: 92.267501 | AO31: 0 | AQ31: =IF(SUM(H31:AK31)=0,0,"ok") -> 0
A32: 20110801217 | B32: MKF-Ⅱ 5A ﾘｷｯﾄﾞ 30g 半 | C32: 半製品 | D32: 半製品 | G32: =IFERROR(VLOOKUP(F32,'[1]2.仕掛品(製造部)'!MY:NB,4,0),0) -> 0 | H32: 0 | J32: 0 | AI32: =IFERROR(SUMIFS('4.3期末全在庫'!$G:$G,'4.3期末全在庫'!$B:$B,'4.仕掛品(製品課)'!A32,'4.3期末全在庫'!$K:$K,"半製品"),"") -> 0 | AK32: =AF32*AI32 -> 0 | AO32: 0 | AQ32: =IF(SUM(H32:AK32)=0,0,"ok") -> 0
A33: 20110801221 | B33: DC 2.5g×2 | C33: 半製品 | D33: 半製品 | E33: 5 | F33: DC | G33: =IFERROR(VLOOKUP(F33,'[1]2.仕掛品(製造部)'!MY:NB,4,0),0) -> 2.5414453 | H33: 0 | J33: 0 | AI33: =IFERROR(SUMIFS('4.3期末全在庫'!$G:$G,'4.3期末全在庫'!$B:$B,'4.仕掛品(製品課)'!A33,'4.3期末全在庫'!$K:$K,"半製品"),"") -> 0 | AK33: =AF33*AI33 -> 0 | AO33: 0 | AQ33: =IF(SUM(H33:AK33)=0,0,"ok") -> 0
A34: 20110801223 | B34: ﾅﾁｭﾗﾙ酵素 ﾌﾞﾙｰﾍﾞﾘｰﾌﾟﾗｽ 2.5g×3 | C34: 半製品 | D34: 半製品 | E34: 7.5 | F34: PR | G34: =IFERROR(VLOOKUP(F34,'[1]2.仕掛品(製造部)'!MY:NB,4,0),0) -> 1.8060342 | H34: 0 | J34: 0 | AI34: =IFERROR(SUMIFS('4.3期末全在庫'!$G:$G,'4.3期末全在庫'!$B:$B,'4.仕掛品(製品課)'!A34,'4.3期末全在庫'!$K:$K,"半製品"),"") -> 0 | AK34: =AF34*AI34 -> 0 | AN34: 471.83603 | AO34: 3237.5045 | AQ34: =IF(SUM(H34:AK34)=0,0,"ok") -> 0
A35: 20110801234 | B35: Man-Koso P 2.5g×4 | C35: 半製品 | D35: 半製品 | E35: 10 | F35: P | G35: =IFERROR(VLOOKUP(F35,'[1]2.仕掛品(製造部)'!MY:NB,4,0),0) -> 1.2657092 | H35: 0 | J35: 0 | AI35: =IFERROR(SUMIFS('4.3期末全在庫'!$G:$G,'4.3期末全在庫'!$B:$B,'4.仕掛品(製品課)'!A35,'4.3期末全在庫'!$K:$K,"半製品"),"") -> 0 | AK35: =AF35*AI35 -> 0 | AN35: 815.61763 | AO35: 0 | AQ35: =IF(SUM(H35:AK35)=0,0,"ok") -> 0
A36: 20110801266 | B36: B 2.5g×2 | C36: 半製品 | D36: 半製品 | E36: 5 | F36: B | G36: =IFERROR(VLOOKUP(F36,'[1]2.仕掛品(製造部)'!MY:NB,4,0),0) -> 1.3486947 | H36: 0 | J36: 0 | AI36: =IFERROR(SUMIFS('4.3期末全在庫'!$G:$G,'4.3期末全在庫'!$B:$B,'4.仕掛品(製品課)'!A36,'4.3期末全在庫'!$K:$K,"半製品"),"") -> 0 | AK36: =AF36*AI36 -> 0 | AN36: 484.84922 | AO36: 1826.5396 | AQ36: =IF(SUM(H36:AK36)=0,0,"ok") -> 0
A37: 20110801267 | B37: EB 2.5g×2 | C37: 半製品 | D37: 半製品 | E37: 5 | F37: EB | G37: =IFERROR(VLOOKUP(F37,'[1]2.仕掛品(製造部)'!MY:NB,4,0),0) -> 1.3583252 | H37: 4500 | J37: 19728.659 | AI37: =IFERROR(SUMIFS('4.3期末全在庫'!$G:$G,'4.3期末全在庫'!$B:$B,'4.仕掛品(製品課)'!A37,'4.3期末全在庫'!$K:$K,"半製品"),"") -> 12600 | AK37: =AI37*AF172/E37*E172 -> 369655.96 | AO37: 2136.147 | AQ37: =IF(SUM(H37:AK37)=0,0,"ok") -> ok
A38: 20110801268 | B38: V 2.5g×2 | C38: 半製品 | D38: 半製品 | E38: 5 | F38: V | G38: =IFERROR(VLOOKUP(F38,'[1]2.仕掛品(製造部)'!MY:NB,4,0),0) -> 1.2113727 | H38: 0 | J38: 0 | AI38: =IFERROR(SUMIFS('4.3期末全在庫'!$G:$G,'4.3期末全在庫'!$B:$B,'4.仕掛品(製品課)'!A38,'4.3期末全在庫'!$K:$K,"半製品"),"") -> 12700 | AK38: =AI38*AF178/E38*E178 -> 337292.91 | AN38: 594.95854 | AO38: 2504.1591 | AQ38: =IF(SUM(H38:AK38)=0,0,"ok") -> ok
A39: 20110801270 | B39: I 2.5g×2 | C39: 半製品 | D39: 半製品 | E39: 5 | F39: I | G39: =IFERROR(VLOOKUP(F39,'[1]2.仕掛品(製造部)'!MY:NB,4,0),0) -> 2.6770701 | H39: 0 | J39: 0 | AI39: =IFERROR(SUMIFS('4.3期末全在庫'!$G:$G,'4.3期末全在庫'!$B:$B,'4.仕掛品(製品課)'!A39,'4.3期末全在庫'!$K:$K,"半製品"),"") -> 0 | AK39: =AF39*AI39 -> 0 | AN39: 244.44922 | AO39: 914.29186 | AQ39: =IF(SUM(H39:AK39)=0,0,"ok") -> 0
A40: 20110801272 | B40: MANDA KOSO 2.5g×2 | C40: 半製品 | D40: 半製品 | E40: 5 | F40: P | G40: =IFERROR(VLOOKUP(F40,'[1]2.仕掛品(製造部)'!MY:NB,4,0),0) -> 1.2657092 | H40: 0 | J40: 0 | AI40: =IFERROR(SUMIFS('4.3期末全在庫'!$G:$G,'4.3期末全在庫'!$B:$B,'4.仕掛品(製品課)'!A40,'4.3期末全在庫'!$K:$K,"半製品"),"") -> 0 | AK40: =AF40*AI40 -> 0 | AN40: 204.85381 | AO40: 1187.3955 | AQ40: =IF(SUM(H40:AK40)=0,0,"ok") -> 0
A41: 20110801273 | B41: P 2.5g×2 | C41: 半製品 | D41: 半製品 | E41: 5 | F41: P | G41: =IFERROR(VLOOKUP(F41,'[1]2.仕掛品(製造部)'!MY:NB,4,0),0) -> 1.2657092 | H41: 124800 | J41: 599836.36 | AI41: =IFERROR(SUMIFS('4.3期末全在庫'!$G:$G,'4.3期末全在庫'!$B:$B,'4.仕掛品(製品課)'!A41,'4.3期末全在庫'!$K:$K,"半製品"),"") -> 52300 | AK41: =AI41*AF336/E41*E336 -> 670818.01 | AN41: 68.967368 | AO41: 729.09329 | AQ41: =IF(SUM(H41:AK41)=0,0,"ok") -> ok
A42: 20110801274 | B42: O 2.5g×2 | C42: 半製品 | D42: 半製品 | E42: 5 | F42: O | G42: =IFERROR(VLOOKUP(F42,'[1]2.仕掛品(製造部)'!MY:NB,4,0),0) -> 1.3228108 | H42: 0 | J42: 0 | AI42: =IFERROR(SUMIFS('4.3期末全在庫'!$G:$G,'4.3期末全在庫'!$B:$B,'4.仕掛品(製品課)'!A42,'4.3期末全在庫'!$K:$K,"半製品"),"") -> 0 | AK42: =AF42*AI42 -> 0 | AN42: 44.058684 | AO42: 433.65191 | AQ42: =IF(SUM(H42:AK42)=0,0,"ok") -> 0
A43: 20110801277 | B43: ﾌﾞﾙｰﾍﾞﾘｰﾌﾟﾗｽ 2.5g×2 | C43: 半製品 | D43: 半製品 | E43: 5 | F43: PR | G43: =IFERROR(VLOOKUP(F43,'[1]2.仕掛品(製造部)'!MY:NB,4,0),0) -> 1.8060342 | H43: 0 | J43: 0 | AI43: =IFERROR(SUMIFS('4.3期末全在庫'!$G:$G,'4.3期末全在庫'!$B:$B,'4.仕掛品(製品課)'!A43,'4.3期末全在庫'!$K:$K,"半製品"),"") -> 0 | AK43: =AF43*AI43 -> 0 | AN43: 124.25737 | AO43: 655.0643 | AQ43: =IF(SUM(H43:AK43)=0,0,"ok") -> 0
A44: 20110801280 | B44: G 2.5g×2 | C44: 半製品 | D44: 半製品 | E44: 5 | F44: G | G44: =IFERROR(VLOOKUP(F44,'[1]2.仕掛品(製造部)'!MY:NB,4,0),0) -> 2.7753038 | H44: 0 | J44: 0 | AI44: =IFERROR(SUMIFS('4.3期末全在庫'!$G:$G,'4.3期末全在庫'!$B:$B,'4.仕掛品(製品課)'!A44,'4.3期末全在庫'!$K:$K,"半製品"),"") -> 0 | AK44: =AF44*AI44 -> 0 | AO44: 4034.3004 | AQ44: =IF(SUM(H44:AK44)=0,0,"ok") -> 0
A45: 20110801283 | B45: 5A 2.5g×2 | C45: 半製品 | D45: 半製品 | E45: 5 | F45: 5A | G45: =IFERROR(VLOOKUP(F45,'[1]2.仕掛品(製造部)'!MY:NB,4,0),0) -> 5.1725294 | H45: 0 | J45: 0 | AI45: =IFERROR(SUMIFS('4.3期末全在庫'!$G:$G,'4.3期末全在庫'!$B:$B,'4.仕掛品(製品課)'!A45,'4.3期末全在庫'!$K:$K,"半製品"),"") -> 0 | AK45: =AF45*AI45 -> 0 | AO45: 3237.3253 | AQ45: =IF(SUM(H45:AK45)=0,0,"ok") -> 0
A46: 20110801300 | B46: X 1ml×2 | C46: 半製品 | D46: 半製品 | E46: 2.6 | F46: X | G46: =IFERROR(VLOOKUP(F46,'[1]2.仕掛品(製造部)'!MY:NB,4,0),0) -> 1.5731245 | H46: 0 | J46: 0 | AI46: =IFERROR(SUMIFS('4.3期末全在庫'!$G:$G,'4.3期末全在庫'!$B:$B,'4.仕掛品(製品課)'!A46,'4.3期末全在庫'!$K:$K,"半製品"),"") -> 0 | AK46: =AF46*AI46 -> 0 | AN46: 141.81276 | AO46: 3712.8163 | AQ46: =IF(SUM(H46:AK46)=0,0,"ok") -> 0
A47: 20110801492 | B47: 新･MKF-Ⅱ 30g TOMⅢ-30 №3 | C47: 半製品 | D47: 半製品 | G47: =IFERROR(VLOOKUP(F47,'[1]2.仕掛品(製造部)'!MY:NB,4,0),0) -> 0 | H47: 0 | J47: 0 | AI47: =IFERROR(SUMIFS('4.3期末全在庫'!$G:$G,'4.3期末全在庫'!$B:$B,'4.仕掛品(製品課)'!A47,'4.3期末全在庫'!$K:$K,"半製品"),"") -> 0 | AK47: =AF47*AI47 -> 0 | AN47: 175 | AO47: 3082.7114 | AQ47: =IF(SUM(H47:AK47)=0,0,"ok") -> 0
A48: 20110801505 | B48: 六角茶色瓶 145g E-100 | C48: 半製品 | D48: 半製品 | G48: =IFERROR(VLOOKUP(F48,'[1]2.仕掛品(製造部)'!MY:NB,4,0),0) -> 0 | H48: 0 | J48: 0 | AI48: =IFERROR(SUMIFS('4.3期末全在庫'!$G:$G,'4.3期末全在庫'!$B:$B,'4.仕掛品(製品課)'!A48,'4.3期末全在庫'!$K:$K,"半製品"),"") -> 0 | AK48: =AF48*AI48 -> 0 | AN48: 550.8769 | AO48: 1685.6497 | AQ48: =IF(SUM(H48:AK48)=0,0,"ok") -> 0
A49: 20110801533 | B49: 食品8角 310g 瓶 大商硝子 | C49: 半製品 | D49: 半製品 | G49: =IFERROR(VLOOKUP(F49,'[1]2.仕掛品(製造部)'!MY:NB,4,0),0) -> 0 | H49: 0 | J49: 0 | AI49: =IFERROR(SUMIFS('4.3期末全在庫'!$G:$G,'4.3期末全在庫'!$B:$B,'4.仕掛品(製品課)'!A49,'4.3期末全在庫'!$K:$K,"半製品"),"") -> 0 | AK49: =AF49*AI49 -> 0 | AO49: 0 | AQ49: =IF(SUM(H49:AK49)=0,0,"ok") -> 0
A50: 20110801536 | B50: 分包ﾌｨﾙﾑ (無地) 幅70mm ﾀｶﾗ | C50: 半製品 | D50: 半製品 | G50: =IFERROR(VLOOKUP(F50,'[1]2.仕掛品(製造部)'!MY:NB,4,0),0) -> 0 | H50: 0 | J50: 0 | AI50: =IFERROR(SUMIFS('4.3期末全在庫'!$G:$G,'4.3期末全在庫'!$B:$B,'4.仕掛品(製品課)'!A50,'4.3期末全在庫'!$K:$K,"半製品"),"") -> 0 | AK50: =AF50*AI50 -> 0 | AN50: 82.800699 | AO50: 390.40495 | AQ50: =IF(SUM(H50:AK50)=0,0,"ok") -> 0
A51: 20110801549 | B51: Jﾎﾞﾄﾙ 丸型細口(ﾅﾁｭﾗﾙ) 1ﾘｯﾄﾙ | C51: 半製品 | D51: 半製品 | G51: =IFERROR(VLOOKUP(F51,'[1]2.仕掛品(製造部)'!MY:NB,4,0),0) -> 0 | H51: 0 | J51: 0 | AI51: =IFERROR(SUMIFS('4.3期末全在庫'!$G:$G,'4.3期末全在庫'!$B:$B,'4.仕掛品(製品課)'!A51,'4.3期末全在庫'!$K:$K,"半製品"),"") -> 0 | AK51: =AF51*AI51 -> 0 | AO51: 8.7154732 | AQ51: =IF(SUM(H51:AK51)=0,0,"ok") -> 0
A52: 20110801604 | B52: 食品8角 310gｷｬｯﾌﾟ(大調和ﾏｰｸ入) | C52: 半製品 | D52: 半製品 | G52: =IFERROR(VLOOKUP(F52,'[1]2.仕掛品(製造部)'!MY:NB,4,0),0) -> 0 | H52: 0 | J52: 0 | AI52: =IFERROR(SUMIFS('4.3期末全在庫'!$G:$G,'4.3期末全在庫'!$B:$B,'4.仕掛品(製品課)'!A52,'4.3期末全在庫'!$K:$K,"半製品"),"") -> 0 | AK52: =AF52*AI52 -> 0 | AO52: 6.4400381 | AQ52: =IF(SUM(H52:AK52)=0,0,"ok") -> 0
A53: 20110801610 | B53: 新･MKF-Ⅱ 30g TOMⅢ-CAP №1 | C53: 半製品 | D53: 半製品 | G53: =IFERROR(VLOOKUP(F53,'[1]2.仕掛品(製造部)'!MY:NB,4,0),0) -> 0 | H53: 0 | J53: 0 | AI53: =IFERROR(SUMIFS('4.3期末全在庫'!$G:$G,'4.3期末全在庫'!$B:$B,'4.仕掛品(製品課)'!A53,'4.3期末全在庫'!$K:$K,"半製品"),"") -> 0 | AK53: =AF53*AI53 -> 0 | AO53: 0 | AQ53: =IF(SUM(H53:AK53)=0,0,"ok") -> 0
A54: 20110801621 | B54: 70g用ｷｬｯﾌﾟ（大調和ﾏｰｸ入） | C54: 半製品 | D54: 半製品 | G54: =IFERROR(VLOOKUP(F54,'[1]2.仕掛品(製造部)'!MY:NB,4,0),0) -> 0 | H54: 0 | J54: 0 | AI54: =IFERROR(SUMIFS('4.3期末全在庫'!$G:$G,'4.3期末全在庫'!$B:$B,'4.仕掛品(製品課)'!A54,'4.3期末全在庫'!$K:$K,"半製品"),"") -> 0 | AK54: =AF54*AI54 -> 0 | AO54: 7.4080624 | AQ54: =IF(SUM(H54:AK54)=0,0,"ok") -> 0
A55: 20110801622 | B55: 145ｇ用 ｷｬｯﾌﾟ（大調和ﾏｰｸ入り） | C55: 半製品 | D55: 半製品 | G55: =IFERROR(VLOOKUP(F55,'[1]2.仕掛品(製造部)'!MY:NB,4,0),0) -> 0 | H55: 0 | J55: 0 | AI55: =IFERROR(SUMIFS('4.3期末全在庫'!$G:$G,'4.3期末全在庫'!$B:$B,'4.仕掛品(製品課)'!A55,'4.3期末全在庫'!$K:$K,"半製品"),"") -> 0 | AK55: =AF55*AI55 -> 0 | AO55: 0 | AQ55: =IF(SUM(H55:AK55)=0,0,"ok") -> 0
A56: 20110801624 | B56: 70ｇ用ｷｬｯﾌﾟ（刻印なし） | C56: 半製品 | D56: 半製品 | G56: =IFERROR(VLOOKUP(F56,'[1]2.仕掛品(製造部)'!MY:NB,4,0),0) -> 0 | H56: 0 | J56: 0 | AI56: =IFERROR(SUMIFS('4.3期末全在庫'!$G:$G,'4.3期末全在庫'!$B:$B,'4.仕掛品(製品課)'!A56,'4.3期末全在庫'!$K:$K,"半製品"),"") -> 0 | AK56: =AF56*AI56 -> 0 | AO56: 6.1625532 | AQ56: =IF(SUM(H56:AK56)=0,0,"ok") -> 0
A57: 20110801689 | B57: 新･MKF-Ⅱ 30g TOCAP用 | C57: 半製品 | D57: 半製品 | G57: =IFERROR(VLOOKUP(F57,'[1]2.仕掛品(製造部)'!MY:NB,4,0),0) -> 0 | H57: 0 | J57: 0 | AI57: =IFERROR(SUMIFS('4.3期末全在庫'!$G:$G,'4.3期末全在庫'!$B:$B,'4.仕掛品(製品課)'!A57,'4.3期末全在庫'!$K:$K,"半製品"),"") -> 0 | AK57: =AF57*AI57 -> 0 | AO57: 0 | AQ57: =IF(SUM(H57:AK57)=0,0,"ok") -> 0
A58: 20110801698 | B58: 食品8角 310g SPPﾊｲｼｰﾄ 大商硝子 | C58: 半製品 | D58: 半製品 | G58: =IFERROR(VLOOKUP(F58,'[1]2.仕掛品(製造部)'!MY:NB,4,0),0) -> 0 | H58: 0 | J58: 0 | AI58: =IFERROR(SUMIFS('4.3期末全在庫'!$G:$G,'4.3期末全在庫'!$B:$B,'4.仕掛品(製品課)'!A58,'4.3期末全在庫'!$K:$K,"半製品"),"") -> 0 | AK58: =AF58*AI58 -> 0 | AO58: 0 | AQ58: =IF(SUM(H58:AK58)=0,0,"ok") -> 0
A59: 20110803102 | B59: 食品8角 310g 瓶ｼｭﾘﾝｸ 大商硝子 | C59: 半製品 | D59: 半製品 | G59: =IFERROR(VLOOKUP(F59,'[1]2.仕掛品(製造部)'!MY:NB,4,0),0) -> 0 | H59: 0 | J59: 0 | AI59: =IFERROR(SUMIFS('4.3期末全在庫'!$G:$G,'4.3期末全在庫'!$B:$B,'4.仕掛品(製品課)'!A59,'4.3期末全在庫'!$K:$K,"半製品"),"") -> 0 | AK59: =AF59*AI59 -> 0 | AO59: 3.7627945 | AQ59: =IF(SUM(H59:AK59)=0,0,"ok") -> 0
A60: 20110900030 | B60: PE 2.5g | C60: 半製品 | D60: 半製品 | E60: 2.5 | F60: PE | H60: 0 | J60: 0 | AI60: =IFERROR(SUMIFS('4.3期末全在庫'!$G:$G,'4.3期末全在庫'!$B:$B,'4.仕掛品(製品課)'!A60,'4.3期末全在庫'!$K:$K,"半製品"),"") -> 0 | AK60: =AF60*AI60 -> 0 | AO60: 132.80325 | AQ60: =IF(SUM(H60:AK60)=0,0,"ok") -> 0
A61: 20111000018 | B61: MKﾐｸｽﾁｬｰ(ﾍﾟｰｽﾄ)㎏ 半 | C61: 半製品 | D61: 半製品 | G61: =IFERROR(VLOOKUP(F61,'[1]2.仕掛品(製造部)'!MY:NB,4,0),0) -> 0 | H61: 0 | J61: 0 | AI61: =IFERROR(SUMIFS('4.3期末全在庫'!$G:$G,'4.3期末全在庫'!$B:$B,'4.仕掛品(製品課)'!A61,'4.3期末全在庫'!$K:$K,"半製品"),"") -> 0 | AK61: =AF61*AI61 -> 0 | AO61: 6.4280051 | AQ61: =IF(SUM(H61:AK61)=0,0,"ok") -> 0
A62: 20111000019 | B62: MKﾐｸｽﾁｬｰ(ﾘｷｯﾄﾞ)㎏ 半 | C62: 半製品 | D62: 半製品 | G62: =IFERROR(VLOOKUP(F62,'[1]2.仕掛品(製造部)'!MY:NB,4,0),0) -> 0 | H62: 0 | J62: 0 | AI62: =IFERROR(SUMIFS('4.3期末全在庫'!$G:$G,'4.3期末全在庫'!$B:$B,'4.仕掛品(製品課)'!A62,'4.3期末全在庫'!$K:$K,"半製品"),"") -> 0 | AK62: =AF62*AI62 -> 0 | AO62: 0 | AQ62: =IF(SUM(H62:AK62)=0,0,"ok") -> 0
A63: 20111000949 | B63: 表示用無地ﾗﾍﾞﾙ 63×50 | C63: 半製品 | D63: 半製品 | G63: =IFERROR(VLOOKUP(F63,'[1]2.仕掛品(製造部)'!MY:NB,4,0),0) -> 0 | H63: 0 | J63: 0 | AI63: =IFERROR(SUMIFS('4.3期末全在庫'!$G:$G,'4.3期末全在庫'!$B:$B,'4.仕掛品(製品課)'!A63,'4.3期末全在庫'!$K:$K,"半製品"),"") -> 0 | AK63: =AF63*AI63 -> 0 | AO63: 406.82861 | AQ63: =IF(SUM(H63:AK63)=0,0,"ok") -> 0
A64: 20111000967 | B64: 延寿酵素 OLIGO PLUS 145g 半 | C64: 半製品 | D64: 半製品 | E64: 145 | F64: PT | G64: =IFERROR(VLOOKUP(F64,'[1]2.仕掛品(製造部)'!MY:NB,4,0),0) -> 0 | H64: 0 | J64: 0 | AI64: =IFERROR(SUMIFS('4.3期末全在庫'!$G:$G,'4.3期末全在庫'!$B:$B,'4.仕掛品(製品課)'!A64,'4.3期末全在庫'!$K:$K,"半製品"),"") -> 0 | AK64: =AF64*AI64 -> 0 | AN64: 719.47185 | AO64: 2035.457 | AQ64: =IF(SUM(H64:AK64)=0,0,"ok") -> 0
A65: 20111100047 | B65: PT 2.5×2 | C65: 半製品 | D65: 半製品 | E65: 5 | F65: PT | G65: =IFERROR(VLOOKUP(F65,'[1]2.仕掛品(製造部)'!MY:NB,4,0),0) -> 0 | H65: 0 | J65: 0 | AI65: =IFERROR(SUMIFS('4.3期末全在庫'!$G:$G,'4.3期末全在庫'!$B:$B,'4.仕掛品(製品課)'!A65,'4.3期末全在庫'!$K:$K,"半製品"),"") -> 0 | AK65: =AF65*AI65 -> 0 | AN65: 912.30041 | AO65: 1981.9319 | AQ65: =IF(SUM(H65:AK65)=0,0,"ok") -> 0
A66: 20120300043 | B66: Man-Koso LIFE Y 5g×3 | C66: 半製品 | D66: 半製品 | E66: 15 | F66: Y | G66: =IFERROR(VLOOKUP(F66,'[1]2.仕掛品(製造部)'!MY:NB,4,0),0) -> 1.6405741 | H66: 0 | J66: 0 | AI66: =IFERROR(SUMIFS('4.3期末全在庫'!$G:$G,'4.3期末全在庫'!$B:$B,'4.仕掛品(製品課)'!A66,'4.3期末全在庫'!$K:$K,"半製品"),"") -> 0 | AK66: =AF66*AI66 -> 0 | AO66: 0 | AQ66: =IF(SUM(H66:AK66)=0,0,"ok") -> 0
A67: 20120900071 | B67: PE 2.5g | C67: 半製品 | D67: 半製品 | E67: 2.5 | F67: PE | G67: =IFERROR(VLOOKUP(F67,'[1]2.仕掛品(製造部)'!MY:NB,4,0),0) -> 1.1499334 | H67: 0 | J67: 0 | AI67: =IFERROR(SUMIFS('4.3期末全在庫'!$G:$G,'4.3期末全在庫'!$B:$B,'4.仕掛品(製品課)'!A67,'4.3期末全在庫'!$K:$K,"半製品"),"") -> 0 | AK67: =AF67*AI67 -> 0 | AO67: 0 | AQ67: =IF(SUM(H67:AK67)=0,0,"ok") -> 0
A68: 20121000006 | B68: ﾉﾆ酵素 2g×2 | C68: 半製品 | D68: 半製品 | E68: 4 | F68: PSA | G68: =IFERROR(VLOOKUP(F68,'[1]2.仕掛品(製造部)'!MY:NB,4,0),0) -> 1.7935093 | H68: 0 | J68: 0 | AI68: =IFERROR(SUMIFS('4.3期末全在庫'!$G:$G,'4.3期末全在庫'!$B:$B,'4.仕掛品(製品課)'!A68,'4.3期末全在庫'!$K:$K,"半製品"),"") -> 0 | AK68: =AF68*AI68 -> 0 | AO68: 0 | AQ68: =IF(SUM(H68:AK68)=0,0,"ok") -> 0
A69: 20121000043 | B69: Q 2.5g×2 | C69: 半製品 | D69: 半製品 | E69: 5 | F69: Q | G69: =IFERROR(VLOOKUP(F69,'[1]2.仕掛品(製造部)'!MY:NB,4,0),0) -> 1.5486311 | H69: 0 | J69: 0 | AI69: =IFERROR(SUMIFS('4.3期末全在庫'!$G:$G,'4.3期末全在庫'!$B:$B,'4.仕掛品(製品課)'!A69,'4.3期末全在庫'!$K:$K,"半製品"),"") -> 0 | AK69: =AF69*AI69 -> 0 | AO69: 0 | AQ69: =IF(SUM(H69:AK69)=0,0,"ok") -> 0
A70: 20130100020 | B70: 食品8角310g瓶(刻印なし)新ｷｬｯﾌﾟ | C70: 半製品 | D70: 半製品 | G70: =IFERROR(VLOOKUP(F70,'[1]2.仕掛品(製造部)'!MY:NB,4,0),0) -> 0 | H70: 0 | J70: 0 | AI70: =IFERROR(SUMIFS('4.3期末全在庫'!$G:$G,'4.3期末全在庫'!$B:$B,'4.仕掛品(製品課)'!A70,'4.3期末全在庫'!$K:$K,"半製品"),"") -> 0 | AK70: =AF70*AI70 -> 0 | AO70: 0 | AQ70: =IF(SUM(H70:AK70)=0,0,"ok") -> 0
A71: 20130100025 | B71: NONI酵素 300g ﾌｧﾐﾘｰｻｲｽﾞ 半 | C71: 半製品 | D71: 半製品 | G71: =IFERROR(VLOOKUP(F71,'[1]2.仕掛品(製造部)'!MY:NB,4,0),0) -> 0 | H71: 0 | J71: 0 | AI71: =IFERROR(SUMIFS('4.3期末全在庫'!$G:$G,'4.3期末全在庫'!$B:$B,'4.仕掛品(製品課)'!A71,'4.3期末全在庫'!$K:$K,"半製品"),"") -> 0 | AK71: =AF71*AI71 -> 0 | AO71: 0 | AQ71: =IF(SUM(H71:AK71)=0,0,"ok") -> 0
A72: 20130200022 | B72: CE 2g×3 540g用 | C72: 半製品 | D72: 半製品 | E72: 6 | F72: CE | G72: =IFERROR(VLOOKUP(F72,'[1]2.仕掛品(製造部)'!MY:NB,4,0),0) -> 0 | H72: 0 | J72: 0 | AI72: =IFERROR(SUMIFS('4.3期末全在庫'!$G:$G,'4.3期末全在庫'!$B:$B,'4.仕掛品(製品課)'!A72,'4.3期末全在庫'!$K:$K,"半製品"),"") -> 0 | AK72: =AF72*AI72 -> 0 | AO72: 0 | AQ72: =IF(SUM(H72:AK72)=0,0,"ok") -> 0
A73: 20130400028 | B73: 3年3ヶ月以上発酵熟成酵素 70g 半 | C73: 半製品 | D73: 半製品 | E73: 70 | F73: P | G73: =IFERROR(VLOOKUP(F73,'[1]2.仕掛品(製造部)'!MY:NB,4,0),0) -> 1.2657092 | H73: 0 | J73: 0 | AI73: =IFERROR(SUMIFS('4.3期末全在庫'!$G:$G,'4.3期末全在庫'!$B:$B,'4.仕掛品(製品課)'!A73,'4.3期末全在庫'!$K:$K,"半製品"),"") -> 0 | AK73: =AF73*AI73 -> 0 | AO73: 0 | AQ73: =IF(SUM(H73:AK73)=0,0,"ok") -> 0
A74: 20130400029 | B74: 3年3ヶ月発酵熟成酵素 2.5g×2 | C74: 半製品 | D74: 半製品 | E74: 5 | F74: P | G74: =IFERROR(VLOOKUP(F74,'[1]2.仕掛品(製造部)'!MY:NB,4,0),0) -> 1.2657092 | H74: 0 | J74: 0 | AI74: =IFERROR(SUMIFS('4.3期末全在庫'!$G:$G,'4.3期末全在庫'!$B:$B,'4.仕掛品(製品課)'!A74,'4.3期末全在庫'!$K:$K,"半製品"),"") -> 0 | AK74: =AF74*AI74 -> 0 | AO74: 0 | AQ74: =IF(SUM(H74:AK74)=0,0,"ok") -> 0
A75: 20130900009 | B75: JA 2.5g×2 無地 | C75: 半製品 | D75: 半製品 | E75: 5 | F75: JA | G75: =IFERROR(VLOOKUP(F75,'[1]2.仕掛品(製造部)'!MY:NB,4,0),0) -> 0 | H75: 0 | J75: 0 | AI75: =IFERROR(SUMIFS('4.3期末全在庫'!$G:$G,'4.3期末全在庫'!$B:$B,'4.仕掛品(製品課)'!A75,'4.3期末全在庫'!$K:$K,"半製品"),"") -> 0 | AK75: =AF75*AI75 -> 0 | AO75: 0 | AQ75: =IF(SUM(H75:AK75)=0,0,"ok") -> 0
A76: 20131000001 | B76: 3SPPΦ68.3×1.5ﾊｲｼ-ﾄ | C76: 半製品 | D76: 半製品 | G76: =IFERROR(VLOOKUP(F76,'[1]2.仕掛品(製造部)'!MY:NB,4,0),0) -> 0 | H76: 0 | J76: 0 | AI76: =IFERROR(SUMIFS('4.3期末全在庫'!$G:$G,'4.3期末全在庫'!$B:$B,'4.仕掛品(製品課)'!A76,'4.3期末全在庫'!$K:$K,"半製品"),"") -> 0 | AK76: =AF76*AI76 -> 0 | AO76: 0 | AQ76: =IF(SUM(H76:AK76)=0,0,"ok") -> 0
A77: 20131100008 | B77: NONI分包ｱﾙﾐﾌｨﾙﾑ(新ロゴ） | C77: 半製品 | D77: 半製品 | G77: =IFERROR(VLOOKUP(F77,'[1]2.仕掛品(製造部)'!MY:NB,4,0),0) -> 0 | H77: 0 | J77: 0 | AI77: =IFERROR(SUMIFS('4.3期末全在庫'!$G:$G,'4.3期末全在庫'!$B:$B,'4.仕掛品(製品課)'!A77,'4.3期末全在庫'!$K:$K,"半製品"),"") -> 0 | AK77: =AF77*AI77 -> 0 | AO77: 0 | AQ77: =IF(SUM(H77:AK77)=0,0,"ok") -> 0
A78: 20131100013 | B78: NONI300g 表ﾗﾍﾞﾙ(新ロゴ) | C78: 半製品 | D78: 半製品 | G78: =IFERROR(VLOOKUP(F78,'[1]2.仕掛品(製造部)'!MY:NB,4,0),0) -> 0 | H78: 0 | J78: 0 | AI78: =IFERROR(SUMIFS('4.3期末全在庫'!$G:$G,'4.3期末全在庫'!$B:$B,'4.仕掛品(製品課)'!A78,'4.3期末全在庫'!$K:$K,"半製品"),"") -> 0 | AK78: =AF78*AI78 -> 0 | AO78: 0 | AQ78: =IF(SUM(H78:AK78)=0,0,"ok") -> 0
A79: 20131200048 | B79: ｴｺｺﾞｰﾙﾄﾞEX180ｇ 検 | C79: 半製品 | D79: 半製品 | G79: =IFERROR(VLOOKUP(F79,'[1]2.仕掛品(製造部)'!MY:NB,4,0),0) -> 0 | H79: 0 | J79: 0 | AI79: =IFERROR(SUMIFS('4.3期末全在庫'!$G:$G,'4.3期末全在庫'!$B:$B,'4.仕掛品(製品課)'!A79,'4.3期末全在庫'!$K:$K,"半製品"),"") -> 0 | AK79: =AF79*AI79 -> 0 | AO79: 0 | AQ79: =IF(SUM(H79:AK79)=0,0,"ok") -> 0
A80: 20140100009 | B80: 万田酵素145g(販売店向け)表ﾗﾍﾞﾙ | C80: 半製品 | D80: 半製品 | G80: =IFERROR(VLOOKUP(F80,'[1]2.仕掛品(製造部)'!MY:NB,4,0),0) -> 0 | H80: 0 | J80: 0 | AI80: =IFERROR(SUMIFS('4.3期末全在庫'!$G:$G,'4.3期末全在庫'!$B:$B,'4.仕掛品(製品課)'!A80,'4.3期末全在庫'!$K:$K,"半製品"),"") -> 0 | AK80: =AF80*AI80 -> 0 | AO80: 0 | AQ80: =IF(SUM(H80:AK80)=0,0,"ok") -> 0
A81: 20140100078 | B81: 万田酵素300g 表ラベル 税 | C81: 半製品 | D81: 半製品 | G81: =IFERROR(VLOOKUP(F81,'[1]2.仕掛品(製造部)'!MY:NB,4,0),0) -> 0 | H81: 0 | J81: 0 | AI81: =IFERROR(SUMIFS('4.3期末全在庫'!$G:$G,'4.3期末全在庫'!$B:$B,'4.仕掛品(製品課)'!A81,'4.3期末全在庫'!$K:$K,"半製品"),"") -> 0 | AK81: =AF81*AI81 -> 0 | AO81: 0 | AQ81: =IF(SUM(H81:AK81)=0,0,"ok") -> 0
A82: 20140800032 | B82: PV 2.5g×2 | C82: 半製品 | D82: 半製品 | E82: 5 | F82: PV | G82: =IFERROR(VLOOKUP(F82,'[1]2.仕掛品(製造部)'!MY:NB,4,0),0) -> 1.9177072 | H82: 0 | J82: 0 | AI82: =IFERROR(SUMIFS('4.3期末全在庫'!$G:$G,'4.3期末全在庫'!$B:$B,'4.仕掛品(製品課)'!A82,'4.3期末全在庫'!$K:$K,"半製品"),"") -> 0 | AK82: =AF82*AI82 -> 0 | AO82: 0 | AQ82: =IF(SUM(H82:AK82)=0,0,"ok") -> 0
A83: 20140900009 | B83: Vitalize 2.5g×2 | C83: 半製品 | D83: 半製品 | E83: 2.5 | F83: B | G83: =IFERROR(VLOOKUP(F83,'[1]2.仕掛品(製造部)'!MY:NB,4,0),0) -> 1.3486947 | H83: 0 | J83: 0 | AI83: =IFERROR(SUMIFS('4.3期末全在庫'!$G:$G,'4.3期末全在庫'!$B:$B,'4.仕掛品(製品課)'!A83,'4.3期末全在庫'!$K:$K,"半製品"),"") -> 0 | AK83: =AF83*AI83 -> 0 | AO83: 0 | AQ83: =IF(SUM(H83:AK83)=0,0,"ok") -> 0
A84: 20141100018 | B84: PPﾊｲｼｰﾄ 145g用 高久産業 | C84: 半製品 | D84: 半製品 | G84: =IFERROR(VLOOKUP(F84,'[1]2.仕掛品(製造部)'!MY:NB,4,0),0) -> 0 | H84: 0 | J84: 0 | AI84: =IFERROR(SUMIFS('4.3期末全在庫'!$G:$G,'4.3期末全在庫'!$B:$B,'4.仕掛品(製品課)'!A84,'4.3期末全在庫'!$K:$K,"半製品"),"") -> 0 | AK84: =AF84*AI84 -> 0 | AO84: 0 | AQ84: =IF(SUM(H84:AK84)=0,0,"ok") -> 0
A85: 20151200008 | B85: P 2.5g | C85: 半製品 | D85: 半製品 | E85: 2.5 | F85: P | G85: =IFERROR(VLOOKUP(F85,'[1]2.仕掛品(製造部)'!MY:NB,4,0),0) -> 1.2657092 | H85: 0 | J85: 0 | AI85: =IFERROR(SUMIFS('4.3期末全在庫'!$G:$G,'4.3期末全在庫'!$B:$B,'4.仕掛品(製品課)'!A85,'4.3期末全在庫'!$K:$K,"半製品"),"") -> 0 | AK85: =AF85*AI85 -> 0 | AO85: 0 | AQ85: =IF(SUM(H85:AK85)=0,0,"ok") -> 0
A86: 20160800001 | B86: EC-500用 ｷｬｯﾌﾟ(ｿﾌﾄﾛﾝ79.5×1.5) | C86: 半製品 | D86: 半製品 | G86: =IFERROR(VLOOKUP(F86,'[1]2.仕掛品(製造部)'!MY:NB,4,0),0) -> 0 | H86: 0 | J86: 0 | AI86: =IFERROR(SUMIFS('4.3期末全在庫'!$G:$G,'4.3期末全在庫'!$B:$B,'4.仕掛品(製品課)'!A86,'4.3期末全在庫'!$K:$K,"半製品"),"") -> 0 | AK86: =AF86*AI86 -> 0 | AO86: 0 | AQ86: =IF(SUM(H86:AK86)=0,0,"ok") -> 0
A87: 20170300033 | B87: 145gﾋﾞﾝ用ﾛｰﾙｼｭﾘﾝｸﾌｨﾙﾑ | C87: 半製品 | D87: 半製品 | G87: =IFERROR(VLOOKUP(F87,'[1]2.仕掛品(製造部)'!MY:NB,4,0),0) -> 0 | H87: 0 | J87: 0 | AI87: =IFERROR(SUMIFS('4.3期末全在庫'!$G:$G,'4.3期末全在庫'!$B:$B,'4.仕掛品(製品課)'!A87,'4.3期末全在庫'!$K:$K,"半製品"),"") -> 0 | AK87: =AF87*AI87 -> 0 | AO87: 0 | AQ87: =IF(SUM(H87:AK87)=0,0,"ok") -> 0
A88: 20170400032 | B88: 万田酵素 STANDARD 分包ﾌｨﾙﾑ | C88: 半製品 | D88: 半製品 | G88: =IFERROR(VLOOKUP(F88,'[1]2.仕掛品(製造部)'!MY:NB,4,0),0) -> 0 | H88: 0 | J88: 0 | AI88: =IFERROR(SUMIFS('4.3期末全在庫'!$G:$G,'4.3期末全在庫'!$B:$B,'4.仕掛品(製品課)'!A88,'4.3期末全在庫'!$K:$K,"半製品"),"") -> 0 | AK88: =AF88*AI88 -> 0 | AO88: 0 | AQ88: =IF(SUM(H88:AK88)=0,0,"ok") -> 0
A89: 20170400033 | B89: 万田酵素 GINGER 分包ﾌｨﾙﾑ | C89: 半製品 | D89: 半製品 | G89: =IFERROR(VLOOKUP(F89,'[1]2.仕掛品(製造部)'!MY:NB,4,0),0) -> 0 | H89: 0 | J89: 0 | AI89: =IFERROR(SUMIFS('4.3期末全在庫'!$G:$G,'4.3期末全在庫'!$B:$B,'4.仕掛品(製品課)'!A89,'4.3期末全在庫'!$K:$K,"半製品"),"") -> 0 | AK89: =AF89*AI89 -> 0 | AO89: 0 | AQ89: =IF(SUM(H89:AK89)=0,0,"ok") -> 0
A90: 20170500057 | B90: GINGER 2.5g | C90: 半製品 | D90: 半製品 | E90: 2.5 | F90: PE | G90: =IFERROR(VLOOKUP(F90,'[1]2.仕掛品(製造部)'!MY:NB,4,0),0) -> 1.1499334 | H90: 31600 | J90: 67389.992 | AI90: =IFERROR(SUMIFS('4.3期末全在庫'!$G:$G,'4.3期末全在庫'!$B:$B,'4.仕掛品(製品課)'!A90,'4.3期末全在庫'!$K:$K,"半製品"),"") -> 18000 | AK90: =AI90*AF334/E109*E334 -> 125180.49 | AO90: 0 | AQ90: =IF(SUM(H90:AK90)=0,0,"ok") -> ok
A91: 20170500058 | B91: STANDARD 2.5g | C91: 半製品 | D91: 半製品 | E91: 2.5 | F91: PX | G91: =IFERROR(VLOOKUP(F91,'[1]2.仕掛品(製造部)'!MY:NB,4,0),0) -> 1.2530514 | H91: 8400 | J91: 20308.946 | AI91: =IFERROR(SUMIFS('4.3期末全在庫'!$G:$G,'4.3期末全在庫'!$B:$B,'4.仕掛品(製品課)'!A91,'4.3期末全在庫'!$K:$K,"半製品"),"") -> 26000 | AK91: =AF273*AI91/E91*E273 -> 463797.99 | AO91: 0 | AQ91: =IF(SUM(H91:AK91)=0,0,"ok") -> ok
A92: 20170700070 | B92: XC 1ml×2 | C92: 半製品 | D92: 半製品 | E92: 2.6 | F92: XC | G92: =IFERROR(VLOOKUP(F92,'[1]2.仕掛品(製造部)'!MY:NB,4,0),0) -> 2.7031088 | H92: 0 | J92: 0 | AI92: =IFERROR(SUMIFS('4.3期末全在庫'!$G:$G,'4.3期末全在庫'!$B:$B,'4.仕掛品(製品課)'!A92,'4.3期末全在庫'!$K:$K,"半製品"),"") -> 0 | AK92: =AF92*AI92 -> 0 | AO92: 0 | AQ92: =IF(SUM(H92:AK92)=0,0,"ok") -> 0
A93: 20171100054 | B93: 145g ｷｬｯﾌﾟ(刻印なし) H | C93: 半製品 | D93: 半製品 | G93: =IFERROR(VLOOKUP(F93,'[1]2.仕掛品(製造部)'!MY:NB,4,0),0) -> 0 | H93: 0 | J93: 0 | AI93: =IFERROR(SUMIFS('4.3期末全在庫'!$G:$G,'4.3期末全在庫'!$B:$B,'4.仕掛品(製品課)'!A93,'4.3期末全在庫'!$K:$K,"半製品"),"") -> 0 | AK93: =AF93*AI93 -> 0 | AO93: 0 | AQ93: =IF(SUM(H93:AK93)=0,0,"ok") -> 0
A94: 20180300010 | B94: STANDARD 26g ﾁｭｰﾌﾞ一式 | C94: 半製品 | D94: 半製品 | G94: =IFERROR(VLOOKUP(F94,'[1]2.仕掛品(製造部)'!MY:NB,4,0),0) -> 0 | H94: 0 | J94: 0 | AI94: =IFERROR(SUMIFS('4.3期末全在庫'!$G:$G,'4.3期末全在庫'!$B:$B,'4.仕掛品(製品課)'!A94,'4.3期末全在庫'!$K:$K,"半製品"),"") -> 0 | AK94: =AF94*AI94 -> 0 | AO94: 0 | AQ94: =IF(SUM(H94:AK94)=0,0,"ok") -> 0
A95: 20180400012 | B95: NONI300g 裏ベル(新ﾛｺﾞ)② | C95: 半製品 | D95: 半製品 | G95: =IFERROR(VLOOKUP(F95,'[1]2.仕掛品(製造部)'!MY:NB,4,0),0) -> 0 | H95: 0 | J95: 0 | AI95: =IFERROR(SUMIFS('4.3期末全在庫'!$G:$G,'4.3期末全在庫'!$B:$B,'4.仕掛品(製品課)'!A95,'4.3期末全在庫'!$K:$K,"半製品"),"") -> 0 | AK95: =AF95*AI95 -> 0 | AN95: 341.64818 | AO95: 1056.8317 | AQ95: =IF(SUM(H95:AK95)=0,0,"ok") -> 0
A96: 20180400027 | B96: GINGER ﾁｭｰﾌﾞﾀｲﾌﾟ 26g | C96: 半製品 | D96: 半製品 | E96: 26 | F96: PE | G96: =IFERROR(VLOOKUP(F96,'[1]2.仕掛品(製造部)'!MY:NB,4,0),0) -> 1.1499334 | H96: 0 | J96: 0 | AI96: =IFERROR(SUMIFS('4.3期末全在庫'!$G:$G,'4.3期末全在庫'!$B:$B,'4.仕掛品(製品課)'!A96,'4.3期末全在庫'!$K:$K,"半製品"),"") -> 0 | AK96: =AF96*AI96 -> 0 | AN96: 95.723269 | AO96: 329.00288 | AQ96: =IF(SUM(H96:AK96)=0,0,"ok") -> 0
A97: 20180400028 | B97: STANDARD ﾁｭｰﾌﾞﾀｲﾌﾟ 26g | C97: 半製品 | D97: 半製品 | E97: 26 | F97: PX | G97: =IFERROR(VLOOKUP(F97,'[1]2.仕掛品(製造部)'!MY:NB,4,0),0) -> 1.2530514 | H97: 0 | J97: 0 | AI97: =IFERROR(SUMIFS('4.3期末全在庫'!$G:$G,'4.3期末全在庫'!$B:$B,'4.仕掛品(製品課)'!A97,'4.3期末全在庫'!$K:$K,"半製品"),"") -> 0 | AK97: =AF97*AI97 -> 0 | AN97: 550.64155 | AO97: 2161.6618 | AQ97: =IF(SUM(H97:AK97)=0,0,"ok") -> 0
A98: 20180400029 | B98: MULBERRY ﾁｭｰﾌﾞﾀｲﾌﾟ 26g | C98: 半製品 | D98: 半製品 | E98: 26 | F98: MP | G98: =IFERROR(VLOOKUP(F98,'[1]2.仕掛品(製造部)'!MY:NB,4,0),0) -> 1.1798248 | H98: 0 | J98: 0 | AI98: =IFERROR(SUMIFS('4.3期末全在庫'!$G:$G,'4.3期末全在庫'!$B:$B,'4.仕掛品(製品課)'!A98,'4.3期末全在庫'!$K:$K,"半製品"),"") -> 0 | AK98: =AF98*AI98 -> 0 | AN98: 721.07321 | AO98: 3984.9366 | AQ98: =IF(SUM(H98:AK98)=0,0,"ok") -> 0
A99: 20180700008 | B99: MULBERRY 2.5g | C99: 半製品 | D99: 半製品 | E99: 2.5 | F99: MP | G99: =IFERROR(VLOOKUP(F99,'[1]2.仕掛品(製造部)'!MY:NB,4,0),0) -> 1.1798248 | H99: 40000 | J99: 87224.699 | AI99: =IFERROR(SUMIFS('4.3期末全在庫'!$G:$G,'4.3期末全在庫'!$B:$B,'4.仕掛品(製品課)'!A99,'4.3期末全在庫'!$K:$K,"半製品"),"") -> 24200 | AK99: =AF333*AI99/E99*E333 -> 172038.19 | AN99: 1775.9687 | AO99: 7296.6701 | AQ99: =IF(SUM(H99:AK99)=0,0,"ok") -> ok
A100: 20191200054 | B100: 新・MKF-Ⅱ 30g ﾗﾍﾞﾙ（改）② | C100: 半製品 | D100: 半製品 | G100: =IFERROR(VLOOKUP(F100,'[1]2.仕掛品(製造部)'!MY:NB,4,0),0) -> 0 | H100: 0 | J100: 0 | AI100: =IFERROR(SUMIFS('4.3期末全在庫'!$G:$G,'4.3期末全在庫'!$B:$B,'4.仕掛品(製品課)'!A100,'4.3期末全在庫'!$K:$K,"半製品"),"") -> 0 | AK100: =AF100*AI100 -> 0 | AN100: 138.98756 | AO100: 293.86191 | AQ100: =IF(SUM(H100:AK100)=0,0,"ok") -> 0
A101: 20191200056 | B101: MKF-Ⅱ 5A ﾘｷｯﾄﾞ 30g ﾗﾍﾞﾙ(改)② | C101: 半製品 | D101: 半製品 | G101: =IFERROR(VLOOKUP(F101,'[1]2.仕掛品(製造部)'!MY:NB,4,0),0) -> 0 | H101: 0 | J101: 0 | AI101: =IFERROR(SUMIFS('4.3期末全在庫'!$G:$G,'4.3期末全在庫'!$B:$B,'4.仕掛品(製品課)'!A101,'4.3期末全在庫'!$K:$K,"半製品"),"") -> 0 | AK101: =AF101*AI101 -> 0 | AN101: 970.35569 | AO101: 4245.3617 | AQ101: =IF(SUM(H101:AK101)=0,0,"ok") -> 0
...

Sheet 4.1製品別資材価格
A3: 商品コード | B3: 商品名１ | C3: 合計 / 金額 | D3: 37期
A4: 20040100009 | B4: 原料 万田酵素(植物用） | C4: 0 | D4: 0
A5: 20050300004 | B5: 低分子化万田酵素 1kg | C5: 143.43322 | D5: 143.42252
A6: 20050700013 | B6: 万田酵素 ｊ 分包150g | C6: 418.80133 | D6: 417.06227
A7: 20051000011 | B7: MANDA L5000 450g(海外向け) | C7: 945.04107 | D7: 1291.2509
A8: 20051200005 | B8: 万田HI酵素 分包150g | C8: 422.38363 | D8: 186.79004
A9: 20051200013 | B9: MKF-Ⅰ 分包150g(AAAAA) | C9: 110.73288 | D9: 89.7066
A10: 20060100007 | B10: 新･MKF-Ⅱ 30g | C10: 199.73596 | D10: 471.64261
A11: 20060200007 | B11: 万田酵素 金印145g | C11: 899.57608 | D11: 899.64964
A12: 20060800006 | B12: 試供品 万田31号 1ml×6 | C12: 17.53588 | D12: 20.534598
A13: 20061200012 | B13: 万田酵素 145g(販売店向け) | C13: 225.63506 | D13: 226.80204
A14: 20070300033 | B14: 万田酵素 分包150g(販売店向け) | C14: 106.38363 | D14: 91.301511
A15: 20071000005 | B15: 試供品 HI酵素 5g | C15: 7.8361921 | D15: 9.7972177
... A36: 20091200013 | B36: MANDA CARE PLUS 5g(ﾊﾟﾊﾟｲﾔ･ｺｺｱ) | C36: 27.501403 | D36: 27.467642
A37: 20091200015 | B37: ﾅﾁｭﾗﾙ酵素ﾌﾞﾙｰﾍﾞﾘｰﾌﾟﾗｽ 分包150g | C37: 3936.6387 | D37: #N/A
A38: 20091200016 | B38: 試供品 ﾅﾁｭﾗﾙ酵素ﾌﾞﾙｰﾍﾞﾘｰﾌﾟﾗｽ 5g | C38: 1934.1849 | D38: #N/A
A39: 20110300007 | B39: Man-Koso PREMIUM 145g | C39: 638.1255 | D39: 325.75295
A40: 20110300008 | B40: Man-Koso CARAT 145g | C40: 1776.1255 | D40: 503.33628
A41: 20110400012 | B41: MKﾐｸｽﾁｬｰ(ﾘｷｯﾄﾞ)(kg) | C41: 143.43322 | D41: 143.42252
A42: 20110800272 | B42: ｽｰﾊﾟｰ万田酵素 氣Ⅰ | C42: 1990.9943 | D42: 1849.9916
A43: 20110800295 | B43: 万田酵素 MJ | C43: 488.13626 | D43: 450.93447
A44: 20110800311 | B44: MANDA HI KOHSO | C44: 1102.6433 | D44: 679.82203
A45: 20110800312 | B45: MANDA KOHSO GOLD | C45: 2009.6203 | D45: #N/A
A46: 20110800629 | B46: 万田HI酵素 145g | C46: 370.27608 | D46: 315.86232
A47: 20110800918 | B47: Man-Koso PREMIUM 分包150g | C47: 1325.6438 | D47: 421.38538
A48: 20120300038 | B48: Man-Koso LIFE 450g | C48: 1147.2118 | D48: 597.87874
A49: 20120500014 | B49: 植物性発酵物（A飼料）1ﾘｯﾄﾙ | C49: 198.49587 | D49: 195.85654
A50: 20120800030 | B50: マンダアニモ 650g | C50: 153.69444 | D50: 127.59437
A51: 20120900082 | B51: NONI酵素 分包60g | C51: 67.898378 | D51: 66.55584
A52: 20130100001 | B52: NONI酵素 300g ファミリーサイズ | C52: 550.96919 | D52: 471.94356
A53: 20140100011 | B53: Man-Koso GOLD 145g | C53: 2510.1255 | D53: 906.72531
A54: 20160900041 | B54: 万田31号 500ml(韓国向) | C54: 658.72293 | D54: 641.31804
A55: 20160900042 | B55: 万田31号 1ﾘｯﾄﾙ(韓国向) | C55: 516.09644 | D55: 470.26725
A56: 20170400004 | B56: 試供品 万田酵素 GINGER 2.5g | C56: 2.706436 | D56: #N/A
A57: 20170400005 | B57: 万田酵素 GINGER 分包20g | C57: 26.569678 | D57: 26.500765
A58: 20170400006 | B58: 万田酵素 GINGER 分包77.5g | C58: 30.431406 | D58: 29.901531
A59: 20170400007 | B59: 試供品 万田酵素 STANDARD 2.5g | C59: 2.9489439 | D59: 2.9409498
A60: 20170400008 | B60: 万田酵素 STANDARD 分包20g | C60: 26.819383 | D60: 26.746765
A61: 20170400009 | B61: 万田酵素 STANDARD 分包77.5g | C61: 36.475339 | D61: 34.997281
A62: 20170400016 | B62: 万田酵素 STANDARD 分包35g | C62: 287.17036 | D62: 287.06603
A63: 20170400017 | B63: 万田酵素 GINGER 分包35g | C63: 56.048379 | D63: 55.950529
A64: 20171000004 | B64: 万田酵素 MULBERRY 分包77.5g | C64: 36.096046 | D64: 29.833191
A65: 20171000006 | B65: 万田酵素 MULBERRY 分包20g | C65: 26.4992 | D65: 26.523631
A66: 20171000008 | B66: 万田酵素STANDARDﾁｭｰﾌﾞﾀｲﾌﾟ26×3本 | C66: 373.77788 | D66: 373.6766
A67: 20171000009 | B67: 万田酵素GINGER ﾁｭｰﾌﾞﾀｲﾌﾟ26×3本 | C67: 373.77738 | D67: 373.6766
A68: 20171000010 | B68: 万田酵素MULBERRYﾁｭｰﾌﾞﾀｲﾌﾟ26g×3 | C68: 373.77788 | D68: 373.6766
... A77: 20200200034 | B77: 万田酵素 MULBERRY 分包 10g | C77: 161.36218 | D77: 85.710843
A78: 20200300074 | B78: 万田31号 50ml（韓国向） | C78: 314.99457 | D78: #N/A
A79: 20200800016 | B79: 万田酵素ｴｸｾﾚﾝﾄ 145g | C79: 1258.9659 | D79: 878.85178
A80: 20200800017 | B80: 万田酵素ｴｸｾﾚﾝﾄ 分包30g | C80: 119.06788 | D80: 163.19504
A81: 20200800018 | B81: 万田酵素ｴｸｾﾚﾝﾄ 分包450g | C81: 1603.6479 | D81: 1063.5334
A82: 20201100053 | B82: 万田酵素 MANUKA HONEY 分包77.5g | C82: 102.41805 | D82: 101.63103
A83: 20201100054 | B83: 試供品 万田酵素 MANUKA HONEY2.5g | C83: 5.0679425 | D83: 8.1397498
A84: 20210300049 | B84: MKﾐｸｽﾁｬｰ(ﾌﾞﾛｯｸﾀｲﾌﾟ)(kg) | C84: 9.2098806 | D84: 9.2098806
A85: 20210700007 | B85: MKﾐｸｽﾁｬｰ(ﾍﾟｰｽﾄ) 1kg | C85: 156.43322 | D85: 156.42252
A86: 20211100014 | B86: 特選EXﾌﾟﾗｽ 分包70g(2.5g×28包) | C86: 219.41091 | D86: 134.45893
A87: 20211100015 | B87: 特選EXﾌﾟﾗｽ 分包150g(2.5g×60包) | C87: 371.06034 | D87: 244.27401
A88: 20211100027 | B88: 万田酵素MULBERRY 粒44.1g(生産用) | C88: 53.837495 | D88: 53.766132
A89: 20220100027 | B89: MULBERRY 2.5g 支給用 | C89: 0.45126549 | D89: 0.45597371
A90: 20220100028 | B90: GINGER 2.5g 支給用 | C90: 0.46513795 | D90: 0.45817823
... A106: 20230700024 | B106: 万田酵素(宇宙用) | C106: 194.78211 | D106: 207.44664
A107: 20230900058 | B107: 万田酵素 MULBERRY 分包12.5g | C107: 16.590992 | D107: #N/A
A108: 20231100072 | B108: ｽｰﾊﾟｰ万田酵素 分包35g | C108: 77.041259 | D108: 76.955153
A109: 20231100073 | B109: ｽｰﾊﾟｰ万田酵素 分包150g | C109: 201.10053 | D109: 199.36147
A110: 20231100074 | B110: ｽｰﾊﾟｰ万田酵素 分包450g | C110: 1109.6177 | D110: 1104.4006
A111: 20231100078 | B111: 発酵しょうが 2.5g 支給用 | C111: 0.43374357 | D111: 0.43680653
A112: 20231200033 | B112: 万田酵素 分包75g (中国虹越) | C112: 138.88233 | D112: 138.4439
A113: 20240100051 | B113: 万田酵素 MANUKA HONEY Premium | C113: 54.529045 | D113: 53.736031
A114: 20240200038 | B114: MANDA WELLNESS SUPERDRINK 30x3g | C114: 1469.7999 | D114: #N/A
A115: 20240400018 | B115: 万田酵素(宇宙用) 2.5g×4包 | C115: 360.69597 | D115: #N/A
A116: 20240400019 | B116: 万田酵素(宇宙用) 2.5g×8包 | C116: 68.543971 | D116: #N/A
A117: 20240400020 | B117: 万田酵素(宇宙用) 2.5g×8包 | C117: 167.48118 | D117: #N/A
A118: 20240500062 | B118: 試供品 MANDA L5000 5g | C118: 1350.4349 | D118: #N/A
A119: 20240600040 | B119: NONI酵素 分包14g | C119: 113.46495 | D119: #N/A
A120: 20241000066 | B120: 馬用万田酵素 1kg | C120: 134.82942 | D120: #N/A
A121: 20241100041 | B121: 試供品 万田酵素分包5g(中国虹越) | C121: 1458.6349 | D121: #N/A
A122: 20241200012 | B122: 万田酵素ﾌﾟﾗｽ温発酵しょうが 75g | C122: 670.33405 | D122: #N/A
A123: 20241200064 | B123: 万田ｸﾞﾘｰﾝｷｰﾊﾟｰ 200ml | C123: 216.62941 | D123: #N/A
A124: 20250300060 | B124: 万田ｱﾐﾉｱﾙﾌｧﾌﾟﾗｽ(1L)(生産用) | C124: 2.7944907 | D124: #N/A
A125: 20250300087 | B125: 万田酵素 分包150g (中国) | C125: 97.628938 | D125: #N/A
A126: 20250400005 | B126: 馬用万田酵素 10kg | C126: 1536.8942 | D126: #N/A

Sheet 4.2半製品
C2: SC商品ｺｰﾄﾞ | D2: 商品名 | E2: 合計 / 作業実績の合計 | F2: 合計 / 作業時間の合計
C3: 20110801273 | D3: P 2.5g×2 | E3: 473700 | F3: 10500
C4: 20170500057 | D4: GINGER 2.5g | E4: 13473100 | F4: 52965
C5: 20170500058 | D5: STANDARD 2.5g | E5: 4514900 | F5: 18700
C6: 20180700008 | D6: MULBERRY 2.5g | E6: 5978800 | F6: 23285
C7: 20180801158 | D7: PG 2.5g×2 | E7: 22050 | F7: 550
C8: 20191200066 | D8: MANDA WELLNESS SUPERFOOD 2.5g | E8: 9300 | F8: 80
C9: 20200200008 | D9: D 2.5g | E9: 63500 | F9: 810
C10: 20201100060 | D10: PXM 2.5g | E10: 276900 | F10: 1585
C11: 20230600090 | D11: 発酵しょうが 2.5g | E11: 6526400 | F11: 25365
C12: 20110801159 | D12: ZA 2.5g×2 | E12: 24750 | F12: 780
C13: 20110801215 | D13: 5A 5g×2 | E13: 12210 | F13: 590
C14: 20110801266 | D14: B 2.5g×2 | E14: 48300 | F14: 1345
... C37: 20250400001 | D37: KOL 2.5g×2(中国古井向け) | E37: 210000 | F37: 4560
C38: 総計 | E38: 33098213 | F38: 169980

Sheet 4.3期末全在庫
A1: 商品コード | B1: CD統合(AB品含む) | C1: 倉庫名 | D1: 商品名１ | E1: 商品名２ | F1: 単位名 | G1: 当月在庫数 | H1: 商品区分名 | I1: 科目分類 | J1: 科目分類名 | K1: 区分 | L1: 単価 | M1: 金額 | N1: 備考 | O1: 在庫計上
A2: 20220500015 | B2: =VLOOKUP(A:A,[2]振替CD変換!B:C,2,FALSE) -> 20220500015 | C2: 発送倉庫 | D2: 万田酵素ﾄﾞﾘﾝｸﾀｲﾌﾟ 50ml | E2: 10本入仕様用 | F2: 本 | G2: =780050-G3 -> 146800 | H2: 製品 | I2: 1 | J2: 人体 | K2: 製品 | M2: =G2*L2 -> 0 | O2: 製品シート
A3: (有償)20220500015 | B3: (有償)20220500015 | C3: 発送倉庫 | D3: 万田酵素ﾄﾞﾘﾝｸ 50ml(有償支給分) | E3: 10本入仕様用 | F3: 本 | G3: 633250 | H3: 製品 | I3: 1 | J3: 人体 | K3: 製品 | M3: =G3*L3 -> 0 | O3: 製品シート | Q3: To 山田さん
A4: 20220500015 | B4: =VLOOKUP(A:A,[2]振替CD変換!B:C,2,FALSE) -> 20220500015 | C4: 通販倉庫 | D4: 万田酵素ﾄﾞﾘﾝｸﾀｲﾌﾟ 50ml | E4: 10本入仕様用 | F4: 本 | G4: 5640 | H4: 製品 | I4: 1 | J4: 人体 | K4: 製品 | M4: =G4*L4 -> 0 | O4: 製品シート | Q4: 今年、O列は製品シート、仕掛品（製品課）シートへ数字を飛ばす際に使ってません
A5: 20220500015 | B5: =VLOOKUP(A:A,[2]振替CD変換!B:C,2,FALSE) -> 20220500015 | C5: 関東倉庫 ﾌﾟﾗｽﾛｼﾞ埼玉 | D5: 万田酵素ﾄﾞﾘﾝｸﾀｲﾌﾟ 50ml | E5: 10本入仕様用 | F5: 本 | G5: 584470 | H5: 製品 | I5: 1 | J5: 人体 | K5: 製品 | M5: =G5*L5 -> 0 | O5: 製品シート | Q5: 他に使ってなければ削除でOKです
A6: 20220500015 | B6: =VLOOKUP(A:A,[2]振替CD変換!B:C,2,FALSE) -> 20220500015 | C6: JP岡山倉庫 | D6: 万田酵素ﾄﾞﾘﾝｸﾀｲﾌﾟ 50ml | E6: 10本入仕様用 | F6: 本 | G6: 393660 | H6: 製品 | I6: 1 | J6: 人体 | K6: 製品 | M6: =G6*L6 -> 0 | O6: 製品シート | Q6: 2024.6.14 宮入
A7: 20240800028 | B7: =VLOOKUP(A:A,[2]振替CD変換!B:C,2,FALSE) -> 20240800028 | C7: 発送倉庫 | D7: 万田酵素ﾄﾞﾘﾝｸ ﾌﾟﾗｽ 710ml | F7: 本 | G7: 11186 | H7: 製品 | I7: 1 | J7: 人体 | K7: 製品 | M7: =G7*L7 -> 0 | O7: 製品シート
A8: 20240800028 | B8: =VLOOKUP(A:A,[2]振替CD変換!B:C,2,FALSE) -> 20240800028 | C8: 通販倉庫 | D8: 万田酵素ﾄﾞﾘﾝｸ ﾌﾟﾗｽ 710ml | F8: 本 | G8: 22 | H8: 製品 | I8: 1 | J8: 人体 | K8: 製品 | M8: =G8*L8 -> 0 | O8: 製品シート
A9: 20240800028 | B9: =VLOOKUP(A:A,[2]振替CD変換!B:C,2,FALSE) -> 20240800028 | C9: 関東倉庫 ﾌﾟﾗｽﾛｼﾞ埼玉 | D9: 万田酵素ﾄﾞﾘﾝｸ ﾌﾟﾗｽ 710ml | F9: 本 | G9: =15327-G10 -> 2167 | H9: 製品 | I9: 1 | J9: 人体 | K9: 製品 | M9: =G9*L9 -> 0 | O9: 製品シート
A10: (有償)20240800028 | B10: (有償)20240800028 | C10: 関東倉庫 ﾌﾟﾗｽﾛｼﾞ埼玉 | D10: 万田酵素ﾄﾞﾘﾝｸ ﾌﾟﾗｽ 710ml(有償支給分) | F10: 本 | G10: 13160 | H10: 製品 | I10: 1 | J10: 人体 | K10: 製品 | M10: =G10*L10 -> 0 | O10: 製品シート
A11: 20240800028 | B11: =VLOOKUP(A:A,[2]振替CD変換!B:C,2,FALSE) -> 20240800028 | C11: JP岡山倉庫 | D11: 万田酵素ﾄﾞﾘﾝｸ ﾌﾟﾗｽ 710ml | F11: 本 | G11: 15177 | H11: 製品 | I11: 1 | J11: 人体 | K11: 製品 | M11: =G11*L11 -> 0 | O11: 製品シート
A12: 20110801125 | B12: =VLOOKUP(A:A,[2]振替CD変換!B:C,2,FALSE) -> 20110801125 | C12: 洗瓶倉庫 | D12: ｽｰﾊﾟｰ万田酵素 氣Ⅰ 瓶 検 | F12: 本 | G12: 183 | H12: 半製品 | I12: 52 | J12: 資材 | K12: 資材 | L12: =VLOOKUP(A:A,[2]資材単価マスタ202505!C:F,4,FALSE) -> 526 | M12: =G12*L12 -> 96258
A13: 20110801129 | B13: =VLOOKUP(A:A,[2]振替CD変換!B:C,2,FALSE) -> 20110801129 | C13: 洗瓶倉庫 | D13: Jﾎﾞﾄﾙ 丸型細口 1ﾘｯﾄﾙ 検 | F13: 本 | G13: 30 | H13: 半製品 | I13: 52 | J13: 資材 | K13: 資材 | L13: =VLOOKUP(A:A,[2]資材単価マスタ202505!C:F,4,FALSE) -> 130 | M13: =G13*L13 -> 3900
